Workbook

Sheet Instruction pour le projet
A2: TRAVAIL A FAIRE | G2: EVALUATION DU TRAVAIL
G3: critères | H3: Note
A4: Objectif du projet : Mettre en place un outil opérationnel permettant l’écoulement du bilan, le calcul automatisé des indicateurs de liquidité et de risque de taux, ainsi que la visualisation des analyses via un dashboard ergonomique et facilement exploitable. | G4: Compréhension du sujet | H4: 4
G5: Outil utilisé (VBA, python,…) | H5: 3
A6: plus precisement il faudrait : | G6: Design de l'interface | H6: 3
A7: 1- créer un interface utilisateur, qui permettra à l'ulisateur d'importer les inputs (les differents onglets du classeur), de faire le traitement de la donnée (les ecoulements et calcul des indicateurs) et de presenter les analyses (presenter l'analyse sur les différents indicateurs). Si possible permettre à l'utilisateur d'exporter les résultats (écoulements et analyses). | G7: Ehaustivité et Présentation des analyses | H7: 7
G8: Presenation du projet + redaction de la procedure d'utilisation de l'outil | H8: 3
A9: Les metriques à calculer sont : | G9: Total | H9: 20
A10: 1- analyse du bilan (analyse de la structure du bilan, analyse à priori de la liquidité et analyse à priori du financement)
A11: 2- le gap de liquidité statique
A12: 3 - le gap de liquidité dynamique
A13: 4 - le gap de liquidité statique stressé pour les differents scenarios de liquidité (idiosyncratique, systémique, combiné)
A14: 5 - le gap de liquidité dynamique stressé(idiosyncratique, systémique, combiné)
A15: 6 - le gap de taux fixé
A16: 7 - l'EVE à bilan statique
A17: 8 - sensibilité de l'EVE pour les differents scenarios de taux reglémentaire
A18: 9 - le SOT EVE et compoarer à 15% du Tier 1
A19: 10- la MNI à bilan constant (presenter la MNI du stock, la MNI de la nouvelle production et la MNI total)
A20: 11 - sensibilité de la MNI pour les différents scenarios de taux reglémentaire
A21: 12- le SOT MNI et comparer à 5% du tier 1
... A33: - les montant donnés sont en KEUR. Pour l'analyse il faudrait permet à l'utilisateur de les afficher en EUR (unité) ou KEUR (millier) ou MEUR (million) ou GEUR (milliard)

Sheet Bilan au 31_12_2025_BAUL
E1: E n liquidité | G1: E n taux | I1: 0 | J1: 1 | K1: 2 | L1: 3 | M1: 4 | N1: 5 | O1: 6 | P1: 7 | Q1: 8 | R1: 9 | S1: 10 | T1: 11 | U1: 12 | V1: 13 | W1: 14 | X1: 15 | Y1: 16 | Z1: 17 | AA1: 18 | AB1: 19 | AC1: 20 | AD1: 21 | AE1: 22 | AF1: 23 | AG1: 24 | AH1: 25 | AI1: 26 | AJ1: 27 | AK1: 28 | AL1: 29 | AM1: 30 | AN1: 31 | AO1: 32 | AP1: 33 | AQ1: 34 | AR1: 35 | AS1: 36 | AT1: 37 | AU1: 38 | AV1: 39 | AW1: 40 | AX1: 41 | AY1: 42 | AZ1: 43 | BA1: 44 | BB1: 45 | BC1: 46 | BD1: 47 | BE1: 48 | BF1: 49 | BG1: 50 | BH1: 51 | BI1: 52 | BJ1: 53 | BK1: 54 | BL1: 55 | BM1: 56 | BN1: 57 | BO1: 58 | BP1: 59 | BQ1: 60 | BR1: 61 | BS1: 62 | BT1: 63 | BU1: 64 | BV1: 65 | BW1: 66 | BX1: 67 | BY1: 68 | BZ1: 69 | CA1: 70 | CB1: 71 | CC1: 72 | CD1: 73 | CE1: 74 | CF1: 75 | CG1: 76 | CH1: 77 | CI1: 78 | CJ1: 79 | CK1: 80 | CL1: 81 | CM1: 82 | CN1: 83 | CO1: 84 | CP1: 85 | CQ1: 86 | CR1: 87 | CS1: 88 | CT1: 89 | CU1: 90 | CV1: 91 | CW1: 92 | CX1: 93 | CY1: 94 | CZ1: 95 | DA1: 96 | DB1: 97 | DC1: 98 | DD1: 99 | DE1: 100 | DF1: 101 | DG1: 102 | DH1: 103 | DI1: 104 | DJ1: 105 | DK1: 106 | DL1: 107 | DM1: 108 | DN1: 109 | DO1: 110 | DP1: 111 | DQ1: 112 | DR1: 113 | DS1: 114 | DT1: 115 | DU1: 116 | DV1: 117 | DW1: 118 | DX1: 119 | DY1: 120
A2: Date d’arrêté | B2: Bilan | C2: Poste du bilan | D2: Taux d'intérèt moyen | E2: Loi d'écoulement | F2: Durée moyenne (en mois) | G2: Loi d'écoulement | H2: Durée moyenne (en mois) | I2: Montant (en k€) | J2: M1 | K2: M2 | L2: M3 | M2: M4 | N2: M5 | O2: M6 | P2: M7 | Q2: M8 | R2: M9 | S2: M10 | T2: M11 | U2: M12 | V2: M13 | W2: M14 | X2: M15 | Y2: M16 | Z2: M17 | AA2: M18 | AB2: M19 | AC2: M20 | AD2: M21 | AE2: M22 | AF2: M23 | AG2: M24 | AH2: M25 | AI2: M26 | AJ2: M27 | AK2: M28 | AL2: M29 | AM2: M30 | AN2: M31 | AO2: M32 | AP2: M33 | AQ2: M34 | AR2: M35 | AS2: M36 | AT2: M37 | AU2: M38 | AV2: M39 | AW2: M40 | AX2: M41 | AY2: M42 | AZ2: M43 | BA2: M44 | BB2: M45 | BC2: M46 | BD2: M47 | BE2: M48 | BF2: M49 | BG2: M50 | BH2: M51 | BI2: M52 | BJ2: M53 | BK2: M54 | BL2: M55 | BM2: M56 | BN2: M57 | BO2: M58 | BP2: M59 | BQ2: M60 | BR2: M61 | BS2: M62 | BT2: M63 | BU2: M64 | BV2: M65 | BW2: M66 | BX2: M67 | BY2: M68 | BZ2: M69 | CA2: M70 | CB2: M71 | CC2: M72 | CD2: M73 | CE2: M74 | CF2: M75 | CG2: M76 | CH2: M77 | CI2: M78 | CJ2: M79 | CK2: M80 | CL2: M81 | CM2: M82 | CN2: M83 | CO2: M84 | CP2: M85 | CQ2: M86 | CR2: M87 | CS2: M88 | CT2: M89 | CU2: M90 | CV2: M91 | CW2: M92 | CX2: M93 | CY2: M94 | CZ2: M95 | DA2: M96 | DB2: M97 | DC2: M98 | DD2: M99 | DE2: M100 | DF2: M101 | DG2: M102 | DH2: M103 | DI2: M104 | DJ2: M105 | DK2: M106 | DL2: M107 | DM2: M108 | DN2: M109 | DO2: M110 | DP2: M111 | DQ2: M112 | DR2: M113 | DS2: M114 | DT2: M115 | DU2: M116 | DV2: M117 | DW2: M118 | DX2: M119 | DY2: M120
A3: 46022 | B3: ACTIF | C3: CAISSE, BANQUES CENTRALES | I3: 1255.124 | J3: =SUM(J4:J5) -> 1244.3264 | K3: =SUM(K4:K5) -> 1233.5288 | L3: =SUM(L4:L5) -> 1222.7312 | M3: =SUM(M4:M5) -> 1211.9336 | N3: =SUM(N4:N5) -> 1201.136 | O3: =SUM(O4:O5) -> 1190.3384 | P3: =SUM(P4:P5) -> 1179.5408 | Q3: =SUM(Q4:Q5) -> 1168.7433 | ... DY3: =SUM(DY4:DY5) -> 0
A4: 46022 | B4: ACTIF | C4: - Caisse | D4: 0 | E4: Linéaire | F4: 60 | G4: In fine | H4: 60 | I4: 40.58686 | J4: =IF(J$1<$F4,$I4*(($F4-J$1)/$F4),0) -> 39.910412 | K4: =IF(K$1<$F4,$I4*(($F4-K$1)/$F4),0) -> 39.233965 | L4: =IF(L$1<$F4,$I4*(($F4-L$1)/$F4),0) -> 38.557517 | M4: =IF(M$1<$F4,$I4*(($F4-M$1)/$F4),0) -> 37.881069 | N4: =IF(N$1<$F4,$I4*(($F4-N$1)/$F4),0) -> 37.204622 | O4: =IF(O$1<$F4,$I4*(($F4-O$1)/$F4),0) -> 36.528174 | P4: =IF(P$1<$F4,$I4*(($F4-P$1)/$F4),0) -> 35.851726 | Q4: =IF(Q$1<$F4,$I4*(($F4-Q$1)/$F4),0) -> 35.175279 | ... DY4: =IF(DY$1<$F4,$I4*(($F4-DY$1)/$F4),0) -> 0
A5: 46022 | B5: ACTIF | C5: - Compte courant BDF | D5: 0.00040572687 | E5: Linéaire | F5: 120 | G5: Ine fine | H5: 120 | I5: 1214.5371 | J5: =IF(J$1<$F5,$I5*(($F5-J$1)/$F5),0) -> 1204.416 | K5: =IF(K$1<$F5,$I5*(($F5-K$1)/$F5),0) -> 1194.2948 | L5: =IF(L$1<$F5,$I5*(($F5-L$1)/$F5),0) -> 1184.1737 | M5: =IF(M$1<$F5,$I5*(($F5-M$1)/$F5),0) -> 1174.0525 | N5: =IF(N$1<$F5,$I5*(($F5-N$1)/$F5),0) -> 1163.9314 | O5: =IF(O$1<$F5,$I5*(($F5-O$1)/$F5),0) -> 1153.8103 | P5: =IF(P$1<$F5,$I5*(($F5-P$1)/$F5),0) -> 1143.6891 | Q5: =IF(Q$1<$F5,$I5*(($F5-Q$1)/$F5),0) -> 1133.568 | ... DY5: =IF(DY$1<$F5,$I5*(($F5-DY$1)/$F5),0) -> 0
A6: 46022 | B6: ACTIF | C6: CREANCES SUR LES ETS DE CREDIT | I6: 28006.945 | J6: =SUM(J7:J8) -> 24825.899 | K6: =SUM(K7:K8) -> 21644.854 | L6: =SUM(L7:L8) -> 18463.808 | M6: =SUM(M7:M8) -> 15282.762 | N6: =SUM(N7:N8) -> 12101.717 | O6: =SUM(O7:O8) -> 8920.671 | P6: =SUM(P7:P8) -> 8920.671 | Q6: =SUM(Q7:Q8) -> 8920.671 | ... DY6: =SUM(DY7:DY8) -> 0
A7: 46022 | B7: ACTIF | C7: - A vue | D7: 0 | E7: Linéaire | F7: 6 | G7: Linéaire | H7: 6 | I7: 19086.274 | J7: =IF(J$1<$F7,$I7*(($F7-J$1)/$F7),0) -> 15905.228 | K7: =IF(K$1<$F7,$I7*(($F7-K$1)/$F7),0) -> 12724.183 | L7: =IF(L$1<$F7,$I7*(($F7-L$1)/$F7),0) -> 9543.137 | M7: =IF(M$1<$F7,$I7*(($F7-M$1)/$F7),0) -> 6362.0913 | N7: =IF(N$1<$F7,$I7*(($F7-N$1)/$F7),0) -> 3181.0457 | O7: =IF(O$1<$F7,$I7*(($F7-O$1)/$F7),0) -> 0 | P7: =IF(P$1<$F7,$I7*(($F7-P$1)/$F7),0) -> 0 | Q7: =IF(Q$1<$F7,$I7*(($F7-Q$1)/$F7),0) -> 0 | ... DY7: =IF(DY$1<$F7,$I7*(($F7-DY$1)/$F7),0) -> 0
A8: 46022 | B8: ACTIF | C8: - A terme | D8: 0.02489751 | E8: In fine | F8: 12 | G8: In fine | H8: 12 | I8: 8920.671 | J8: =IF(J$1<$F8,$I8,0) -> 8920.671 | K8: =IF(K$1<$F8,$I8,0) -> 8920.671 | L8: =IF(L$1<$F8,$I8,0) -> 8920.671 | M8: =IF(M$1<$F8,$I8,0) -> 8920.671 | N8: =IF(N$1<$F8,$I8,0) -> 8920.671 | O8: =IF(O$1<$F8,$I8,0) -> 8920.671 | P8: =IF(P$1<$F8,$I8,0) -> 8920.671 | Q8: =IF(Q$1<$F8,$I8,0) -> 8920.671 | ... DY8: =IF(DY$1<$F8,$I8,0) -> 0
A9: 46022 | B9: ACTIF | C9: CREANCES SUR LA CLIENTELE | I9: 125650.32 | J9: =SUM(J10:J12) -> 45066.509 | K9: =SUM(K10:K12) -> 40146.149 | L9: =SUM(L10:L12) -> 35212.566 | M9: =SUM(M10:M12) -> 30265.727 | N9: =SUM(N10:N12) -> 25305.594 | O9: =SUM(O10:O12) -> 20332.132 | P9: =SUM(P10:P12) -> 15345.305 | Q9: =SUM(Q10:Q12) -> 10345.078 | ... DY9: =SUM(DY10:DY12) -> 0
A10: 46022 | B10: ACTIF | C10: - Créances commerciales | D10: 0.048443032 | E10: Constant | F10: 60 | G10: Constant | H10: 60 | I10: 358.117 | J10: =IF(J$1<$F10,(I10*(1+($D10/12)))-(-PMT($D10/12,$F10,$I10)),0) -> 352.8301 | K10: =IF(K$1<$F10,(J10*(1+($D10/12)))-(-PMT($D10/12,$F10,$I10)),0) -> 347.52185 | L10: =IF(L$1<$F10,(K10*(1+($D10/12)))-(-PMT($D10/12,$F10,$I10)),0) -> 342.19217 | M10: =IF(M$1<$F10,(L10*(1+($D10/12)))-(-PMT($D10/12,$F10,$I10)),0) -> 336.84098 | N10: =IF(N$1<$F10,(M10*(1+($D10/12)))-(-PMT($D10/12,$F10,$I10)),0) -> 331.46818 | O10: =IF(O$1<$F10,(N10*(1+($D10/12)))-(-PMT($D10/12,$F10,$I10)),0) -> 326.0737 | P10: =IF(P$1<$F10,(O10*(1+($D10/12)))-(-PMT($D10/12,$F10,$I10)),0) -> 320.65744 | Q10: =IF(Q$1<$F10,(P10*(1+($D10/12)))-(-PMT($D10/12,$F10,$I10)),0) -> 315.21931 | ... DY10: =IF(DY$1<$F10,(DX10*(1+($D10/12)))-(-PMT($D10/12,$F10,$I10)),0) -> 0
A11: 46022 | B11: ACTIF | C11: - Autres concours à la clientèle | D11: 0.032228873 | E11: Constant | F11: 10 | G11: Constant | H11: 10 | I11: 49615.566 | J11: =IF(J$1<$F11,(I11*(1+($D11/12)))-(-PMT($D11/12,$F11,$I11)),0) -> 44713.679 | K11: =IF(K$1<$F11,(J11*(1+($D11/12)))-(-PMT($D11/12,$F11,$I11)),0) -> 39798.627 | L11: =IF(L$1<$F11,(K11*(1+($D11/12)))-(-PMT($D11/12,$F11,$I11)),0) -> 34870.374 | M11: =IF(M$1<$F11,(L11*(1+($D11/12)))-(-PMT($D11/12,$F11,$I11)),0) -> 29928.886 | N11: =IF(N$1<$F11,(M11*(1+($D11/12)))-(-PMT($D11/12,$F11,$I11)),0) -> 24974.125 | O11: =IF(O$1<$F11,(N11*(1+($D11/12)))-(-PMT($D11/12,$F11,$I11)),0) -> 20006.058 | P11: =IF(P$1<$F11,(O11*(1+($D11/12)))-(-PMT($D11/12,$F11,$I11)),0) -> 15024.648 | Q11: =IF(Q$1<$F11,(P11*(1+($D11/12)))-(-PMT($D11/12,$F11,$I11)),0) -> 10029.858 | ... DY11: =IF(DY$1<$F11,(DX11*(1+($D11/12)))-(-PMT($D11/12,$F11,$I11)),0) -> 0
A12: 46022 | B12: ACTIF | C12: - Comptes ordinaires débiteurs | D12: 0.039912213 | E12: In fine | F12: 1 | G12: In fine | H12: 1 | I12: 75676.636 | J12: =IF(J$1<$F12,$I12,0) -> 0 | K12: =IF(K$1<$F12,$I12,0) -> 0 | L12: =IF(L$1<$F12,$I12,0) -> 0 | M12: =IF(M$1<$F12,$I12,0) -> 0 | N12: =IF(N$1<$F12,$I12,0) -> 0 | O12: =IF(O$1<$F12,$I12,0) -> 0 | P12: =IF(P$1<$F12,$I12,0) -> 0 | Q12: =IF(Q$1<$F12,$I12,0) -> 0 | ... DY12: =IF(DY$1<$F12,$I12,0) -> 0
A13: 46022 | B13: ACTIF | C13: Investissements financiers | D13: 0.05 | E13: Ine fine | F13: 84 | G13: Ine fine | H13: 84 | I13: 28 | J13: =IF(J$1<$F13,$I13,0) -> 28 | K13: =IF(K$1<$F13,$I13,0) -> 28 | L13: =IF(L$1<$F13,$I13,0) -> 28 | M13: =IF(M$1<$F13,$I13,0) -> 28 | N13: =IF(N$1<$F13,$I13,0) -> 28 | O13: =IF(O$1<$F13,$I13,0) -> 28 | P13: =IF(P$1<$F13,$I13,0) -> 28 | Q13: =IF(Q$1<$F13,$I13,0) -> 28 | ... DY13: =IF(DY$1<$F13,$I13,0) -> 0
A14: 46022 | B14: ACTIF | C14: Immobilisations corporelles et incorporelles | E14: Linéaire | F14: 120 | G14: Linéaire | H14: 120 | I14: 82 | J14: =IF(J$1<$F14,$I14*(($F14-J$1)/$F14),0) -> 81.316667 | K14: =IF(K$1<$F14,$I14*(($F14-K$1)/$F14),0) -> 80.633333 | L14: =IF(L$1<$F14,$I14*(($F14-L$1)/$F14),0) -> 79.95 | M14: =IF(M$1<$F14,$I14*(($F14-M$1)/$F14),0) -> 79.266667 | N14: =IF(N$1<$F14,$I14*(($F14-N$1)/$F14),0) -> 78.583333 | O14: =IF(O$1<$F14,$I14*(($F14-O$1)/$F14),0) -> 77.9 | P14: =IF(P$1<$F14,$I14*(($F14-P$1)/$F14),0) -> 77.216667 | Q14: =IF(Q$1<$F14,$I14*(($F14-Q$1)/$F14),0) -> 76.533333 | ... DY14: =IF(DY$1<$F14,$I14*(($F14-DY$1)/$F14),0) -> 0
A15: 46022 | B15: ACTIF | C15: Autres actifs | E15: Linéaire | F15: 120 | G15: Linéaire | H15: 120 | I15: 570 | J15: =IF(J$1<$F15,$I15*(($F15-J$1)/$F15),0) -> 565.25 | K15: =IF(K$1<$F15,$I15*(($F15-K$1)/$F15),0) -> 560.5 | L15: =IF(L$1<$F15,$I15*(($F15-L$1)/$F15),0) -> 555.75 | M15: =IF(M$1<$F15,$I15*(($F15-M$1)/$F15),0) -> 551 | N15: =IF(N$1<$F15,$I15*(($F15-N$1)/$F15),0) -> 546.25 | O15: =IF(O$1<$F15,$I15*(($F15-O$1)/$F15),0) -> 541.5 | P15: =IF(P$1<$F15,$I15*(($F15-P$1)/$F15),0) -> 536.75 | Q15: =IF(Q$1<$F15,$I15*(($F15-Q$1)/$F15),0) -> 532 | ... DY15: =IF(DY$1<$F15,$I15*(($F15-DY$1)/$F15),0) -> 0
A16: 46022 | B16: ACTIF | C16: Total actif | I16: =I3+I6+I9+I13+I14+I15 -> 155592.39 | J16: =J3+J6+J9+SUM(J13:J15) -> 71811.302 | K16: =K3+K6+K9+SUM(K13:K15) -> 63693.665 | L16: =L3+L6+L9+SUM(L13:L15) -> 55562.806 | M16: =M3+M6+M9+SUM(M13:M15) -> 47418.689 | N16: =N3+N6+N9+SUM(N13:N15) -> 39261.28 | O16: =O3+O6+O9+SUM(O13:O15) -> 31090.541 | P16: =P3+P6+P9+SUM(P13:P15) -> 26087.483 | Q16: =Q3+Q6+Q9+SUM(Q13:Q15) -> 21071.025 | ... DY16: =DY3+DY6+DY9+SUM(DY13:DY15) -> 0
A17: 46022 | B17: PASSIF | C17: DETTES ENVERS ETS DE CREDIT | I17: =I18+I19 -> 74095.3 | J17: =SUM(J18:J19) -> 73528.24 | K17: =SUM(K18:K19) -> 73150.2 | L17: =SUM(L18:L19) -> 72772.16 | M17: =SUM(M18:M19) -> 72394.12 | N17: =SUM(N18:N19) -> 72205.1 | O17: =SUM(O18:O19) -> 72205.1 | P17: =SUM(P18:P19) -> 72205.1 | Q17: =SUM(Q18:Q19) -> 72205.1 | ... DY17: =SUM(DY18:DY19) -> 0
A18: 46022 | B18: PASSIF | C18: - A vue | D18: 0 | E18: 90%-20%*t, t<=4mois | F18: 4 | G18: In fine | H18: 4 | I18: 1890.2 | J18: =IF(J$1<=$F18,$I18*(90%-(20%*J$1)),0) -> 1323.14 | K18: =IF(K$1<=$F18,$I18*(90%-(20%*K$1)),0) -> 945.1 | L18: =IF(L$1<=$F18,$I18*(90%-(20%*L$1)),0) -> 567.06 | M18: =IF(M$1<=$F18,$I18*(90%-(20%*M$1)),0) -> 189.02 | N18: =IF(N$1<=$F18,$I18*(90%-(20%*N$1)),0) -> 0 | O18: =IF(O$1<=$F18,$I18*(90%-(20%*O$1)),0) -> 0 | P18: =IF(P$1<=$F18,$I18*(90%-(20%*P$1)),0) -> 0 | Q18: =IF(Q$1<=$F18,$I18*(90%-(20%*Q$1)),0) -> 0 | ... DY18: =IF(DY$1<=$F18,$I18*(90%-(20%*DY$1)),0) -> 0
A19: 46022 | B19: PASSIF | C19: - A terme | D19: 0.0138965 | E19: Ine fine | F19: 24 | G19: Ine fine | H19: 24 | I19: 72205.1 | J19: =IF(J$1<$F19,$I19,0) -> 72205.1 | K19: =IF(K$1<$F19,$I19,0) -> 72205.1 | L19: =IF(L$1<$F19,$I19,0) -> 72205.1 | M19: =IF(M$1<$F19,$I19,0) -> 72205.1 | N19: =IF(N$1<$F19,$I19,0) -> 72205.1 | O19: =IF(O$1<$F19,$I19,0) -> 72205.1 | P19: =IF(P$1<$F19,$I19,0) -> 72205.1 | Q19: =IF(Q$1<$F19,$I19,0) -> 72205.1 | ... DY19: =IF(DY$1<$F19,$I19,0) -> 0
A20: 46022 | B20: PASSIF | C20: CPTES CREDITEURS DE LA CLIENTELE | I20: 50161.059 | J20: =SUM(J21:J22) -> 43848.513 | K20: =SUM(K21:K22) -> 40644.299 | L20: =SUM(L21:L22) -> 38020.91 | M20: =SUM(M21:M22) -> 35873.06 | N20: =SUM(N21:N22) -> 34114.55 | O20: =SUM(O21:O22) -> 32674.804 | P20: =SUM(P21:P22) -> 31496.039 | Q20: =SUM(Q21:Q22) -> 30530.948 | ... DY20: =SUM(DY21:DY22) -> 8.1505852e-07
A21: 46022 | B21: PASSIF | C21: - A vue | D21: 0 | E21: 90%*exp(-20%*t), t<=120 mois | F21: 120 | G21: Linéaire | H21: 120 | I21: 23989.094 | J21: =IF(J$1<=$F21,$I21*(90%*EXP(-20%*J$1)),0) -> 17676.548 | K21: =IF(K$1<=$F21,$I21*(90%*EXP(-20%*K$1)),0) -> 14472.334 | L21: =IF(L$1<=$F21,$I21*(90%*EXP(-20%*L$1)),0) -> 11848.945 | M21: =IF(M$1<=$F21,$I21*(90%*EXP(-20%*M$1)),0) -> 9701.0953 | N21: =IF(N$1<=$F21,$I21*(90%*EXP(-20%*N$1)),0) -> 7942.585 | O21: =IF(O$1<=$F21,$I21*(90%*EXP(-20%*O$1)),0) -> 6502.8386 | P21: =IF(P$1<=$F21,$I21*(90%*EXP(-20%*P$1)),0) -> 5324.074 | Q21: =IF(Q$1<=$F21,$I21*(90%*EXP(-20%*Q$1)),0) -> 4358.9831 | ... DY21: =IF(DY$1<=$F21,$I21*(90%*EXP(-20%*DY$1)),0) -> 8.1505852e-07
A22: 46022 | B22: PASSIF | C22: - A terme | D22: 0.0083386457 | E22: In fine | F22: 60 | G22: In fine | H22: 60 | I22: 26171.965 | J22: =IF(J$1<$F22,$I22,0) -> 26171.965 | K22: =IF(K$1<$F22,$I22,0) -> 26171.965 | L22: =IF(L$1<$F22,$I22,0) -> 26171.965 | M22: =IF(M$1<$F22,$I22,0) -> 26171.965 | N22: =IF(N$1<$F22,$I22,0) -> 26171.965 | O22: =IF(O$1<$F22,$I22,0) -> 26171.965 | P22: =IF(P$1<$F22,$I22,0) -> 26171.965 | Q22: =IF(Q$1<$F22,$I22,0) -> 26171.965 | ... DY22: =IF(DY$1<$F22,$I22,0) -> 0
A23: 46022 | B23: PASSIF | C23: Autres passifs | D23: 0 | E23: Linéaire | F23: 120 | G23: Linéaire | H23: 120 | I23: 2297.337 | J23: =IF(J$1<$F23,$I23*(($F23-J$1)/$F23),0) -> 2278.1925 | K23: =IF(K$1<$F23,$I23*(($F23-K$1)/$F23),0) -> 2259.048 | L23: =IF(L$1<$F23,$I23*(($F23-L$1)/$F23),0) -> 2239.9036 | M23: =IF(M$1<$F23,$I23*(($F23-M$1)/$F23),0) -> 2220.7591 | N23: =IF(N$1<$F23,$I23*(($F23-N$1)/$F23),0) -> 2201.6146 | O23: =IF(O$1<$F23,$I23*(($F23-O$1)/$F23),0) -> 2182.4702 | P23: =IF(P$1<$F23,$I23*(($F23-P$1)/$F23),0) -> 2163.3257 | Q23: =IF(Q$1<$F23,$I23*(($F23-Q$1)/$F23),0) -> 2144.1812 | ... DY23: =IF(DY$1<$F23,$I23*(($F23-DY$1)/$F23),0) -> 0
A24: 46022 | B24: PASSIF | C24: Provisions pour risques et charges | D24: 0 | E24: Linéaire | F24: 120 | G24: Linéaire | H24: 120 | I24: 2994.787 | J24: =IF(J$1<$F24,$I24*(($F24-J$1)/$F24),0) -> 2969.8304 | K24: =IF(K$1<$F24,$I24*(($F24-K$1)/$F24),0) -> 2944.8739 | L24: =IF(L$1<$F24,$I24*(($F24-L$1)/$F24),0) -> 2919.9173 | M24: =IF(M$1<$F24,$I24*(($F24-M$1)/$F24),0) -> 2894.9608 | N24: =IF(N$1<$F24,$I24*(($F24-N$1)/$F24),0) -> 2870.0042 | O24: =IF(O$1<$F24,$I24*(($F24-O$1)/$F24),0) -> 2845.0476 | P24: =IF(P$1<$F24,$I24*(($F24-P$1)/$F24),0) -> 2820.0911 | Q24: =IF(Q$1<$F24,$I24*(($F24-Q$1)/$F24),0) -> 2795.1345 | ... DY24: =IF(DY$1<$F24,$I24*(($F24-DY$1)/$F24),0) -> 0
A25: 46022 | B25: PASSIF | C25: Financement LT | D25: 0.035 | E25: In fine | F25: 72 | G25: In fine | H25: 72 | I25: 130 | J25: =IF(J$1<$F25,$I25,0) -> 130 | K25: =IF(K$1<$F25,$I25,0) -> 130 | L25: =IF(L$1<$F25,$I25,0) -> 130 | M25: =IF(M$1<$F25,$I25,0) -> 130 | N25: =IF(N$1<$F25,$I25,0) -> 130 | O25: =IF(O$1<$F25,$I25,0) -> 130 | P25: =IF(P$1<$F25,$I25,0) -> 130 | Q25: =IF(Q$1<$F25,$I25,0) -> 130 | ... DY25: =IF(DY$1<$F25,$I25,0) -> 0
A26: 46022 | B26: PASSIF | C26: Capitaux propres | I26: 25913.849 | J26: =SUM(J27:J33) -> 25697.9 | K26: =SUM(K27:K33) -> 25481.952 | L26: =SUM(L27:L33) -> 25266.003 | M26: =SUM(M27:M33) -> 25050.054 | N26: =SUM(N27:N33) -> 24834.105 | O26: =SUM(O27:O33) -> 24618.157 | P26: =SUM(P27:P33) -> 24402.208 | Q26: =SUM(Q27:Q33) -> 24186.259 | ... DY26: =SUM(DY27:DY33) -> 0
A27: 46022 | B27: PASSIF | C27: FRBG | D27: 0 | E27: Linéaire | F27: 120 | G27: Linéaire | H27: 120 | I27: 476.541 | J27: =IF(J$1<$F27,$I27*(($F27-J$1)/$F27),0) -> 472.56983 | K27: =IF(K$1<$F27,$I27*(($F27-K$1)/$F27),0) -> 468.59865 | L27: =IF(L$1<$F27,$I27*(($F27-L$1)/$F27),0) -> 464.62748 | M27: =IF(M$1<$F27,$I27*(($F27-M$1)/$F27),0) -> 460.6563 | N27: =IF(N$1<$F27,$I27*(($F27-N$1)/$F27),0) -> 456.68513 | O27: =IF(O$1<$F27,$I27*(($F27-O$1)/$F27),0) -> 452.71395 | P27: =IF(P$1<$F27,$I27*(($F27-P$1)/$F27),0) -> 448.74277 | Q27: =IF(Q$1<$F27,$I27*(($F27-Q$1)/$F27),0) -> 444.7716 | ... DY27: =IF(DY$1<$F27,$I27*(($F27-DY$1)/$F27),0) -> 0
A28: 46022 | B28: PASSIF | C28: Capital souscrit | D28: 0 | E28: Linéaire | F28: 120 | G28: Linéaire | H28: 120 | I28: 18000.179 | J28: =IF(J$1<$F28,$I28*(($F28-J$1)/$F28),0) -> 17850.178 | K28: =IF(K$1<$F28,$I28*(($F28-K$1)/$F28),0) -> 17700.176 | L28: =IF(L$1<$F28,$I28*(($F28-L$1)/$F28),0) -> 17550.175 | M28: =IF(M$1<$F28,$I28*(($F28-M$1)/$F28),0) -> 17400.173 | N28: =IF(N$1<$F28,$I28*(($F28-N$1)/$F28),0) -> 17250.172 | O28: =IF(O$1<$F28,$I28*(($F28-O$1)/$F28),0) -> 17100.17 | P28: =IF(P$1<$F28,$I28*(($F28-P$1)/$F28),0) -> 16950.169 | Q28: =IF(Q$1<$F28,$I28*(($F28-Q$1)/$F28),0) -> 16800.167 | ... DY28: =IF(DY$1<$F28,$I28*(($F28-DY$1)/$F28),0) -> 0
A29: 46022 | B29: PASSIF | C29: Prime d'émission | D29: 0 | E29: Linéaire | F29: 120 | G29: Linéaire | H29: 120 | I29: 2.22 | J29: =IF(J$1<$F29,$I29*(($F29-J$1)/$F29),0) -> 2.2015 | K29: =IF(K$1<$F29,$I29*(($F29-K$1)/$F29),0) -> 2.183 | L29: =IF(L$1<$F29,$I29*(($F29-L$1)/$F29),0) -> 2.1645 | M29: =IF(M$1<$F29,$I29*(($F29-M$1)/$F29),0) -> 2.146 | N29: =IF(N$1<$F29,$I29*(($F29-N$1)/$F29),0) -> 2.1275 | O29: =IF(O$1<$F29,$I29*(($F29-O$1)/$F29),0) -> 2.109 | P29: =IF(P$1<$F29,$I29*(($F29-P$1)/$F29),0) -> 2.0905 | Q29: =IF(Q$1<$F29,$I29*(($F29-Q$1)/$F29),0) -> 2.072 | ... DY29: =IF(DY$1<$F29,$I29*(($F29-DY$1)/$F29),0) -> 0
A30: 46022 | B30: PASSIF | C30: Réserves | D30: 0 | E30: Linéaire | F30: 120 | G30: Linéaire | H30: 120 | I30: 429.975 | J30: =IF(J$1<$F30,$I30*(($F30-J$1)/$F30),0) -> 426.39188 | K30: =IF(K$1<$F30,$I30*(($F30-K$1)/$F30),0) -> 422.80875 | L30: =IF(L$1<$F30,$I30*(($F30-L$1)/$F30),0) -> 419.22563 | M30: =IF(M$1<$F30,$I30*(($F30-M$1)/$F30),0) -> 415.6425 | N30: =IF(N$1<$F30,$I30*(($F30-N$1)/$F30),0) -> 412.05938 | O30: =IF(O$1<$F30,$I30*(($F30-O$1)/$F30),0) -> 408.47625 | P30: =IF(P$1<$F30,$I30*(($F30-P$1)/$F30),0) -> 404.89312 | Q30: =IF(Q$1<$F30,$I30*(($F30-Q$1)/$F30),0) -> 401.31 | ... DY30: =IF(DY$1<$F30,$I30*(($F30-DY$1)/$F30),0) -> 0
A31: 46022 | B31: PASSIF | C31: Report à nouveau | D31: 0 | E31: Linéaire | F31: 120 | G31: Linéaire | H31: 120 | I31: 7004.934 | J31: =IF(J$1<$F31,$I31*(($F31-J$1)/$F31),0) -> 6946.5596 | K31: =IF(K$1<$F31,$I31*(($F31-K$1)/$F31),0) -> 6888.1851 | L31: =IF(L$1<$F31,$I31*(($F31-L$1)/$F31),0) -> 6829.8107 | M31: =IF(M$1<$F31,$I31*(($F31-M$1)/$F31),0) -> 6771.4362 | N31: =IF(N$1<$F31,$I31*(($F31-N$1)/$F31),0) -> 6713.0618 | O31: =IF(O$1<$F31,$I31*(($F31-O$1)/$F31),0) -> 6654.6873 | P31: =IF(P$1<$F31,$I31*(($F31-P$1)/$F31),0) -> 6596.3129 | Q31: =IF(Q$1<$F31,$I31*(($F31-Q$1)/$F31),0) -> 6537.9384 | ... DY31: =IF(DY$1<$F31,$I31*(($F31-DY$1)/$F31),0) -> 0
A32: 46022 | B32: PASSIF | C32: Résultat de l'exercice | D32: 0 | E32: Linéaire | F32: 120 | G32: Linéaire | H32: 120 | I32: 0 | J32: =IF(J$1<$F32,$I32*(($F32-J$1)/$F32),0) -> 0 | K32: =IF(K$1<$F32,$I32*(($F32-K$1)/$F32),0) -> 0 | L32: =IF(L$1<$F32,$I32*(($F32-L$1)/$F32),0) -> 0 | M32: =IF(M$1<$F32,$I32*(($F32-M$1)/$F32),0) -> 0 | N32: =IF(N$1<$F32,$I32*(($F32-N$1)/$F32),0) -> 0 | O32: =IF(O$1<$F32,$I32*(($F32-O$1)/$F32),0) -> 0 | P32: =IF(P$1<$F32,$I32*(($F32-P$1)/$F32),0) -> 0 | Q32: =IF(Q$1<$F32,$I32*(($F32-Q$1)/$F32),0) -> 0 | ... DY32: =IF(DY$1<$F32,$I32*(($F32-DY$1)/$F32),0) -> 0
A33: 46022 | B33: PASSIF | C33: Dividende | D33: 0 | E33: Linéaire | F33: 120 | G33: Linéaire | H33: 120 | I33: 0 | J33: =IF(J$1<$F33,$I33*(($F33-J$1)/$F33),0) -> 0 | K33: =IF(K$1<$F33,$I33*(($F33-K$1)/$F33),0) -> 0 | L33: =IF(L$1<$F33,$I33*(($F33-L$1)/$F33),0) -> 0 | M33: =IF(M$1<$F33,$I33*(($F33-M$1)/$F33),0) -> 0 | N33: =IF(N$1<$F33,$I33*(($F33-N$1)/$F33),0) -> 0 | O33: =IF(O$1<$F33,$I33*(($F33-O$1)/$F33),0) -> 0 | P33: =IF(P$1<$F33,$I33*(($F33-P$1)/$F33),0) -> 0 | Q33: =IF(Q$1<$F33,$I33*(($F33-Q$1)/$F33),0) -> 0 | ... DY33: =IF(DY$1<$F33,$I33*(($F33-DY$1)/$F33),0) -> 0
A34: 46022 | B34: PASSIF | C34: Total passif | I34: =I26+I24+I23+I20+I17+I25 -> 155592.33 | J34: =J17+J20+SUM(J23:J26) -> 148452.68 | K34: =K17+K20+SUM(K23:K26) -> 144610.37 | L34: =L17+L20+SUM(L23:L26) -> 141348.89 | M34: =M17+M20+SUM(M23:M26) -> 138562.95 | N34: =N17+N20+SUM(N23:N26) -> 136355.37 | O34: =O17+O20+SUM(O23:O26) -> 134655.58 | P34: =P17+P20+SUM(P23:P26) -> 133216.76 | Q34: =Q17+Q20+SUM(Q23:Q26) -> 131991.62 | ... DY34: =DY17+DY20+SUM(DY23:DY26) -> 8.1505852e-07
A35: Gap de liquidité statique | G35: =G33-G22 -> #VALUE! | H35: =H33-H22 -> 60 | I35: =I34-I16 -> -0.05598 | J35: =J34-J16 -> 76641.375 | K35: =K34-K16 -> 80916.707 | L35: =L34-L16 -> 85786.088 | M35: =M34-M16 -> 91144.265 | N35: =N34-N16 -> 97094.095 | O35: =O34-O16 -> 103565.04 | P35: =P34-P16 -> 107129.28 | ... DY35: =DY34-DY16 -> 8.1505852e-07
A39: 3) Analyse de la structure de la banque | B39: Ratio | C39: Valeurs
B40: CREANCES SUR LA CLIENTELE/Total Actifs | C40: =I9/I16 -> 0.80756084 | H40: s
B41: CREANCES SUR LES ETS DE CREDIT /Total Actifs | C41: =I6/I16 -> 0.18000203
B42: Investissements financiers / Total Actifs | C42: =I13/I16 -> 0.00017995739
B43: CPTES CREDITEURS DE LA CLIENTELE/ Total Passifs | C43: =I20/I34 -> 0.32238773
B44: DETTES ENVERS ETS DE CREDIT/ Total Passifs | C44: =I17/I34 -> 0.47621434
A46: Analyse a priori de la liquidité | B46: Ratio | C46: Valeurs
B47: CREANCES SUR LA CLIENTELE/CPTES CREDITEURS DE LA CLIENTELE | C47: =I9/I20 -> 2.5049375
B48: HQLA/ Total actifs | C48: =(I3+I13)/I16 -> 0.0082467015
B49: HQLA/ CPTES CREDITEURS DE LA CLIENTELE | C49: =(I3+I13)/I20 -> 0.025580082
A51: Analyse du financement | B51: Ratio | C51: Valeurs
B52: DETTES ENVERS ETS DE CREDIT/ Total Passifs | C52: =I17/I34 -> 0.47621434
B53: CPTES CREDITEURS DE LA CLIENTELE_AV/ CPTES CREDITEURS DE LA CLIENTELE | C53: =I21/I20 -> 0.47824138
B54: CPTES CREDITEURS DE LA CLIENTELE_AT/ TCPTES CREDITEURS DE LA CLIENTELE | C54: =I22/I20 -> 0.52175862
C58: *ETS : Etablissement
C59: *FRBG : Fonds pour Risques Bancaires Généraux

Sheet Bilan au 31_12_2025_BAU T
E1: E n liquidité | G1: E n taux | I1: 0 | J1: 1 | K1: 2 | L1: 3 | M1: 4 | N1: 5 | O1: 6 | P1: 7 | Q1: 8 | R1: 9 | S1: 10 | T1: 11 | U1: 12 | V1: 13 | W1: 14 | X1: 15 | Y1: 16 | Z1: 17 | AA1: 18 | AB1: 19 | AC1: 20 | AD1: 21 | AE1: 22 | AF1: 23 | AG1: 24 | AH1: 25 | AI1: 26 | AJ1: 27 | AK1: 28 | AL1: 29 | AM1: 30 | AN1: 31 | AO1: 32 | AP1: 33 | AQ1: 34 | AR1: 35 | AS1: 36 | AT1: 37 | AU1: 38 | AV1: 39 | AW1: 40 | AX1: 41 | AY1: 42 | AZ1: 43 | BA1: 44 | BB1: 45 | BC1: 46 | BD1: 47 | BE1: 48 | BF1: 49 | BG1: 50 | BH1: 51 | BI1: 52 | BJ1: 53 | BK1: 54 | BL1: 55 | BM1: 56 | BN1: 57 | BO1: 58 | BP1: 59 | BQ1: 60 | BR1: 61 | BS1: 62 | BT1: 63 | BU1: 64 | BV1: 65 | BW1: 66 | BX1: 67 | BY1: 68 | BZ1: 69 | CA1: 70 | CB1: 71 | CC1: 72 | CD1: 73 | CE1: 74 | CF1: 75 | CG1: 76 | CH1: 77 | CI1: 78 | CJ1: 79 | CK1: 80 | CL1: 81 | CM1: 82 | CN1: 83 | CO1: 84 | CP1: 85 | CQ1: 86 | CR1: 87 | CS1: 88 | CT1: 89 | CU1: 90 | CV1: 91 | CW1: 92 | CX1: 93 | CY1: 94 | CZ1: 95 | DA1: 96 | DB1: 97 | DC1: 98 | DD1: 99 | DE1: 100 | DF1: 101 | DG1: 102 | DH1: 103 | DI1: 104 | DJ1: 105 | DK1: 106 | DL1: 107 | DM1: 108 | DN1: 109 | DO1: 110 | DP1: 111 | DQ1: 112 | DR1: 113 | DS1: 114 | DT1: 115 | DU1: 116 | DV1: 117 | DW1: 118 | DX1: 119 | DY1: 120
A2: Date d’arrêté | B2: Bilan | C2: Poste du bilan | D2: Taux d'intérèt moyen | E2: Loi d'écoulement | F2: Durée moyenne (en mois) | G2: Loi d'écoulement | H2: Durée moyenne (en mois) | I2: Montant (en k€) | J2: M1 | K2: M2 | L2: M3 | M2: M4 | N2: M5 | O2: M6 | P2: M7 | Q2: M8 | R2: M9 | S2: M10 | T2: M11 | U2: M12 | V2: M13 | W2: M14 | X2: M15 | Y2: M16 | Z2: M17 | AA2: M18 | AB2: M19 | AC2: M20 | AD2: M21 | AE2: M22 | AF2: M23 | AG2: M24 | AH2: M25 | AI2: M26 | AJ2: M27 | AK2: M28 | AL2: M29 | AM2: M30 | AN2: M31 | AO2: M32 | AP2: M33 | AQ2: M34 | AR2: M35 | AS2: M36 | AT2: M37 | AU2: M38 | AV2: M39 | AW2: M40 | AX2: M41 | AY2: M42 | AZ2: M43 | BA2: M44 | BB2: M45 | BC2: M46 | BD2: M47 | BE2: M48 | BF2: M49 | BG2: M50 | BH2: M51 | BI2: M52 | BJ2: M53 | BK2: M54 | BL2: M55 | BM2: M56 | BN2: M57 | BO2: M58 | BP2: M59 | BQ2: M60 | BR2: M61 | BS2: M62 | BT2: M63 | BU2: M64 | BV2: M65 | BW2: M66 | BX2: M67 | BY2: M68 | BZ2: M69 | CA2: M70 | CB2: M71 | CC2: M72 | CD2: M73 | CE2: M74 | CF2: M75 | CG2: M76 | CH2: M77 | CI2: M78 | CJ2: M79 | CK2: M80 | CL2: M81 | CM2: M82 | CN2: M83 | CO2: M84 | CP2: M85 | CQ2: M86 | CR2: M87 | CS2: M88 | CT2: M89 | CU2: M90 | CV2: M91 | CW2: M92 | CX2: M93 | CY2: M94 | CZ2: M95 | DA2: M96 | DB2: M97 | DC2: M98 | DD2: M99 | DE2: M100 | DF2: M101 | DG2: M102 | DH2: M103 | DI2: M104 | DJ2: M105 | DK2: M106 | DL2: M107 | DM2: M108 | DN2: M109 | DO2: M110 | DP2: M111 | DQ2: M112 | DR2: M113 | DS2: M114 | DT2: M115 | DU2: M116 | DV2: M117 | DW2: M118 | DX2: M119 | DY2: M120
A3: 46022 | B3: ACTIF | C3: CAISSE, BANQUES CENTRALES | I3: 1255.124 | J3: =SUM(J4:J5) -> 1255.124 | K3: =SUM(K4:K5) -> 1255.124 | L3: =SUM(L4:L5) -> 1255.124 | M3: =SUM(M4:M5) -> 1255.124 | N3: =SUM(N4:N5) -> 1255.124 | O3: =SUM(O4:O5) -> 1255.124 | P3: =SUM(P4:P5) -> 1255.124 | Q3: =SUM(Q4:Q5) -> 1255.124 | ... DY3: =SUM(DY4:DY5) -> 0
A4: 46022 | B4: ACTIF | C4: - Caisse | D4: 0 | E4: Linéaire | F4: 60 | G4: In fine | H4: 60 | I4: 40.58686 | J4: =IF(J$1<$F4,$I4,0) -> 40.58686 | K4: =IF(K$1<$F4,$I4,0) -> 40.58686 | L4: =IF(L$1<$F4,$I4,0) -> 40.58686 | M4: =IF(M$1<$F4,$I4,0) -> 40.58686 | N4: =IF(N$1<$F4,$I4,0) -> 40.58686 | O4: =IF(O$1<$F4,$I4,0) -> 40.58686 | P4: =IF(P$1<$F4,$I4,0) -> 40.58686 | Q4: =IF(Q$1<$F4,$I4,0) -> 40.58686 | ... DY4: =IF(DY$1<$F4,$I4,0) -> 0
A5: 46022 | B5: ACTIF | C5: - Compte courant BDF | D5: 0.00040572687 | E5: Linéaire | F5: 120 | G5: Ine fine | H5: 120 | I5: 1214.5371 | J5: =IF(J$1<$F5,$I5,0) -> 1214.5371 | K5: =IF(K$1<$F5,$I5,0) -> 1214.5371 | L5: =IF(L$1<$F5,$I5,0) -> 1214.5371 | M5: =IF(M$1<$F5,$I5,0) -> 1214.5371 | N5: =IF(N$1<$F5,$I5,0) -> 1214.5371 | O5: =IF(O$1<$F5,$I5,0) -> 1214.5371 | P5: =IF(P$1<$F5,$I5,0) -> 1214.5371 | Q5: =IF(Q$1<$F5,$I5,0) -> 1214.5371 | ... DY5: =IF(DY$1<$F5,$I5,0) -> 0
A6: 46022 | B6: ACTIF | C6: CREANCES SUR LES ETS DE CREDIT | I6: 28006.945 | J6: =SUM(J7:J8) -> 24825.899 | K6: =SUM(K7:K8) -> 21644.854 | L6: =SUM(L7:L8) -> 18463.808 | M6: =SUM(M7:M8) -> 15282.762 | N6: =SUM(N7:N8) -> 12101.717 | O6: =SUM(O7:O8) -> 8920.671 | P6: =SUM(P7:P8) -> 8920.671 | Q6: =SUM(Q7:Q8) -> 8920.671 | ... DY6: =SUM(DY7:DY8) -> 0
A7: 46022 | B7: ACTIF | C7: - A vue | D7: 0 | E7: Linéaire | F7: 6 | G7: Linéaire | H7: 6 | I7: 19086.274 | J7: =IF(J$1<$F7,$I7*(($F7-J$1)/$F7),0) -> 15905.228 | K7: =IF(K$1<$F7,$I7*(($F7-K$1)/$F7),0) -> 12724.183 | L7: =IF(L$1<$F7,$I7*(($F7-L$1)/$F7),0) -> 9543.137 | M7: =IF(M$1<$F7,$I7*(($F7-M$1)/$F7),0) -> 6362.0913 | N7: =IF(N$1<$F7,$I7*(($F7-N$1)/$F7),0) -> 3181.0457 | O7: =IF(O$1<$F7,$I7*(($F7-O$1)/$F7),0) -> 0 | P7: =IF(P$1<$F7,$I7*(($F7-P$1)/$F7),0) -> 0 | Q7: =IF(Q$1<$F7,$I7*(($F7-Q$1)/$F7),0) -> 0 | ... DY7: =IF(DY$1<$F7,$I7*(($F7-DY$1)/$F7),0) -> 0
A8: 46022 | B8: ACTIF | C8: - A terme | D8: 0.02489751 | E8: In fine | F8: 12 | G8: In fine | H8: 12 | I8: 8920.671 | J8: =IF(J$1<$F8,$I8,0) -> 8920.671 | K8: =IF(K$1<$F8,$I8,0) -> 8920.671 | L8: =IF(L$1<$F8,$I8,0) -> 8920.671 | M8: =IF(M$1<$F8,$I8,0) -> 8920.671 | N8: =IF(N$1<$F8,$I8,0) -> 8920.671 | O8: =IF(O$1<$F8,$I8,0) -> 8920.671 | P8: =IF(P$1<$F8,$I8,0) -> 8920.671 | Q8: =IF(Q$1<$F8,$I8,0) -> 8920.671 | ... DY8: =IF(DY$1<$F8,$I8,0) -> 0
A9: 46022 | B9: ACTIF | C9: CREANCES SUR LA CLIENTELE | I9: 125650.32 | J9: =SUM(J10:J12) -> 45066.509 | K9: =SUM(K10:K12) -> 40146.149 | L9: =SUM(L10:L12) -> 35212.566 | M9: =SUM(M10:M12) -> 30265.727 | N9: =SUM(N10:N12) -> 25305.594 | O9: =SUM(O10:O12) -> 20332.132 | P9: =SUM(P10:P12) -> 15345.305 | Q9: =SUM(Q10:Q12) -> 10345.078 | ... DY9: =SUM(DY10:DY12) -> 0
A10: 46022 | B10: ACTIF | C10: - Créances commerciales | D10: 0.048443032 | E10: Constant | F10: 60 | G10: Constant | H10: 60 | I10: 358.117 | J10: =IF(J$1<$F10,(I10*(1+($D10/12)))-(-PMT($D10/12,$F10,$I10)),0) -> 352.8301 | K10: =IF(K$1<$F10,(J10*(1+($D10/12)))-(-PMT($D10/12,$F10,$I10)),0) -> 347.52185 | L10: =IF(L$1<$F10,(K10*(1+($D10/12)))-(-PMT($D10/12,$F10,$I10)),0) -> 342.19217 | M10: =IF(M$1<$F10,(L10*(1+($D10/12)))-(-PMT($D10/12,$F10,$I10)),0) -> 336.84098 | N10: =IF(N$1<$F10,(M10*(1+($D10/12)))-(-PMT($D10/12,$F10,$I10)),0) -> 331.46818 | O10: =IF(O$1<$F10,(N10*(1+($D10/12)))-(-PMT($D10/12,$F10,$I10)),0) -> 326.0737 | P10: =IF(P$1<$F10,(O10*(1+($D10/12)))-(-PMT($D10/12,$F10,$I10)),0) -> 320.65744 | Q10: =IF(Q$1<$F10,(P10*(1+($D10/12)))-(-PMT($D10/12,$F10,$I10)),0) -> 315.21931 | ... DY10: =IF(DY$1<$F10,(DX10*(1+($D10/12)))-(-PMT($D10/12,$F10,$I10)),0) -> 0
A11: 46022 | B11: ACTIF | C11: - Autres concours à la clientèle | D11: 0.032228873 | E11: Constant | F11: 10 | G11: Constant | H11: 10 | I11: 49615.566 | J11: =IF(J$1<$F11,(I11*(1+($D11/12)))-(-PMT($D11/12,$F11,$I11)),0) -> 44713.679 | K11: =IF(K$1<$F11,(J11*(1+($D11/12)))-(-PMT($D11/12,$F11,$I11)),0) -> 39798.627 | L11: =IF(L$1<$F11,(K11*(1+($D11/12)))-(-PMT($D11/12,$F11,$I11)),0) -> 34870.374 | M11: =IF(M$1<$F11,(L11*(1+($D11/12)))-(-PMT($D11/12,$F11,$I11)),0) -> 29928.886 | N11: =IF(N$1<$F11,(M11*(1+($D11/12)))-(-PMT($D11/12,$F11,$I11)),0) -> 24974.125 | O11: =IF(O$1<$F11,(N11*(1+($D11/12)))-(-PMT($D11/12,$F11,$I11)),0) -> 20006.058 | P11: =IF(P$1<$F11,(O11*(1+($D11/12)))-(-PMT($D11/12,$F11,$I11)),0) -> 15024.648 | Q11: =IF(Q$1<$F11,(P11*(1+($D11/12)))-(-PMT($D11/12,$F11,$I11)),0) -> 10029.858 | ... DY11: =IF(DY$1<$F11,(DX11*(1+($D11/12)))-(-PMT($D11/12,$F11,$I11)),0) -> 0
A12: 46022 | B12: ACTIF | C12: - Comptes ordinaires débiteurs | D12: 0.039912213 | E12: In fine | F12: 1 | G12: In fine | H12: 1 | I12: 75676.636 | J12: =IF(J$1<$F12,$I12,0) -> 0 | K12: =IF(K$1<$F12,$I12,0) -> 0 | L12: =IF(L$1<$F12,$I12,0) -> 0 | M12: =IF(M$1<$F12,$I12,0) -> 0 | N12: =IF(N$1<$F12,$I12,0) -> 0 | O12: =IF(O$1<$F12,$I12,0) -> 0 | P12: =IF(P$1<$F12,$I12,0) -> 0 | Q12: =IF(Q$1<$F12,$I12,0) -> 0 | ... DY12: =IF(DY$1<$F12,$I12,0) -> 0
A13: 46022 | B13: ACTIF | C13: Investissements financiers | D13: 0.05 | E13: Ine fine | F13: 84 | G13: Ine fine | H13: 84 | I13: 28 | J13: =IF(J$1<$F13,$I13,0) -> 28 | K13: =IF(K$1<$F13,$I13,0) -> 28 | L13: =IF(L$1<$F13,$I13,0) -> 28 | M13: =IF(M$1<$F13,$I13,0) -> 28 | N13: =IF(N$1<$F13,$I13,0) -> 28 | O13: =IF(O$1<$F13,$I13,0) -> 28 | P13: =IF(P$1<$F13,$I13,0) -> 28 | Q13: =IF(Q$1<$F13,$I13,0) -> 28 | ... DY13: =IF(DY$1<$F13,$I13,0) -> 0
A14: 46022 | B14: ACTIF | C14: Immobilisations corporelles et incorporelles | E14: Linéaire | F14: 120 | G14: Linéaire | H14: 120 | I14: 82 | J14: =IF(J$1<$F14,$I14*(($F14-J$1)/$F14),0) -> 81.316667 | K14: =IF(K$1<$F14,$I14*(($F14-K$1)/$F14),0) -> 80.633333 | L14: =IF(L$1<$F14,$I14*(($F14-L$1)/$F14),0) -> 79.95 | M14: =IF(M$1<$F14,$I14*(($F14-M$1)/$F14),0) -> 79.266667 | N14: =IF(N$1<$F14,$I14*(($F14-N$1)/$F14),0) -> 78.583333 | O14: =IF(O$1<$F14,$I14*(($F14-O$1)/$F14),0) -> 77.9 | P14: =IF(P$1<$F14,$I14*(($F14-P$1)/$F14),0) -> 77.216667 | Q14: =IF(Q$1<$F14,$I14*(($F14-Q$1)/$F14),0) -> 76.533333 | ... DY14: =IF(DY$1<$F14,$I14*(($F14-DY$1)/$F14),0) -> 0
A15: 46022 | B15: ACTIF | C15: Autres actifs | E15: Linéaire | F15: 120 | G15: Linéaire | H15: 120 | I15: 570 | J15: =IF(J$1<$F15,$I15*(($F15-J$1)/$F15),0) -> 565.25 | K15: =IF(K$1<$F15,$I15*(($F15-K$1)/$F15),0) -> 560.5 | L15: =IF(L$1<$F15,$I15*(($F15-L$1)/$F15),0) -> 555.75 | M15: =IF(M$1<$F15,$I15*(($F15-M$1)/$F15),0) -> 551 | N15: =IF(N$1<$F15,$I15*(($F15-N$1)/$F15),0) -> 546.25 | O15: =IF(O$1<$F15,$I15*(($F15-O$1)/$F15),0) -> 541.5 | P15: =IF(P$1<$F15,$I15*(($F15-P$1)/$F15),0) -> 536.75 | Q15: =IF(Q$1<$F15,$I15*(($F15-Q$1)/$F15),0) -> 532 | ... DY15: =IF(DY$1<$F15,$I15*(($F15-DY$1)/$F15),0) -> 0
A16: 46022 | B16: ACTIF | C16: Total actif | I16: =I3+I6+I9+I13+I14+I15 -> 155592.39 | J16: =J3+J6+J9+SUM(J13:J15) -> 71822.099 | K16: =K3+K6+K9+SUM(K13:K15) -> 63715.26 | L16: =L3+L6+L9+SUM(L13:L15) -> 55595.198 | M16: =M3+M6+M9+SUM(M13:M15) -> 47461.88 | N16: =N3+N6+N9+SUM(N13:N15) -> 39315.267 | O16: =O3+O6+O9+SUM(O13:O15) -> 31155.327 | P16: =P3+P6+P9+SUM(P13:P15) -> 26163.067 | Q16: =Q3+Q6+Q9+SUM(Q13:Q15) -> 21157.406 | ... DY16: =DY3+DY6+DY9+SUM(DY13:DY15) -> 0
A17: 46022 | B17: PASSIF | C17: DETTES ENVERS ETS DE CREDIT | I17: =I18+I19 -> 74095.3 | J17: =SUM(J18:J19) -> 74095.3 | K17: =SUM(K18:K19) -> 74095.3 | L17: =SUM(L18:L19) -> 74095.3 | M17: =SUM(M18:M19) -> 72205.1 | N17: =SUM(N18:N19) -> 72205.1 | O17: =SUM(O18:O19) -> 72205.1 | P17: =SUM(P18:P19) -> 72205.1 | Q17: =SUM(Q18:Q19) -> 72205.1 | ... DY17: =SUM(DY18:DY19) -> 0
A18: 46022 | B18: PASSIF | C18: - A vue | D18: 0 | E18: 90%-20%*t, t<=4mois | F18: 4 | G18: In fine | H18: 4 | I18: 1890.2 | J18: =IF(J$1<$F18,$I18,0) -> 1890.2 | K18: =IF(K$1<$F18,$I18,0) -> 1890.2 | L18: =IF(L$1<$F18,$I18,0) -> 1890.2 | M18: =IF(M$1<$F18,$I18,0) -> 0 | N18: =IF(N$1<$F18,$I18,0) -> 0 | O18: =IF(O$1<$F18,$I18,0) -> 0 | P18: =IF(P$1<$F18,$I18,0) -> 0 | Q18: =IF(Q$1<$F18,$I18,0) -> 0 | ... DY18: =IF(DY$1<$F18,$I18,0) -> 0
A19: 46022 | B19: PASSIF | C19: - A terme | D19: 0.0138965 | E19: Ine fine | F19: 24 | G19: Ine fine | H19: 24 | I19: 72205.1 | J19: =IF(J$1<$F19,$I19,0) -> 72205.1 | K19: =IF(K$1<$F19,$I19,0) -> 72205.1 | L19: =IF(L$1<$F19,$I19,0) -> 72205.1 | M19: =IF(M$1<$F19,$I19,0) -> 72205.1 | N19: =IF(N$1<$F19,$I19,0) -> 72205.1 | O19: =IF(O$1<$F19,$I19,0) -> 72205.1 | P19: =IF(P$1<$F19,$I19,0) -> 72205.1 | Q19: =IF(Q$1<$F19,$I19,0) -> 72205.1 | ... DY19: =IF(DY$1<$F19,$I19,0) -> 0
A20: 46022 | B20: PASSIF | C20: CPTES CREDITEURS DE LA CLIENTELE | I20: 50161.059 | J20: =SUM(J21:J22) -> 49961.15 | K20: =SUM(K21:K22) -> 49761.241 | L20: =SUM(L21:L22) -> 49561.332 | M20: =SUM(M21:M22) -> 49361.423 | N20: =SUM(N21:N22) -> 49161.513 | O20: =SUM(O21:O22) -> 48961.604 | P20: =SUM(P21:P22) -> 48761.695 | Q20: =SUM(Q21:Q22) -> 48561.786 | ... DY20: =SUM(DY21:DY22) -> 0
A21: 46022 | B21: PASSIF | C21: - A vue | D21: 0 | E21: 90%*exp(-20%*t), t<=120 mois | F21: 120 | G21: Linéaire | H21: 120 | I21: 23989.094 | J21: =IF(J$1<$F21,$I21*(($F21-J$1)/$F21),0) -> 23789.185 | K21: =IF(K$1<$F21,$I21*(($F21-K$1)/$F21),0) -> 23589.276 | L21: =IF(L$1<$F21,$I21*(($F21-L$1)/$F21),0) -> 23389.367 | M21: =IF(M$1<$F21,$I21*(($F21-M$1)/$F21),0) -> 23189.458 | N21: =IF(N$1<$F21,$I21*(($F21-N$1)/$F21),0) -> 22989.548 | O21: =IF(O$1<$F21,$I21*(($F21-O$1)/$F21),0) -> 22789.639 | P21: =IF(P$1<$F21,$I21*(($F21-P$1)/$F21),0) -> 22589.73 | Q21: =IF(Q$1<$F21,$I21*(($F21-Q$1)/$F21),0) -> 22389.821 | ... DY21: =IF(DY$1<$F21,$I21*(($F21-DY$1)/$F21),0) -> 0
A22: 46022 | B22: PASSIF | C22: - A terme | D22: 0.0083386457 | E22: In fine | F22: 60 | G22: In fine | H22: 60 | I22: 26171.965 | J22: =IF(J$1<$F22,$I22,0) -> 26171.965 | K22: =IF(K$1<$F22,$I22,0) -> 26171.965 | L22: =IF(L$1<$F22,$I22,0) -> 26171.965 | M22: =IF(M$1<$F22,$I22,0) -> 26171.965 | N22: =IF(N$1<$F22,$I22,0) -> 26171.965 | O22: =IF(O$1<$F22,$I22,0) -> 26171.965 | P22: =IF(P$1<$F22,$I22,0) -> 26171.965 | Q22: =IF(Q$1<$F22,$I22,0) -> 26171.965 | ... DY22: =IF(DY$1<$F22,$I22,0) -> 0
A23: 46022 | B23: PASSIF | C23: Autres passifs | D23: 0 | E23: Linéaire | F23: 120 | G23: Linéaire | H23: 120 | I23: 2297.337 | J23: =IF(J$1<$F23,$I23*(($F23-J$1)/$F23),0) -> 2278.1925 | K23: =IF(K$1<$F23,$I23*(($F23-K$1)/$F23),0) -> 2259.048 | L23: =IF(L$1<$F23,$I23*(($F23-L$1)/$F23),0) -> 2239.9036 | M23: =IF(M$1<$F23,$I23*(($F23-M$1)/$F23),0) -> 2220.7591 | N23: =IF(N$1<$F23,$I23*(($F23-N$1)/$F23),0) -> 2201.6146 | O23: =IF(O$1<$F23,$I23*(($F23-O$1)/$F23),0) -> 2182.4702 | P23: =IF(P$1<$F23,$I23*(($F23-P$1)/$F23),0) -> 2163.3257 | Q23: =IF(Q$1<$F23,$I23*(($F23-Q$1)/$F23),0) -> 2144.1812 | ... DY23: =IF(DY$1<$F23,$I23*(($F23-DY$1)/$F23),0) -> 0
A24: 46022 | B24: PASSIF | C24: Provisions pour risques et charges | D24: 0 | E24: Linéaire | F24: 120 | G24: Linéaire | H24: 120 | I24: 2994.787 | J24: =IF(J$1<$F24,$I24*(($F24-J$1)/$F24),0) -> 2969.8304 | K24: =IF(K$1<$F24,$I24*(($F24-K$1)/$F24),0) -> 2944.8739 | L24: =IF(L$1<$F24,$I24*(($F24-L$1)/$F24),0) -> 2919.9173 | M24: =IF(M$1<$F24,$I24*(($F24-M$1)/$F24),0) -> 2894.9608 | N24: =IF(N$1<$F24,$I24*(($F24-N$1)/$F24),0) -> 2870.0042 | O24: =IF(O$1<$F24,$I24*(($F24-O$1)/$F24),0) -> 2845.0476 | P24: =IF(P$1<$F24,$I24*(($F24-P$1)/$F24),0) -> 2820.0911 | Q24: =IF(Q$1<$F24,$I24*(($F24-Q$1)/$F24),0) -> 2795.1345 | ... DY24: =IF(DY$1<$F24,$I24*(($F24-DY$1)/$F24),0) -> 0
A25: 46022 | B25: PASSIF | C25: Financement LT | D25: 0.035 | E25: In fine | F25: 72 | G25: In fine | H25: 72 | I25: 130 | J25: =IF(J$1<$F25,$I25,0) -> 130 | K25: =IF(K$1<$F25,$I25,0) -> 130 | L25: =IF(L$1<$F25,$I25,0) -> 130 | M25: =IF(M$1<$F25,$I25,0) -> 130 | N25: =IF(N$1<$F25,$I25,0) -> 130 | O25: =IF(O$1<$F25,$I25,0) -> 130 | P25: =IF(P$1<$F25,$I25,0) -> 130 | Q25: =IF(Q$1<$F25,$I25,0) -> 130 | ... DY25: =IF(DY$1<$F25,$I25,0) -> 0
A26: 46022 | B26: PASSIF | C26: Capitaux propres | I26: 25913.849 | J26: =SUM(J27:J33) -> 25697.9 | K26: =SUM(K27:K33) -> 25481.952 | L26: =SUM(L27:L33) -> 25266.003 | M26: =SUM(M27:M33) -> 25050.054 | N26: =SUM(N27:N33) -> 24834.105 | O26: =SUM(O27:O33) -> 24618.157 | P26: =SUM(P27:P33) -> 24402.208 | Q26: =SUM(Q27:Q33) -> 24186.259 | ... DY26: =SUM(DY27:DY33) -> 0
A27: 46022 | B27: PASSIF | C27: FRBG | D27: 0 | E27: Linéaire | F27: 120 | G27: Linéaire | H27: 120 | I27: 476.541 | J27: =IF(J$1<$F27,$I27*(($F27-J$1)/$F27),0) -> 472.56983 | K27: =IF(K$1<$F27,$I27*(($F27-K$1)/$F27),0) -> 468.59865 | L27: =IF(L$1<$F27,$I27*(($F27-L$1)/$F27),0) -> 464.62748 | M27: =IF(M$1<$F27,$I27*(($F27-M$1)/$F27),0) -> 460.6563 | N27: =IF(N$1<$F27,$I27*(($F27-N$1)/$F27),0) -> 456.68513 | O27: =IF(O$1<$F27,$I27*(($F27-O$1)/$F27),0) -> 452.71395 | P27: =IF(P$1<$F27,$I27*(($F27-P$1)/$F27),0) -> 448.74277 | Q27: =IF(Q$1<$F27,$I27*(($F27-Q$1)/$F27),0) -> 444.7716 | ... DY27: =IF(DY$1<$F27,$I27*(($F27-DY$1)/$F27),0) -> 0
A28: 46022 | B28: PASSIF | C28: Capital souscrit | D28: 0 | E28: Linéaire | F28: 120 | G28: Linéaire | H28: 120 | I28: 18000.179 | J28: =IF(J$1<$F28,$I28*(($F28-J$1)/$F28),0) -> 17850.178 | K28: =IF(K$1<$F28,$I28*(($F28-K$1)/$F28),0) -> 17700.176 | L28: =IF(L$1<$F28,$I28*(($F28-L$1)/$F28),0) -> 17550.175 | M28: =IF(M$1<$F28,$I28*(($F28-M$1)/$F28),0) -> 17400.173 | N28: =IF(N$1<$F28,$I28*(($F28-N$1)/$F28),0) -> 17250.172 | O28: =IF(O$1<$F28,$I28*(($F28-O$1)/$F28),0) -> 17100.17 | P28: =IF(P$1<$F28,$I28*(($F28-P$1)/$F28),0) -> 16950.169 | Q28: =IF(Q$1<$F28,$I28*(($F28-Q$1)/$F28),0) -> 16800.167 | ... DY28: =IF(DY$1<$F28,$I28*(($F28-DY$1)/$F28),0) -> 0
A29: 46022 | B29: PASSIF | C29: Prime d'émission | D29: 0 | E29: Linéaire | F29: 120 | G29: Linéaire | H29: 120 | I29: 2.22 | J29: =IF(J$1<$F29,$I29*(($F29-J$1)/$F29),0) -> 2.2015 | K29: =IF(K$1<$F29,$I29*(($F29-K$1)/$F29),0) -> 2.183 | L29: =IF(L$1<$F29,$I29*(($F29-L$1)/$F29),0) -> 2.1645 | M29: =IF(M$1<$F29,$I29*(($F29-M$1)/$F29),0) -> 2.146 | N29: =IF(N$1<$F29,$I29*(($F29-N$1)/$F29),0) -> 2.1275 | O29: =IF(O$1<$F29,$I29*(($F29-O$1)/$F29),0) -> 2.109 | P29: =IF(P$1<$F29,$I29*(($F29-P$1)/$F29),0) -> 2.0905 | Q29: =IF(Q$1<$F29,$I29*(($F29-Q$1)/$F29),0) -> 2.072 | ... DY29: =IF(DY$1<$F29,$I29*(($F29-DY$1)/$F29),0) -> 0
A30: 46022 | B30: PASSIF | C30: Réserves | D30: 0 | E30: Linéaire | F30: 120 | G30: Linéaire | H30: 120 | I30: 429.975 | J30: =IF(J$1<$F30,$I30*(($F30-J$1)/$F30),0) -> 426.39188 | K30: =IF(K$1<$F30,$I30*(($F30-K$1)/$F30),0) -> 422.80875 | L30: =IF(L$1<$F30,$I30*(($F30-L$1)/$F30),0) -> 419.22563 | M30: =IF(M$1<$F30,$I30*(($F30-M$1)/$F30),0) -> 415.6425 | N30: =IF(N$1<$F30,$I30*(($F30-N$1)/$F30),0) -> 412.05938 | O30: =IF(O$1<$F30,$I30*(($F30-O$1)/$F30),0) -> 408.47625 | P30: =IF(P$1<$F30,$I30*(($F30-P$1)/$F30),0) -> 404.89312 | Q30: =IF(Q$1<$F30,$I30*(($F30-Q$1)/$F30),0) -> 401.31 | ... DY30: =IF(DY$1<$F30,$I30*(($F30-DY$1)/$F30),0) -> 0
A31: 46022 | B31: PASSIF | C31: Report à nouveau | D31: 0 | E31: Linéaire | F31: 120 | G31: Linéaire | H31: 120 | I31: 7004.934 | J31: =IF(J$1<$F31,$I31*(($F31-J$1)/$F31),0) -> 6946.5596 | K31: =IF(K$1<$F31,$I31*(($F31-K$1)/$F31),0) -> 6888.1851 | L31: =IF(L$1<$F31,$I31*(($F31-L$1)/$F31),0) -> 6829.8107 | M31: =IF(M$1<$F31,$I31*(($F31-M$1)/$F31),0) -> 6771.4362 | N31: =IF(N$1<$F31,$I31*(($F31-N$1)/$F31),0) -> 6713.0618 | O31: =IF(O$1<$F31,$I31*(($F31-O$1)/$F31),0) -> 6654.6873 | P31: =IF(P$1<$F31,$I31*(($F31-P$1)/$F31),0) -> 6596.3129 | Q31: =IF(Q$1<$F31,$I31*(($F31-Q$1)/$F31),0) -> 6537.9384 | ... DY31: =IF(DY$1<$F31,$I31*(($F31-DY$1)/$F31),0) -> 0
A32: 46022 | B32: PASSIF | C32: Résultat de l'exercice | D32: 0 | E32: Linéaire | F32: 120 | G32: Linéaire | H32: 120 | I32: 0 | J32: =IF(J$1<$F32,$I32*(($F32-J$1)/$F32),0) -> 0 | K32: =IF(K$1<$F32,$I32*(($F32-K$1)/$F32),0) -> 0 | L32: =IF(L$1<$F32,$I32*(($F32-L$1)/$F32),0) -> 0 | M32: =IF(M$1<$F32,$I32*(($F32-M$1)/$F32),0) -> 0 | N32: =IF(N$1<$F32,$I32*(($F32-N$1)/$F32),0) -> 0 | O32: =IF(O$1<$F32,$I32*(($F32-O$1)/$F32),0) -> 0 | P32: =IF(P$1<$F32,$I32*(($F32-P$1)/$F32),0) -> 0 | Q32: =IF(Q$1<$F32,$I32*(($F32-Q$1)/$F32),0) -> 0 | ... DY32: =IF(DY$1<$F32,$I32*(($F32-DY$1)/$F32),0) -> 0
A33: 46022 | B33: PASSIF | C33: Dividende | D33: 0 | E33: Linéaire | F33: 120 | G33: Linéaire | H33: 120 | I33: 0 | J33: =IF(J$1<$F33,$I33*(($F33-J$1)/$F33),0) -> 0 | K33: =IF(K$1<$F33,$I33*(($F33-K$1)/$F33),0) -> 0 | L33: =IF(L$1<$F33,$I33*(($F33-L$1)/$F33),0) -> 0 | M33: =IF(M$1<$F33,$I33*(($F33-M$1)/$F33),0) -> 0 | N33: =IF(N$1<$F33,$I33*(($F33-N$1)/$F33),0) -> 0 | O33: =IF(O$1<$F33,$I33*(($F33-O$1)/$F33),0) -> 0 | P33: =IF(P$1<$F33,$I33*(($F33-P$1)/$F33),0) -> 0 | Q33: =IF(Q$1<$F33,$I33*(($F33-Q$1)/$F33),0) -> 0 | ... DY33: =IF(DY$1<$F33,$I33*(($F33-DY$1)/$F33),0) -> 0
A34: 46022 | B34: PASSIF | C34: Total passif | I34: =I26+I24+I23+I20+I17+I25 -> 155592.33 | J34: =J17+J20+SUM(J23:J26) -> 155132.37 | K34: =K17+K20+SUM(K23:K26) -> 154672.41 | L34: =L17+L20+SUM(L23:L26) -> 154212.46 | M34: =M17+M20+SUM(M23:M26) -> 151862.3 | N34: =N17+N20+SUM(N23:N26) -> 151402.34 | O34: =O17+O20+SUM(O23:O26) -> 150942.38 | P34: =P17+P20+SUM(P23:P26) -> 150482.42 | Q34: =Q17+Q20+SUM(Q23:Q26) -> 150022.46 | ... DY34: =DY17+DY20+SUM(DY23:DY26) -> 0
A35: Gap de taux fixé | I35: =I34-I16 -> -0.05598 | J35: =J34-J16 -> 83310.274 | K35: =K34-K16 -> 90957.154 | L35: =L34-L16 -> 98617.257 | M35: =M34-M16 -> 104400.42 | N35: =N34-N16 -> 112087.07 | O35: =O34-O16 -> 119787.05 | P35: =P34-P16 -> 124319.35 | ... DY35: =DY34-DY16 -> 0
C42: *ETS : Etablissement
C43: *FRBG : Fonds pour Risques Bancaires Généraux

Sheet BAU_Liquidité_Dynamique
E1: E n liquidité | G1: E n taux | I1: 0 | J1: 1 | K1: 2 | L1: 3 | M1: 4 | N1: 5 | O1: 6 | P1: 7 | Q1: 8 | R1: 9 | S1: 10 | T1: 11 | U1: 12 | V1: 13 | W1: 14 | X1: 15 | Y1: 16 | Z1: 17 | AA1: 18 | AB1: 19 | AC1: 20 | AD1: 21 | AE1: 22 | AF1: 23 | AG1: 24 | AH1: 25 | AI1: 26 | AJ1: 27 | AK1: 28 | AL1: 29 | AM1: 30 | AN1: 31 | AO1: 32 | AP1: 33 | AQ1: 34 | AR1: 35 | AS1: 36 | AT1: 37 | AU1: 38 | AV1: 39 | AW1: 40 | AX1: 41 | AY1: 42 | AZ1: 43 | BA1: 44 | BB1: 45 | BC1: 46 | BD1: 47 | BE1: 48 | BF1: 49 | BG1: 50 | BH1: 51 | BI1: 52 | BJ1: 53 | BK1: 54 | BL1: 55 | BM1: 56 | BN1: 57 | BO1: 58 | BP1: 59 | BQ1: 60 | BR1: 61 | BS1: 62 | BT1: 63 | BU1: 64 | BV1: 65 | BW1: 66 | BX1: 67 | BY1: 68 | BZ1: 69 | CA1: 70 | CB1: 71 | CC1: 72 | CD1: 73 | CE1: 74 | CF1: 75 | CG1: 76 | CH1: 77 | CI1: 78 | CJ1: 79 | CK1: 80 | CL1: 81 | CM1: 82 | CN1: 83 | CO1: 84 | CP1: 85 | CQ1: 86 | CR1: 87 | CS1: 88 | CT1: 89 | CU1: 90 | CV1: 91 | CW1: 92 | CX1: 93 | CY1: 94 | CZ1: 95 | DA1: 96 | DB1: 97 | DC1: 98 | DD1: 99 | DE1: 100 | DF1: 101 | DG1: 102 | DH1: 103 | DI1: 104 | DJ1: 105 | DK1: 106 | DL1: 107 | DM1: 108 | DN1: 109 | DO1: 110 | DP1: 111 | DQ1: 112 | DR1: 113 | DS1: 114 | DT1: 115 | DU1: 116 | DV1: 117 | DW1: 118 | DX1: 119 | DY1: 120
A2: Date d’arrêté | B2: Bilan | C2: Poste du bilan | D2: Taux d'intérèt moyen | E2: Loi d'écoulement | F2: Durée moyenne (en mois) | G2: Loi d'écoulement | H2: Durée moyenne (en mois) | I2: Montant (en k€) | J2: M1 | K2: M2 | L2: M3 | M2: M4 | N2: M5 | O2: M6 | P2: M7 | Q2: M8 | R2: M9 | S2: M10 | T2: M11 | U2: M12 | V2: M13 | W2: M14 | X2: M15 | Y2: M16 | Z2: M17 | AA2: M18 | AB2: M19 | AC2: M20 | AD2: M21 | AE2: M22 | AF2: M23 | AG2: M24 | AH2: M25 | AI2: M26 | AJ2: M27 | AK2: M28 | AL2: M29 | AM2: M30 | AN2: M31 | AO2: M32 | AP2: M33 | AQ2: M34 | AR2: M35 | AS2: M36 | AT2: M37 | AU2: M38 | AV2: M39 | AW2: M40 | AX2: M41 | AY2: M42 | AZ2: M43 | BA2: M44 | BB2: M45 | BC2: M46 | BD2: M47 | BE2: M48 | BF2: M49 | BG2: M50 | BH2: M51 | BI2: M52 | BJ2: M53 | BK2: M54 | BL2: M55 | BM2: M56 | BN2: M57 | BO2: M58 | BP2: M59 | BQ2: M60 | BR2: M61 | BS2: M62 | BT2: M63 | BU2: M64 | BV2: M65 | BW2: M66 | BX2: M67 | BY2: M68 | BZ2: M69 | CA2: M70 | CB2: M71 | CC2: M72 | CD2: M73 | CE2: M74 | CF2: M75 | CG2: M76 | CH2: M77 | CI2: M78 | CJ2: M79 | CK2: M80 | CL2: M81 | CM2: M82 | CN2: M83 | CO2: M84 | CP2: M85 | CQ2: M86 | CR2: M87 | CS2: M88 | CT2: M89 | CU2: M90 | CV2: M91 | CW2: M92 | CX2: M93 | CY2: M94 | CZ2: M95 | DA2: M96 | DB2: M97 | DC2: M98 | DD2: M99 | DE2: M100 | DF2: M101 | DG2: M102 | DH2: M103 | DI2: M104 | DJ2: M105 | DK2: M106 | DL2: M107 | DM2: M108 | DN2: M109 | DO2: M110 | DP2: M111 | DQ2: M112 | DR2: M113 | DS2: M114 | DT2: M115 | DU2: M116 | DV2: M117 | DW2: M118 | DX2: M119 | DY2: M120
A3: 46022 | B3: ACTIF | C3: CAISSE, BANQUES CENTRALES | I3: =I4+I8 -> 1255.124 | J3: =SUM(J4:J8) -> 1244.3264 | K3: =SUM(K4:K8) -> 1233.5288 | L3: =SUM(L4:L8) -> 1222.7312 | M3: =SUM(M4:M8) -> 1211.9336 | N3: =SUM(N4:N8) -> 1201.136 | O3: =SUM(O4:O8) -> 1190.3384 | P3: =SUM(P4:P8) -> 1179.5408 | Q3: =SUM(Q4:Q8) -> 1168.7433 | ... DY3: =SUM(DY4:DY8) -> 0
A4: 46022 | B4: ACTIF | C4: - Caisse | D4: 0 | E4: Linéaire | F4: 60 | G4: In fine | H4: 60 | I4: 40.58686 | J4: =IF(J$1<$F4,$I4*(($F4-J$1)/$F4),0) -> 39.910412 | K4: =IF(K$1<$F4,$I4*(($F4-K$1)/$F4),0) -> 39.233965 | L4: =IF(L$1<$F4,$I4*(($F4-L$1)/$F4),0) -> 38.557517 | M4: =IF(M$1<$F4,$I4*(($F4-M$1)/$F4),0) -> 37.881069 | N4: =IF(N$1<$F4,$I4*(($F4-N$1)/$F4),0) -> 37.204622 | O4: =IF(O$1<$F4,$I4*(($F4-O$1)/$F4),0) -> 36.528174 | P4: =IF(P$1<$F4,$I4*(($F4-P$1)/$F4),0) -> 35.851726 | Q4: =IF(Q$1<$F4,$I4*(($F4-Q$1)/$F4),0) -> 35.175279 | ... DY4: =IF(DY$1<$F4,$I4*(($F4-DY$1)/$F4),0) -> 0
C5: Nouvelles productions 2026 | U5: ='Plan Moyen Terme (PMT)'!C4-BAU_Liquidité_Dynamique!U4 -> -5.783928 | V5: =IF(AND(U1<V$1, V$1<=$F4),$U5*($F4-V$1)/($F4-$U1),0) -> -5.6634295 | W5: =IF(AND(V1<W$1, W$1<=$F4),$U5*($F4-W$1)/($F4-$U1),0) -> -5.542931 | X5: =IF(AND(W1<X$1, X$1<=$F4),$U5*($F4-X$1)/($F4-$U1),0) -> -5.4224325 | Y5: =IF(AND(X1<Y$1, Y$1<=$F4),$U5*($F4-Y$1)/($F4-$U1),0) -> -5.301934 | Z5: =IF(AND(Y1<Z$1, Z$1<=$F4),$U5*($F4-Z$1)/($F4-$U1),0) -> -5.1814355 | AA5: =IF(AND(Z1<AA$1, AA$1<=$F4),$U5*($F4-AA$1)/($F4-$U1),0) -> -5.060937 | AB5: =IF(AND(AA1<AB$1, AB$1<=$F4),$U5*($F4-AB$1)/($F4-$U1),0) -> -4.9404385 | AC5: =IF(AND(AB1<AC$1, AC$1<=$F4),$U5*($F4-AC$1)/($F4-$U1),0) -> -4.81994 | ... BQ5: =IF(AND(BP1<BQ$1, BQ$1<=$F4),$U5*($F4-BQ$1)/($F4-$U1),0) -> 0 | BR5: =IF(BR$1<$F4-$U1,$U5*($F4-BR$1)/($F4-$U1),0) -> 0 | BS5: =IF(BS$1<$F4-$U1,$U5*($F4-BS$1)/($F4-$U1),0) -> 0 | BT5: =IF(BT$1<$F4-$U1,$U5*($F4-BT$1)/($F4-$U1),0) -> 0 | BU5: =IF(BU$1<$F4-$U1,$U5*($F4-BU$1)/($F4-$U1),0) -> 0 | BV5: =IF(BV$1<$F4-$U1,$U5*($F4-BV$1)/($F4-$U1),0) -> 0 | BW5: =IF(BW$1<$F4-$U1,$U5*($F4-BW$1)/($F4-$U1),0) -> 0 | BX5: =IF(BX$1<$F4-$U1,$U5*($F4-BX$1)/($F4-$U1),0) -> 0 | BY5: =IF(BY$1<$F4-$U1,$U5*($F4-BY$1)/($F4-$U1),0) -> 0 | ... DY5: =IF(DY$1<$F4-$U1,$U5*($F4-DY$1)/($F4-$U1),0) -> 0
C6: Nouvelles productions 2027 | AG6: ='Plan Moyen Terme (PMT)'!D4-BAU_Liquidité_Dynamique!AG4 -> 274.5002 | AH6: =IF(AND(AG1<AH$1, AH$1<=$F4),$AG6*($F4-AH1)/($F4-$AG1),0) -> 266.8752 | AI6: =IF(AND(AH1<AI$1, AI$1<=$F4),$AG6*($F4-AI1)/($F4-$AG1),0) -> 259.25019 | AJ6: =IF(AND(AI1<AJ$1, AJ$1<=$F4),$AG6*($F4-AJ1)/($F4-$AG1),0) -> 251.62519 | AK6: =IF(AND(AJ1<AK$1, AK$1<=$F4),$AG6*($F4-AK1)/($F4-$AG1),0) -> 244.00018 | AL6: =IF(AND(AK1<AL$1, AL$1<=$F4),$AG6*($F4-AL1)/($F4-$AG1),0) -> 236.37518 | AM6: =IF(AND(AL1<AM$1, AM$1<=$F4),$AG6*($F4-AM1)/($F4-$AG1),0) -> 228.75017 | AN6: =IF(AND(AM1<AN$1, AN$1<=$F4),$AG6*($F4-AN1)/($F4-$AG1),0) -> 221.12516 | AO6: =IF(AND(AN1<AO$1, AO$1<=$F4),$AG6*($F4-AO1)/($F4-$AG1),0) -> 213.50016 | ... BQ6: =IF(AND(BP1<BQ$1, BQ$1<=$F4),$AG6*($F4-BQ1)/($F4-$AG1),0) -> 0 | BR6: =IF(BR$1<$F4-$AG1,$AG6*($F4-BR1)/($F4-$AG1),0) -> 0 | BS6: =IF(BS$1<$F4-$AG1,$AG6*($F4-BS1)/($F4-$AG1),0) -> 0 | BT6: =IF(BT$1<$F4-$AG1,$AG6*($F4-BT1)/($F4-$AG1),0) -> 0 | BU6: =IF(BU$1<$F4-$AG1,$AG6*($F4-BU1)/($F4-$AG1),0) -> 0 | BV6: =IF(BV$1<$F4-$AG1,$AG6*($F4-BV1)/($F4-$AG1),0) -> 0 | BW6: =IF(BW$1<$F4-$AG1,$AG6*($F4-BW1)/($F4-$AG1),0) -> 0 | BX6: =IF(BX$1<$F4-$AG1,$AG6*($F4-BX1)/($F4-$AG1),0) -> 0 | BY6: =IF(BY$1<$F4-$AG1,$AG6*($F4-BY1)/($F4-$AG1),0) -> 0 | ... DY6: =IF(DY$1<$F4-$AG1,$AG6*($F4-DY1)/($F4-$AG1),0) -> 0
C7: Nouvelles productions 2028 | AS7: ='Plan Moyen Terme (PMT)'!E4-BAU_Liquidité_Dynamique!AS4 -> 229.86212 | AT7: =IF(AND(AS1<AT$1, AT$1<=$F4),$AS$7*($F$4-AT1)/($F$4-$AS1),0) -> 220.28453 | AU7: =IF(AND(AT1<AU$1, AU$1<=$F4),$AS$7*($F$4-AU1)/($F$4-$AS1),0) -> 210.70694 | AV7: =IF(AND(AU1<AV$1, AV$1<=$F4),$AS$7*($F$4-AV1)/($F$4-$AS1),0) -> 201.12935 | AW7: =IF(AND(AV1<AW$1, AW$1<=$F4),$AS$7*($F$4-AW1)/($F$4-$AS1),0) -> 191.55176 | AX7: =IF(AND(AW1<AX$1, AX$1<=$F4),$AS$7*($F$4-AX1)/($F$4-$AS1),0) -> 181.97418 | AY7: =IF(AND(AX1<AY$1, AY$1<=$F4),$AS$7*($F$4-AY1)/($F$4-$AS1),0) -> 172.39659 | AZ7: =IF(AND(AY1<AZ$1, AZ$1<=$F4),$AS$7*($F$4-AZ1)/($F$4-$AS1),0) -> 162.819 | BA7: =IF(AND(AZ1<BA$1, BA$1<=$F4),$AS$7*($F$4-BA1)/($F$4-$AS1),0) -> 153.24141 | ... BQ7: =IF(AND(BP1<BQ$1, BQ$1<=$F4),$AS$7*($F$4-BQ1)/($F$4-$AS1),0) -> 0
A8: 46022 | B8: ACTIF | C8: - Compte courant BDF | D8: 0.00040572687 | E8: Linéaire | F8: 120 | G8: Ine fine | H8: 120 | I8: 1214.5371 | J8: =IF(J$1<$F8,$I8*(($F8-J$1)/$F8),0) -> 1204.416 | K8: =IF(K$1<$F8,$I8*(($F8-K$1)/$F8),0) -> 1194.2948 | L8: =IF(L$1<$F8,$I8*(($F8-L$1)/$F8),0) -> 1184.1737 | M8: =IF(M$1<$F8,$I8*(($F8-M$1)/$F8),0) -> 1174.0525 | N8: =IF(N$1<$F8,$I8*(($F8-N$1)/$F8),0) -> 1163.9314 | O8: =IF(O$1<$F8,$I8*(($F8-O$1)/$F8),0) -> 1153.8103 | P8: =IF(P$1<$F8,$I8*(($F8-P$1)/$F8),0) -> 1143.6891 | Q8: =IF(Q$1<$F8,$I8*(($F8-Q$1)/$F8),0) -> 1133.568 | ... DY8: =IF(DY$1<$F8,$I8*(($F8-DY$1)/$F8),0) -> 0
C9: Nouvelles productions 2026 | U9: ='Plan Moyen Terme (PMT)'!C5-BAU_Liquidité_Dynamique!U8 -> 175.23103 | V9: =IF(AND(U1<V$1, V$1<=$F8),$U9*($F8-V$1)/($F8-$U$1),0) -> 173.60852 | W9: =IF(AND(V1<W$1, W$1<=$F8),$U9*($F8-W$1)/($F8-$U$1),0) -> 171.98601 | X9: =IF(AND(W1<X$1, X$1<=$F8),$U9*($F8-X$1)/($F8-$U$1),0) -> 170.3635 | Y9: =IF(AND(X1<Y$1, Y$1<=$F8),$U9*($F8-Y$1)/($F8-$U$1),0) -> 168.74099 | Z9: =IF(AND(Y1<Z$1, Z$1<=$F8),$U9*($F8-Z$1)/($F8-$U$1),0) -> 167.11848 | AA9: =IF(AND(Z1<AA$1, AA$1<=$F8),$U9*($F8-AA$1)/($F8-$U$1),0) -> 165.49597 | AB9: =IF(AND(AA1<AB$1, AB$1<=$F8),$U9*($F8-AB$1)/($F8-$U$1),0) -> 163.87347 | AC9: =IF(AND(AB1<AC$1, AC$1<=$F8),$U9*($F8-AC$1)/($F8-$U$1),0) -> 162.25096 | ... DY9: =IF(AND(DX1<DY$1, DY$1<=$F8),$U9*($F8-DY$1)/($F8-$U$1),0) -> 0
C10: Nouvelles productions 2027 | AG10: ='Plan Moyen Terme (PMT)'!D5-BAU_Liquidité_Dynamique!AG8 -> 6047.3703 | AH10: =IF(AND(AG1<AH$1, AH$1<=$F8),$AG10*($F8-AH$1)/($F8-$AG$1),0) -> 5984.3769 | AI10: =IF(AND(AH1<AI$1, AI$1<=$F8),$AG10*($F8-AI$1)/($F8-$AG$1),0) -> 5921.3834 | AJ10: =IF(AND(AI1<AJ$1, AJ$1<=$F8),$AG10*($F8-AJ$1)/($F8-$AG$1),0) -> 5858.39 | AK10: =IF(AND(AJ1<AK$1, AK$1<=$F8),$AG10*($F8-AK$1)/($F8-$AG$1),0) -> 5795.3965 | AL10: =IF(AND(AK1<AL$1, AL$1<=$F8),$AG10*($F8-AL$1)/($F8-$AG$1),0) -> 5732.4031 | AM10: =IF(AND(AL1<AM$1, AM$1<=$F8),$AG10*($F8-AM$1)/($F8-$AG$1),0) -> 5669.4097 | AN10: =IF(AND(AM1<AN$1, AN$1<=$F8),$AG10*($F8-AN$1)/($F8-$AG$1),0) -> 5606.4162 | AO10: =IF(AND(AN1<AO$1, AO$1<=$F8),$AG10*($F8-AO$1)/($F8-$AG$1),0) -> 5543.4228 | ... DY10: =IF(AND(DX1<DY$1, DY$1<=$F8),$AG10*($F8-DY$1)/($F8-$AG$1),0) -> 0
C11: Nouvelles productions 2028 | AS11: ='Plan Moyen Terme (PMT)'!E5-BAU_Liquidité_Dynamique!AS8 -> 4440.824 | AT11: =IF(AND(AS1<AT$1, AT$1<=$F8),$AS11*($F8-AT$1)/($F8-$AS$1),0) -> 4387.9571 | AU11: =IF(AND(AT1<AU$1, AU$1<=$F8),$AS11*($F8-AU$1)/($F8-$AS$1),0) -> 4335.0901 | AV11: =IF(AND(AU1<AV$1, AV$1<=$F8),$AS11*($F8-AV$1)/($F8-$AS$1),0) -> 4282.2232 | AW11: =IF(AND(AV1<AW$1, AW$1<=$F8),$AS11*($F8-AW$1)/($F8-$AS$1),0) -> 4229.3562 | AX11: =IF(AND(AW1<AX$1, AX$1<=$F8),$AS11*($F8-AX$1)/($F8-$AS$1),0) -> 4176.4893 | AY11: =IF(AND(AX1<AY$1, AY$1<=$F8),$AS11*($F8-AY$1)/($F8-$AS$1),0) -> 4123.6223 | AZ11: =IF(AND(AY1<AZ$1, AZ$1<=$F8),$AS11*($F8-AZ$1)/($F8-$AS$1),0) -> 4070.7553 | BA11: =IF(AND(AZ1<BA$1, BA$1<=$F8),$AS11*($F8-BA$1)/($F8-$AS$1),0) -> 4017.8884 | ... DY11: =IF(AND(DX1<DY$1, DY$1<=$F8),$AS11*($F8-DY$1)/($F8-$AS$1),0) -> 0
A12: 46022 | B12: ACTIF | C12: CREANCES SUR LES ETS DE CREDIT | I12: =I13+I17 -> 28006.945 | J12: =SUM(J13:J17) -> 24825.899 | K12: =SUM(K13:K17) -> 21644.854 | L12: =SUM(L13:L17) -> 18463.808 | M12: =SUM(M13:M17) -> 15282.762 | N12: =SUM(N13:N17) -> 12101.717 | O12: =SUM(O13:O17) -> 8920.671 | P12: =SUM(P13:P17) -> 8920.671 | Q12: =SUM(Q13:Q17) -> 8920.671 | ... DY12: =SUM(DY13:DY17) -> 0
A13: 46022 | B13: ACTIF | C13: - A vue | D13: 0 | E13: Linéaire | F13: 6 | G13: Linéaire | H13: 6 | I13: 19086.274 | J13: =IF(J$1<$F13,$I13*(($F13-J$1)/$F13),0) -> 15905.228 | K13: =IF(K$1<$F13,$I13*(($F13-K$1)/$F13),0) -> 12724.183 | L13: =IF(L$1<$F13,$I13*(($F13-L$1)/$F13),0) -> 9543.137 | M13: =IF(M$1<$F13,$I13*(($F13-M$1)/$F13),0) -> 6362.0913 | N13: =IF(N$1<$F13,$I13*(($F13-N$1)/$F13),0) -> 3181.0457 | O13: =IF(O$1<$F13,$I13*(($F13-O$1)/$F13),0) -> 0 | P13: =IF(P$1<$F13,$I13*(($F13-P$1)/$F13),0) -> 0 | Q13: =IF(Q$1<$F13,$I13*(($F13-Q$1)/$F13),0) -> 0 | ... DY13: =IF(DY$1<$F13,$I13*(($F13-DY$1)/$F13),0) -> 0
C14: Nouvelles productions 2026=0
C15: Nouvelles productions 2027=0
C16: Nouvelles productions 2028=0
A17: 46022 | B17: ACTIF | C17: - A terme | D17: 0.02489751 | E17: In fine | F17: 12 | G17: In fine | H17: 12 | I17: 8920.671 | J17: =IF(J$1<$F17,$I17,0) -> 8920.671 | K17: =IF(K$1<$F17,$I17,0) -> 8920.671 | L17: =IF(L$1<$F17,$I17,0) -> 8920.671 | M17: =IF(M$1<$F17,$I17,0) -> 8920.671 | N17: =IF(N$1<$F17,$I17,0) -> 8920.671 | O17: =IF(O$1<$F17,$I17,0) -> 8920.671 | P17: =IF(P$1<$F17,$I17,0) -> 8920.671 | Q17: =IF(Q$1<$F17,$I17,0) -> 8920.671 | ... DY17: =IF(DY$1<$F17,$I17,0) -> 0
C18: Nouvelles productions 2026=0
C19: Nouvelles productions 2027=0 | J19: =PMT($D22/12,$F22,$I22) -> -6.7325943 | K19: =I22*D22/12 -> 1.4456894 | AH19: =AH17 -> 0 | AI19: =AG23*D22/12 -> 17.499894
C20: Nouvelles productions 2028=0
A21: 46022 | B21: ACTIF | C21: CREANCES SUR LA CLIENTELE | I21: =I22+I26+I30 -> 125650.32 | J21: =SUM(J22:J30) -> 45066.509 | K21: =SUM(K22:K30) -> 40146.149 | L21: =SUM(L22:L30) -> 35212.566 | M21: =SUM(M22:M30) -> 30265.727 | N21: =SUM(N22:N30) -> 25305.594 | O21: =SUM(O22:O30) -> 20332.132 | P21: =SUM(P22:P30) -> 15345.305 | Q21: =SUM(Q22:Q30) -> 10345.078 | ... DY21: =SUM(DY22:DY30) -> 0
A22: 46022 | B22: ACTIF | C22: - Créances commerciales | D22: 0.048443032 | E22: Constant | F22: 60 | G22: Constant | H22: 60 | I22: 358.117 | J22: =IF(J$1<$F22,(I22*(1+($D22/12)))-(-PMT($D22/12,$F22,$I22)),0) -> 352.8301 | K22: =IF(K$1<$F22,(J22*(1+($D22/12)))-(-PMT($D22/12,$F22,$I22)),0) -> 347.52185 | L22: =IF(L$1<$F22,(K22*(1+($D22/12)))-(-PMT($D22/12,$F22,$I22)),0) -> 342.19217 | M22: =IF(M$1<$F22,(L22*(1+($D22/12)))-(-PMT($D22/12,$F22,$I22)),0) -> 336.84098 | N22: =IF(N$1<$F22,(M22*(1+($D22/12)))-(-PMT($D22/12,$F22,$I22)),0) -> 331.46818 | O22: =IF(O$1<$F22,(N22*(1+($D22/12)))-(-PMT($D22/12,$F22,$I22)),0) -> 326.0737 | P22: =IF(P$1<$F22,(O22*(1+($D22/12)))-(-PMT($D22/12,$F22,$I22)),0) -> 320.65744 | Q22: =IF(Q$1<$F22,(P22*(1+($D22/12)))-(-PMT($D22/12,$F22,$I22)),0) -> 315.21931 | ... DY22: =IF(DY$1<$F22,(DX22*(1+($D22/12)))-(-PMT($D22/12,$F22,$I22)),0) -> 0
C23: Nouvelles productions 2026 | U23: ='Plan Moyen Terme (PMT)'!C10-BAU_Liquidité_Dynamique!U22 -> 5645.7536 | V23: =IF(AND(U1<V$1, V$1<=$F$22),(U23*(1+($D$22/12)))-(-PMT($D$22/12,$F$22-$U1,$U$23)),0) -> 5538.9252 | W23: =IF(AND(V1<W$1, W$1<=$F$22),(V23*(1+($D$22/12)))-(-PMT($D$22/12,$F$22-$U1,$U$23)),0) -> 5431.6655 | X23: =IF(AND(W1<X$1, X$1<=$F$22),(W23*(1+($D$22/12)))-(-PMT($D$22/12,$F$22-$U1,$U$23)),0) -> 5323.9727 | Y23: =IF(AND(X1<Y$1, Y$1<=$F$22),(X23*(1+($D$22/12)))-(-PMT($D$22/12,$F$22-$U1,$U$23)),0) -> 5215.8453 | Z23: =IF(AND(Y1<Z$1, Z$1<=$F$22),(Y23*(1+($D$22/12)))-(-PMT($D$22/12,$F$22-$U1,$U$23)),0) -> 5107.2813 | AA23: =IF(AND(Z1<AA$1, AA$1<=$F$22),(Z23*(1+($D$22/12)))-(-PMT($D$22/12,$F$22-$U1,$U$23)),0) -> 4998.2791 | AB23: =IF(AND(AA1<AB$1, AB$1<=$F$22),(AA23*(1+($D$22/12)))-(-PMT($D$22/12,$F$22-$U1,$U$23)),0) -> 4888.8369 | AC23: =IF(AND(AB1<AC$1, AC$1<=$F$22),(AB23*(1+($D$22/12)))-(-PMT($D$22/12,$F$22-$U1,$U$23)),0) -> 4778.9528 | ... BQ23: =IF(AND(BP1<BQ$1, BQ$1<=$F$22),(BP23*(1+($D$22/12)))-(-PMT($D$22/12,$F$22-$U1,$U$23)),0) -> -5.1727511e-12
C24: Nouvelles productions 2027 | AG24: ='Plan Moyen Terme (PMT)'!D10-BAU_Liquidité_Dynamique!AG22 -> 3744.8375 | AH24: =IF(AND(AG1<AH$1, AH$1<=$F22),(AG24*(1+$D22/12))+(PMT($D22/12,$F22-$AG1,$AG24)),0) -> 3647.9805 | AI24: =IF(AND(AH1<AI$1, AI$1<=$F22),(AH24*(1+$D22/12))+(PMT($D22/12,$F22-$AG1,$AG24)),0) -> 3550.7326 | AJ24: =IF(AND(AI1<AJ$1, AJ$1<=$F22),(AI24*(1+$D22/12))+(PMT($D22/12,$F22-$AG1,$AG24)),0) -> 3453.0921 | AK24: =IF(AND(AJ1<AK$1, AK$1<=$F22),(AJ24*(1+$D22/12))+(PMT($D22/12,$F22-$AG1,$AG24)),0) -> 3355.0574 | AL24: =IF(AND(AK1<AL$1, AL$1<=$F22),(AK24*(1+$D22/12))+(PMT($D22/12,$F22-$AG1,$AG24)),0) -> 3256.6269 | AM24: =IF(AND(AL1<AM$1, AM$1<=$F22),(AL24*(1+$D22/12))+(PMT($D22/12,$F22-$AG1,$AG24)),0) -> 3157.7991 | AN24: =IF(AND(AM1<AN$1, AN$1<=$F22),(AM24*(1+$D22/12))+(PMT($D22/12,$F22-$AG1,$AG24)),0) -> 3058.5724 | AO24: =IF(AND(AN1<AO$1, AO$1<=$F22),(AN24*(1+$D22/12))+(PMT($D22/12,$F22-$AG1,$AG24)),0) -> 2958.945 | ... BQ24: =IF(AND(BP1<BQ$1, BQ$1<=$F22),(BP24*(1+$D22/12))+(PMT($D22/12,$F22-$AG1,$AG24)),0) -> -1.7337243e-12
C25: Nouvelles productions 2028 | AS25: ='Plan Moyen Terme (PMT)'!E10-BAU_Liquidité_Dynamique!AS22 -> 17882.294 | AT25: =IF(AND($AS1<AT$1, AT$1<=$F22),(AS25*(1+$D22/12))+(PMT($D22/12,$F22-$AS1,$AS25)),0) -> 17171.208 | AU25: =IF(AND($AS1<AU$1, AU$1<=$F22),(AT25*(1+$D22/12))+(PMT($D22/12,$F22-$AS1,$AS25)),0) -> 16457.252 | AV25: =IF(AND($AS1<AV$1, AV$1<=$F22),(AU25*(1+$D22/12))+(PMT($D22/12,$F22-$AS1,$AS25)),0) -> 15740.414 | AW25: =IF(AND($AS1<AW$1, AW$1<=$F22),(AV25*(1+$D22/12))+(PMT($D22/12,$F22-$AS1,$AS25)),0) -> 15020.682 | AX25: =IF(AND($AS1<AX$1, AX$1<=$F22),(AW25*(1+$D22/12))+(PMT($D22/12,$F22-$AS1,$AS25)),0) -> 14298.045 | AY25: =IF(AND($AS1<AY$1, AY$1<=$F22),(AX25*(1+$D22/12))+(PMT($D22/12,$F22-$AS1,$AS25)),0) -> 13572.49 | AZ25: =IF(AND($AS1<AZ$1, AZ$1<=$F22),(AY25*(1+$D22/12))+(PMT($D22/12,$F22-$AS1,$AS25)),0) -> 12844.006 | BA25: =IF(AND($AS1<BA$1, BA$1<=$F22),(AZ25*(1+$D22/12))+(PMT($D22/12,$F22-$AS1,$AS25)),0) -> 12112.582 | ... BQ25: =IF(AND($AS1<BQ$1, BQ$1<=$F22),(BP25*(1+$D22/12))+(PMT($D22/12,$F22-$AS1,$AS25)),0) -> -6.9348971e-12
A26: 46022 | B26: ACTIF | C26: - Autres concours à la clientèle | D26: 0.032228873 | E26: Constant | F26: 10 | G26: Constant | H26: 10 | I26: 49615.566 | J26: =IF(J$1<$F26,(I26*(1+($D26/12)))-(-PMT($D26/12,$F26,$I26)),0) -> 44713.679 | K26: =IF(K$1<$F26,(J26*(1+($D26/12)))-(-PMT($D26/12,$F26,$I26)),0) -> 39798.627 | L26: =IF(L$1<$F26,(K26*(1+($D26/12)))-(-PMT($D26/12,$F26,$I26)),0) -> 34870.374 | M26: =IF(M$1<$F26,(L26*(1+($D26/12)))-(-PMT($D26/12,$F26,$I26)),0) -> 29928.886 | N26: =IF(N$1<$F26,(M26*(1+($D26/12)))-(-PMT($D26/12,$F26,$I26)),0) -> 24974.125 | O26: =IF(O$1<$F26,(N26*(1+($D26/12)))-(-PMT($D26/12,$F26,$I26)),0) -> 20006.058 | P26: =IF(P$1<$F26,(O26*(1+($D26/12)))-(-PMT($D26/12,$F26,$I26)),0) -> 15024.648 | Q26: =IF(Q$1<$F26,(P26*(1+($D26/12)))-(-PMT($D26/12,$F26,$I26)),0) -> 10029.858 | ... DY26: =IF(DY$1<$F26,(DX26*(1+($D26/12)))-(-PMT($D26/12,$F26,$I26)),0) -> 0
C27: Nouvelles productions 2026=0
C28: Nouvelles productions 2027=0
C29: Nouvelles productions 2028=0
A30: 46022 | B30: ACTIF | C30: - Comptes ordinaires débiteurs | D30: 0.039912213 | E30: In fine | F30: 1 | G30: In fine | H30: 1 | I30: 75676.636 | J30: =IF(J$1<$F30,$I30,0) -> 0 | K30: =IF(K$1<$F30,$I30,0) -> 0 | L30: =IF(L$1<$F30,$I30,0) -> 0 | M30: =IF(M$1<$F30,$I30,0) -> 0 | N30: =IF(N$1<$F30,$I30,0) -> 0 | O30: =IF(O$1<$F30,$I30,0) -> 0 | P30: =IF(P$1<$F30,$I30,0) -> 0 | Q30: =IF(Q$1<$F30,$I30,0) -> 0 | ... DY30: =IF(DY$1<$F30,$I30,0) -> 0
C31: Nouvelles productions 2026=0
C32: Nouvelles productions 2027=0
C33: Nouvelles productions 2028=0
A34: 46022 | B34: ACTIF | C34: Investissements financiers | D34: 0.05 | E34: Ine fine | F34: 84 | G34: Ine fine | H34: 84 | I34: 28 | J34: =IF(J$1<$F34,$I34,0) -> 28 | K34: =IF(K$1<$F34,$I34,0) -> 28 | L34: =IF(L$1<$F34,$I34,0) -> 28 | M34: =IF(M$1<$F34,$I34,0) -> 28 | N34: =IF(N$1<$F34,$I34,0) -> 28 | O34: =IF(O$1<$F34,$I34,0) -> 28 | P34: =IF(P$1<$F34,$I34,0) -> 28 | Q34: =IF(Q$1<$F34,$I34,0) -> 28 | ... DY34: =IF(DY$1<$F34,$I34,0) -> 0
C35: Nouvelles productions 2026 | U35: ='Plan Moyen Terme (PMT)'!C13-U34 -> 0 | V35: =IF(AND($U1<V$1, V$1<$F$34),$U$35,0) -> 0 | W35: =IF(AND($U1<W$1, W$1<$F$34),$U$35,0) -> 0 | X35: =IF(AND($U1<X$1, X$1<$F$34),$U$35,0) -> 0 | Y35: =IF(AND($U1<Y$1, Y$1<$F$34),$U$35,0) -> 0 | Z35: =IF(AND($U1<Z$1, Z$1<$F$34),$U$35,0) -> 0 | AA35: =IF(AND($U1<AA$1, AA$1<$F$34),$U$35,0) -> 0 | AB35: =IF(AND($U1<AB$1, AB$1<$F$34),$U$35,0) -> 0 | AC35: =IF(AND($U1<AC$1, AC$1<$F$34),$U$35,0) -> 0 | ... CO35: =IF(AND($U1<CO$1, CO$1<$F$34),$U$35,0) -> 0
C36: Nouvelles productions 2027 | AG36: ='Plan Moyen Terme (PMT)'!D13-BAU_Liquidité_Dynamique!AG34 -> 9184 | AH36: =IF(AND($AG1<AH$1, AH$1<$F$34),$AG$36,0) -> 9184 | AI36: =IF(AND($AG1<AI$1, AI$1<$F$34),$AG$36,0) -> 9184 | AJ36: =IF(AND($AG1<AJ$1, AJ$1<$F$34),$AG$36,0) -> 9184 | AK36: =IF(AND($AG1<AK$1, AK$1<$F$34),$AG$36,0) -> 9184 | AL36: =IF(AND($AG1<AL$1, AL$1<$F$34),$AG$36,0) -> 9184 | AM36: =IF(AND($AG1<AM$1, AM$1<$F$34),$AG$36,0) -> 9184 | AN36: =IF(AND($AG1<AN$1, AN$1<$F$34),$AG$36,0) -> 9184 | AO36: =IF(AND($AG1<AO$1, AO$1<$F$34),$AG$36,0) -> 9184 | ... CO36: =IF(AND($AG1<CO$1, CO$1<$F$34),$AG$36,0) -> 0
C37: Nouvelles productions 2028 | AS37: ='Plan Moyen Terme (PMT)'!E13-BAU_Liquidité_Dynamique!AS34 -> 9478 | AT37: =IF(AND($AS1<AT$1, AT$1<$F$34),$AS$37,0) -> 9478 | AU37: =IF(AND($AS1<AU$1, AU$1<$F$34),$AS$37,0) -> 9478 | AV37: =IF(AND($AS1<AV$1, AV$1<$F$34),$AS$37,0) -> 9478 | AW37: =IF(AND($AS1<AW$1, AW$1<$F$34),$AS$37,0) -> 9478 | AX37: =IF(AND($AS1<AX$1, AX$1<$F$34),$AS$37,0) -> 9478 | AY37: =IF(AND($AS1<AY$1, AY$1<$F$34),$AS$37,0) -> 9478 | AZ37: =IF(AND($AS1<AZ$1, AZ$1<$F$34),$AS$37,0) -> 9478 | BA37: =IF(AND($AS1<BA$1, BA$1<$F$34),$AS$37,0) -> 9478 | ... CO37: =IF(AND($AS1<CO$1, CO$1<$F$34),$AS$37,0) -> 0
A38: 46022 | B38: ACTIF | C38: Immobilisations corporelles et incorporelles | E38: Linéaire | F38: 120 | G38: Linéaire | H38: 120 | I38: 82 | J38: =IF(J$1<$F38,$I38*(($F38-J$1)/$F38),0) -> 81.316667 | K38: =IF(K$1<$F38,$I38*(($F38-K$1)/$F38),0) -> 80.633333 | L38: =IF(L$1<$F38,$I38*(($F38-L$1)/$F38),0) -> 79.95 | M38: =IF(M$1<$F38,$I38*(($F38-M$1)/$F38),0) -> 79.266667 | N38: =IF(N$1<$F38,$I38*(($F38-N$1)/$F38),0) -> 78.583333 | O38: =IF(O$1<$F38,$I38*(($F38-O$1)/$F38),0) -> 77.9 | P38: =IF(P$1<$F38,$I38*(($F38-P$1)/$F38),0) -> 77.216667 | Q38: =IF(Q$1<$F38,$I38*(($F38-Q$1)/$F38),0) -> 76.533333 | ... DY38: =IF(DY$1<$F38,$I38*(($F38-DY$1)/$F38),0) -> 0
C39: Nouvelles productions 2026 | U39: ='Plan Moyen Terme (PMT)'!C14-BAU_Liquidité_Dynamique!U38 -> -13.8 | V39: =IF(AND(U$1<V$1, V$1<=$F38),$U39*($F38-V$1)/($F38-$U$1),0) -> -13.672222 | W39: =IF(AND(V$1<W$1, W$1<=$F38),$U39*($F38-W$1)/($F38-$U$1),0) -> -13.544444 | X39: =IF(AND(W$1<X$1, X$1<=$F38),$U39*($F38-X$1)/($F38-$U$1),0) -> -13.416667 | Y39: =IF(AND(X$1<Y$1, Y$1<=$F38),$U39*($F38-Y$1)/($F38-$U$1),0) -> -13.288889 | Z39: =IF(AND(Y$1<Z$1, Z$1<=$F38),$U39*($F38-Z$1)/($F38-$U$1),0) -> -13.161111 | AA39: =IF(AND(Z$1<AA$1, AA$1<=$F38),$U39*($F38-AA$1)/($F38-$U$1),0) -> -13.033333 | AB39: =IF(AND(AA$1<AB$1, AB$1<=$F38),$U39*($F38-AB$1)/($F38-$U$1),0) -> -12.905556 | AC39: =IF(AND(AB$1<AC$1, AC$1<=$F38),$U39*($F38-AC$1)/($F38-$U$1),0) -> -12.777778 | ... DY39: =IF(AND(DX$1<DY$1, DY$1<=$F38),$U39*($F38-DY$1)/($F38-$U$1),0) -> 0
C40: Nouvelles productions 2027 | AG40: ='Plan Moyen Terme (PMT)'!D14-BAU_Liquidité_Dynamique!AG38 -> 1.4 | AH40: =IF(AND(AG$1<AH$1, AH$1<=$F38),$AG40*($F38-AH$1)/($F38-$AG$1),0) -> 1.3854167 | AI40: =IF(AND(AH$1<AI$1, AI$1<=$F38),$AG40*($F38-AI$1)/($F38-$AG$1),0) -> 1.3708333 | AJ40: =IF(AND(AI$1<AJ$1, AJ$1<=$F38),$AG40*($F38-AJ$1)/($F38-$AG$1),0) -> 1.35625 | AK40: =IF(AND(AJ$1<AK$1, AK$1<=$F38),$AG40*($F38-AK$1)/($F38-$AG$1),0) -> 1.3416667 | AL40: =IF(AND(AK$1<AL$1, AL$1<=$F38),$AG40*($F38-AL$1)/($F38-$AG$1),0) -> 1.3270833 | AM40: =IF(AND(AL$1<AM$1, AM$1<=$F38),$AG40*($F38-AM$1)/($F38-$AG$1),0) -> 1.3125 | AN40: =IF(AND(AM$1<AN$1, AN$1<=$F38),$AG40*($F38-AN$1)/($F38-$AG$1),0) -> 1.2979167 | AO40: =IF(AND(AN$1<AO$1, AO$1<=$F38),$AG40*($F38-AO$1)/($F38-$AG$1),0) -> 1.2833333 | ... DY40: =IF(AND(DX$1<DY$1, DY$1<=$F38),$AG40*($F38-DY$1)/($F38-$AG$1),0) -> 0
C41: Nouvelles productions 2028 | AS41: ='Plan Moyen Terme (PMT)'!E14-BAU_Liquidité_Dynamique!AS38 -> -4.4 | AT41: =IF(AND(AS$1<AT$1, AT$1<=$F38),$AS41*($F38-AT$1)/($F38-$AS$1),0) -> -4.347619 | AU41: =IF(AND(AT$1<AU$1, AU$1<=$F38),$AS41*($F38-AU$1)/($F38-$AS$1),0) -> -4.2952381 | AV41: =IF(AND(AU$1<AV$1, AV$1<=$F38),$AS41*($F38-AV$1)/($F38-$AS$1),0) -> -4.2428571 | AW41: =IF(AND(AV$1<AW$1, AW$1<=$F38),$AS41*($F38-AW$1)/($F38-$AS$1),0) -> -4.1904762 | AX41: =IF(AND(AW$1<AX$1, AX$1<=$F38),$AS41*($F38-AX$1)/($F38-$AS$1),0) -> -4.1380952 | AY41: =IF(AND(AX$1<AY$1, AY$1<=$F38),$AS41*($F38-AY$1)/($F38-$AS$1),0) -> -4.0857143 | AZ41: =IF(AND(AY$1<AZ$1, AZ$1<=$F38),$AS41*($F38-AZ$1)/($F38-$AS$1),0) -> -4.0333333 | BA41: =IF(AND(AZ$1<BA$1, BA$1<=$F38),$AS41*($F38-BA$1)/($F38-$AS$1),0) -> -3.9809524 | ... DY41: =IF(AND(DX$1<DY$1, DY$1<=$F38),$AS41*($F38-DY$1)/($F38-$AS$1),0) -> 0
A42: 46022 | B42: ACTIF | C42: Autres actifs | E42: Linéaire | F42: 120 | G42: Linéaire | H42: 120 | I42: 570 | J42: =IF(J$1<$F42,$I42*(($F42-J$1)/$F42),0) -> 565.25 | K42: =IF(K$1<$F42,$I42*(($F42-K$1)/$F42),0) -> 560.5 | L42: =IF(L$1<$F42,$I42*(($F42-L$1)/$F42),0) -> 555.75 | M42: =IF(M$1<$F42,$I42*(($F42-M$1)/$F42),0) -> 551 | N42: =IF(N$1<$F42,$I42*(($F42-N$1)/$F42),0) -> 546.25 | O42: =IF(O$1<$F42,$I42*(($F42-O$1)/$F42),0) -> 541.5 | P42: =IF(P$1<$F42,$I42*(($F42-P$1)/$F42),0) -> 536.75 | Q42: =IF(Q$1<$F42,$I42*(($F42-Q$1)/$F42),0) -> 532 | ... DY42: =IF(DY$1<$F42,$I42*(($F42-DY$1)/$F42),0) -> 0
C43: Nouvelles productions 2026 | U43: ='Plan Moyen Terme (PMT)'!C15-BAU_Liquidité_Dynamique!U42 -> -3 | V43: =IF(AND(U$1<V$1, V$1<=$F42),$U43*($F42-V$1)/($F42-$U$1),0) -> -2.9722222 | W43: =IF(AND(V$1<W$1, W$1<=$F42),$U43*($F42-W$1)/($F42-$U$1),0) -> -2.9444444 | X43: =IF(AND(W$1<X$1, X$1<=$F42),$U43*($F42-X$1)/($F42-$U$1),0) -> -2.9166667 | Y43: =IF(AND(X$1<Y$1, Y$1<=$F42),$U43*($F42-Y$1)/($F42-$U$1),0) -> -2.8888889 | Z43: =IF(AND(Y$1<Z$1, Z$1<=$F42),$U43*($F42-Z$1)/($F42-$U$1),0) -> -2.8611111 | AA43: =IF(AND(Z$1<AA$1, AA$1<=$F42),$U43*($F42-AA$1)/($F42-$U$1),0) -> -2.8333333 | AB43: =IF(AND(AA$1<AB$1, AB$1<=$F42),$U43*($F42-AB$1)/($F42-$U$1),0) -> -2.8055556 | AC43: =IF(AND(AB$1<AC$1, AC$1<=$F42),$U43*($F42-AC$1)/($F42-$U$1),0) -> -2.7777778 | ... DY43: =IF(AND(DX$1<DY$1, DY$1<=$F42),$U43*($F42-DY$1)/($F42-$U$1),0) -> 0
C44: Nouvelles productions 2027 | AG44: ='Plan Moyen Terme (PMT)'!D15-BAU_Liquidité_Dynamique!AG42 -> 688 | AH44: =IF(AND(AG$1<AH$1, AH$1<=$F42),$AG44*($F42-AH$1)/($F42-$AG$1),0) -> 680.83333 | AI44: =IF(AND(AH$1<AI$1, AI$1<=$F42),$AG44*($F42-AI$1)/($F42-$AG$1),0) -> 673.66667 | AJ44: =IF(AND(AI$1<AJ$1, AJ$1<=$F42),$AG44*($F42-AJ$1)/($F42-$AG$1),0) -> 666.5 | AK44: =IF(AND(AJ$1<AK$1, AK$1<=$F42),$AG44*($F42-AK$1)/($F42-$AG$1),0) -> 659.33333 | AL44: =IF(AND(AK$1<AL$1, AL$1<=$F42),$AG44*($F42-AL$1)/($F42-$AG$1),0) -> 652.16667 | AM44: =IF(AND(AL$1<AM$1, AM$1<=$F42),$AG44*($F42-AM$1)/($F42-$AG$1),0) -> 645 | AN44: =IF(AND(AM$1<AN$1, AN$1<=$F42),$AG44*($F42-AN$1)/($F42-$AG$1),0) -> 637.83333 | AO44: =IF(AND(AN$1<AO$1, AO$1<=$F42),$AG44*($F42-AO$1)/($F42-$AG$1),0) -> 630.66667 | ... DY44: =IF(AND(DX$1<DY$1, DY$1<=$F42),$AG44*($F42-DY$1)/($F42-$AG$1),0) -> 0
C45: Nouvelles productions 2028 | AS45: ='Plan Moyen Terme (PMT)'!E15-BAU_Liquidité_Dynamique!AS42 -> 1628 | AT45: =IF(AND(AS$1<AT$1, AT$1<=$F42),$AS45*($F42-AT$1)/($F42-$AS$1),0) -> 1608.619 | AU45: =IF(AND(AT$1<AU$1, AU$1<=$F42),$AS45*($F42-AU$1)/($F42-$AS$1),0) -> 1589.2381 | AV45: =IF(AND(AU$1<AV$1, AV$1<=$F42),$AS45*($F42-AV$1)/($F42-$AS$1),0) -> 1569.8571 | AW45: =IF(AND(AV$1<AW$1, AW$1<=$F42),$AS45*($F42-AW$1)/($F42-$AS$1),0) -> 1550.4762 | AX45: =IF(AND(AW$1<AX$1, AX$1<=$F42),$AS45*($F42-AX$1)/($F42-$AS$1),0) -> 1531.0952 | AY45: =IF(AND(AX$1<AY$1, AY$1<=$F42),$AS45*($F42-AY$1)/($F42-$AS$1),0) -> 1511.7143 | AZ45: =IF(AND(AY$1<AZ$1, AZ$1<=$F42),$AS45*($F42-AZ$1)/($F42-$AS$1),0) -> 1492.3333 | BA45: =IF(AND(AZ$1<BA$1, BA$1<=$F42),$AS45*($F42-BA$1)/($F42-$AS$1),0) -> 1472.9524 | ... DY45: =IF(AND(DX$1<DY$1, DY$1<=$F42),$AS45*($F42-DY$1)/($F42-$AS$1),0) -> 0
C46: Total nouvelle production actif-2026 | I46: =SUM(I5+I9+I14+I18+I23+I27+I31+I35+I39+I43) -> 0 | J46: =SUM(J5+J9+J14+J18+J23+J27+J31+J35+J39+J43) -> 0 | K46: =SUM(K5+K9+K14+K18+K23+K27+K31+K35+K39+K43) -> 0 | L46: =SUM(L5+L9+L14+L18+L23+L27+L31+L35+L39+L43) -> 0 | M46: =SUM(M5+M9+M14+M18+M23+M27+M31+M35+M39+M43) -> 0 | N46: =SUM(N5+N9+N14+N18+N23+N27+N31+N35+N39+N43) -> 0 | O46: =SUM(O5+O9+O14+O18+O23+O27+O31+O35+O39+O43) -> 0 | P46: =SUM(P5+P9+P14+P18+P23+P27+P31+P35+P39+P43) -> 0 | ... DY46: =SUM(DY5+DY9+DY14+DY18+DY23+DY27+DY31+DY35+DY39+DY43) -> 0
C47: Total nouvelle production actif-2027 | I47: =SUM(I6+I10+I15+I19+I24+I28+I32+I36+I40+I44) -> 0 | J47: =SUM(J6+J10+J15+J19+J24+J28+J32+J36+J40+J44) -> -6.7325943 | K47: =SUM(K6+K10+K15+K19+K24+K28+K32+K36+K40+K44) -> 1.4456894 | L47: =SUM(L6+L10+L15+L19+L24+L28+L32+L36+L40+L44) -> 0 | M47: =SUM(M6+M10+M15+M19+M24+M28+M32+M36+M40+M44) -> 0 | N47: =SUM(N6+N10+N15+N19+N24+N28+N32+N36+N40+N44) -> 0 | O47: =SUM(O6+O10+O15+O19+O24+O28+O32+O36+O40+O44) -> 0 | P47: =SUM(P6+P10+P15+P19+P24+P28+P32+P36+P40+P44) -> 0 | ... DY47: =SUM(DY6+DY10+DY15+DY19+DY24+DY28+DY32+DY36+DY40+DY44) -> 0
C48: Total nouvelle production actif-2028 | I48: =SUM(I7+I11+I16+I20+I25+I29+I33+I37+I41+I45) -> 0 | J48: =SUM(J7+J11+J16+J20+J25+J29+J33+J37+J41+J45) -> 0 | K48: =SUM(K7+K11+K16+K20+K25+K29+K33+K37+K41+K45) -> 0 | L48: =SUM(L7+L11+L16+L20+L25+L29+L33+L37+L41+L45) -> 0 | M48: =SUM(M7+M11+M16+M20+M25+M29+M33+M37+M41+M45) -> 0 | N48: =SUM(N7+N11+N16+N20+N25+N29+N33+N37+N41+N45) -> 0 | O48: =SUM(O7+O11+O16+O20+O25+O29+O33+O37+O41+O45) -> 0 | P48: =SUM(P7+P11+P16+P20+P25+P29+P33+P37+P41+P45) -> 0 | ... DY48: =SUM(DY7+DY11+DY16+DY20+DY25+DY29+DY33+DY37+DY41+DY45) -> 0
A49: 46022 | B49: ACTIF | C49: Total actif | I49: =I3+I12+I21+I34+I38+I42 -> 155592.39 | J49: =J3+J12+J21+J34+J38+J42 -> 71811.302 | K49: =K3+K12+K21+K34+K38+K42 -> 63693.665 | L49: =L3+L12+L21+L34+L38+L42 -> 55562.806 | M49: =M3+M12+M21+M34+M38+M42 -> 47418.689 | N49: =N3+N12+N21+N34+N38+N42 -> 39261.28 | O49: =O3+O12+O21+O34+O38+O42 -> 31090.541 | P49: =P3+P12+P21+P34+P38+P42 -> 26087.483 | ... DY49: =DY3+DY12+DY21+DY34+DY38+DY42 -> 0
A50: 46022 | B50: PASSIF | C50: DETTES ENVERS ETS DE CREDIT | I50: =I51+I55 -> 74095.3 | J50: =SUM(J51:J55) -> 73528.24 | K50: =SUM(K51:K55) -> 73150.2 | L50: =SUM(L51:L55) -> 72772.16 | M50: =SUM(M51:M55) -> 72394.12 | N50: =SUM(N51:N55) -> 72205.1 | O50: =SUM(O51:O55) -> 72205.1 | P50: =SUM(P51:P55) -> 72205.1 | Q50: =SUM(Q51:Q55) -> 72205.1 | ... DY50: =SUM(DY51:DY55) -> 0
A51: 46022 | B51: PASSIF | C51: - A vue | D51: 0 | E51: 90%-20%*t, t<=4mois | F51: 4 | G51: In fine | H51: 4 | I51: 1890.2 | J51: =IF(J$1<=$F51,$I51*(90%-(20%*J$1)),0) -> 1323.14 | K51: =IF(K$1<=$F51,$I51*(90%-(20%*K$1)),0) -> 945.1 | L51: =IF(L$1<=$F51,$I51*(90%-(20%*L$1)),0) -> 567.06 | M51: =IF(M$1<=$F51,$I51*(90%-(20%*M$1)),0) -> 189.02 | N51: =IF(N$1<=$F51,$I51*(90%-(20%*N$1)),0) -> 0 | O51: =IF(O$1<=$F51,$I51*(90%-(20%*O$1)),0) -> 0 | P51: =IF(P$1<=$F51,$I51*(90%-(20%*P$1)),0) -> 0 | Q51: =IF(Q$1<=$F51,$I51*(90%-(20%*Q$1)),0) -> 0 | ... DY51: =IF(DY$1<=$F51,$I51*(90%-(20%*DY$1)),0) -> 0
C52: Nouvelles productions 2026=0
C53: Nouvelles productions 2027=0
C54: Nouvelles productions 2028=0
A55: 46022 | B55: PASSIF | C55: - A terme | D55: 0.0138965 | E55: Ine fine | F55: 24 | G55: Ine fine | H55: 24 | I55: 72205.1 | J55: =IF(J$1<$F55,$I55,0) -> 72205.1 | K55: =IF(K$1<$F55,$I55,0) -> 72205.1 | L55: =IF(L$1<$F55,$I55,0) -> 72205.1 | M55: =IF(M$1<$F55,$I55,0) -> 72205.1 | N55: =IF(N$1<$F55,$I55,0) -> 72205.1 | O55: =IF(O$1<$F55,$I55,0) -> 72205.1 | P55: =IF(P$1<$F55,$I55,0) -> 72205.1 | Q55: =IF(Q$1<$F55,$I55,0) -> 72205.1 | ... DY55: =IF(DY$1<$F55,$I55,0) -> 0
C56: Nouvelles productions 2026 | U56: ='Plan Moyen Terme (PMT)'!C19-BAU_Liquidité_Dynamique!U55 -> 16804.9 | V56: =IF(AND($U$1<V$1, V$1<$F$55),$U$56,0) -> 16804.9 | W56: =IF(AND($U$1<W$1, W$1<$F$55),$U$56,0) -> 16804.9 | X56: =IF(AND($U$1<X$1, X$1<$F$55),$U$56,0) -> 16804.9 | Y56: =IF(AND($U$1<Y$1, Y$1<$F$55),$U$56,0) -> 16804.9 | Z56: =IF(AND($U$1<Z$1, Z$1<$F$55),$U$56,0) -> 16804.9 | AA56: =IF(AND($U$1<AA$1, AA$1<$F$55),$U$56,0) -> 16804.9 | AB56: =IF(AND($U$1<AB$1, AB$1<$F$55),$U$56,0) -> 16804.9 | AC56: =IF(AND($U$1<AC$1, AC$1<$F$55),$U$56,0) -> 16804.9 | ... AG56: =IF(AND($U$1<AG$1, AG$1<$F$55),$U$56,0) -> 0
C57: Nouvelles productions 2027=0
C58: Nouvelles productions 2028=0
A59: 46022 | B59: PASSIF | C59: CPTES CREDITEURS DE LA CLIENTELE | I59: =I60+I64 -> 50161.059 | J59: =SUM(J60:J64) -> 43848.513 | K59: =SUM(K60:K64) -> 40644.299 | L59: =SUM(L60:L64) -> 38020.91 | M59: =SUM(M60:M64) -> 35873.06 | N59: =SUM(N60:N64) -> 34114.55 | O59: =SUM(O60:O64) -> 32674.804 | P59: =SUM(P60:P64) -> 31496.039 | Q59: =SUM(Q60:Q64) -> 30530.948 | ... DY59: =SUM(DY60:DY64) -> 8.1505852e-07
A60: 46022 | B60: PASSIF | C60: - A vue | D60: 0 | E60: 90%*exp(-20%*t), t<=120 mois | F60: 120 | G60: Linéaire | H60: 120 | I60: 23989.094 | J60: =IF(J$1<=$F60,$I60*(90%*EXP(-20%*J$1)),0) -> 17676.548 | K60: =IF(K$1<=$F60,$I60*(90%*EXP(-20%*K$1)),0) -> 14472.334 | L60: =IF(L$1<=$F60,$I60*(90%*EXP(-20%*L$1)),0) -> 11848.945 | M60: =IF(M$1<=$F60,$I60*(90%*EXP(-20%*M$1)),0) -> 9701.0953 | N60: =IF(N$1<=$F60,$I60*(90%*EXP(-20%*N$1)),0) -> 7942.585 | O60: =IF(O$1<=$F60,$I60*(90%*EXP(-20%*O$1)),0) -> 6502.8386 | P60: =IF(P$1<=$F60,$I60*(90%*EXP(-20%*P$1)),0) -> 5324.074 | Q60: =IF(Q$1<=$F60,$I60*(90%*EXP(-20%*Q$1)),0) -> 4358.9831 | ... DY60: =IF(DY$1<=$F60,$I60*(90%*EXP(-20%*DY$1)),0) -> 8.1505852e-07
C61: Nouvelles productions 2026 | U61: ='Plan Moyen Terme (PMT)'!C21-BAU_Liquidité_Dynamique!U60 -> 16491.383 | V61: =IF(AND($U$1<V$1, V$1<$F$60),$U61*(90%*EXP(-20%*(V$1-$U$1))),0) -> 12151.802 | W61: =IF(AND($U$1<W$1, W$1<$F$60),$U61*(90%*EXP(-20%*(W$1-$U$1))),0) -> 9949.0539 | X61: =IF(AND($U$1<X$1, X$1<$F$60),$U61*(90%*EXP(-20%*(X$1-$U$1))),0) -> 8145.5964 | Y61: =IF(AND($U$1<Y$1, Y$1<$F$60),$U61*(90%*EXP(-20%*(Y$1-$U$1))),0) -> 6669.0503 | Z61: =IF(AND($U$1<Z$1, Z$1<$F$60),$U61*(90%*EXP(-20%*(Z$1-$U$1))),0) -> 5460.1566 | AA61: =IF(AND($U$1<AA$1, AA$1<$F$60),$U61*(90%*EXP(-20%*(AA$1-$U$1))),0) -> 4470.3981 | AB61: =IF(AND($U$1<AB$1, AB$1<$F$60),$U61*(90%*EXP(-20%*(AB$1-$U$1))),0) -> 3660.0524 | AC61: =IF(AND($U$1<AC$1, AC$1<$F$60),$U61*(90%*EXP(-20%*(AC$1-$U$1))),0) -> 2996.5975 | ... DY61: =IF(AND($U$1<DY$1, DY$1<$F$60),$U61*(90%*EXP(-20%*(DY$1-$U$1))),0) -> 0
C62: Nouvelles productions 2027 | AG62: ='Plan Moyen Terme (PMT)'!D21-BAU_Liquidité_Dynamique!AG60 -> 33064.318 | AH62: =IF(AND($AG$1<AH$1, AH$1<$F$60),$AG62*(90%*EXP(-20%*(AH$1-$AG$1))),0) -> 24363.697 | AI62: =IF(AND($AG$1<AI$1, AI$1<$F$60),$AG62*(90%*EXP(-20%*(AI$1-$AG$1))),0) -> 19947.308 | AJ62: =IF(AND($AG$1<AJ$1, AJ$1<$F$60),$AG62*(90%*EXP(-20%*(AJ$1-$AG$1))),0) -> 16331.474 | AK62: =IF(AND($AG$1<AK$1, AK$1<$F$60),$AG62*(90%*EXP(-20%*(AK$1-$AG$1))),0) -> 13371.08 | AL62: =IF(AND($AG$1<AL$1, AL$1<$F$60),$AG62*(90%*EXP(-20%*(AL$1-$AG$1))),0) -> 10947.315 | AM62: =IF(AND($AG$1<AM$1, AM$1<$F$60),$AG62*(90%*EXP(-20%*(AM$1-$AG$1))),0) -> 8962.9031 | AN62: =IF(AND($AG$1<AN$1, AN$1<$F$60),$AG62*(90%*EXP(-20%*(AN$1-$AG$1))),0) -> 7338.2044 | AO62: =IF(AND($AG$1<AO$1, AO$1<$F$60),$AG62*(90%*EXP(-20%*(AO$1-$AG$1))),0) -> 6008.0137 | ... DY62: =IF(AND($AG$1<DY$1, DY$1<$F$60),$AG62*(90%*EXP(-20%*(DY$1-$AG$1))),0) -> 0
C63: Nouvelles productions 2028 | AS63: ='Plan Moyen Terme (PMT)'!E21-BAU_Liquidité_Dynamique!AS60 -> 39595.881 | AT63: =IF(AND($AS$1<AT$1, AT$1<$F$60),$AS63*(90%*EXP(-20%*(AT$1-$AS$1))),0) -> 29176.529 | AU63: =IF(AND($AS$1<AU$1, AU$1<$F$60),$AS63*(90%*EXP(-20%*(AU$1-$AS$1))),0) -> 23887.722 | AV63: =IF(AND($AS$1<AV$1, AV$1<$F$60),$AS63*(90%*EXP(-20%*(AV$1-$AS$1))),0) -> 19557.612 | AW63: =IF(AND($AS$1<AW$1, AW$1<$F$60),$AS63*(90%*EXP(-20%*(AW$1-$AS$1))),0) -> 16012.419 | AX63: =IF(AND($AS$1<AX$1, AX$1<$F$60),$AS63*(90%*EXP(-20%*(AX$1-$AS$1))),0) -> 13109.86 | AY63: =IF(AND($AS$1<AY$1, AY$1<$F$60),$AS63*(90%*EXP(-20%*(AY$1-$AS$1))),0) -> 10733.445 | AZ63: =IF(AND($AS$1<AZ$1, AZ$1<$F$60),$AS63*(90%*EXP(-20%*(AZ$1-$AS$1))),0) -> 8787.8017 | BA63: =IF(AND($AS$1<BA$1, BA$1<$F$60),$AS63*(90%*EXP(-20%*(BA$1-$AS$1))),0) -> 7194.8435 | ... DY63: =IF(AND($AS$1<DY$1, DY$1<$F$60),$AS63*(90%*EXP(-20%*(DY$1-$AS$1))),0) -> 0
A64: 46022 | B64: PASSIF | C64: - A terme | D64: 0.0083386457 | E64: In fine | F64: 60 | G64: In fine | H64: 60 | I64: 26171.965 | J64: =IF(J$1<$F64,$I64,0) -> 26171.965 | K64: =IF(K$1<$F64,$I64,0) -> 26171.965 | L64: =IF(L$1<$F64,$I64,0) -> 26171.965 | M64: =IF(M$1<$F64,$I64,0) -> 26171.965 | N64: =IF(N$1<$F64,$I64,0) -> 26171.965 | O64: =IF(O$1<$F64,$I64,0) -> 26171.965 | P64: =IF(P$1<$F64,$I64,0) -> 26171.965 | Q64: =IF(Q$1<$F64,$I64,0) -> 26171.965 | ... DY64: =IF(DY$1<$F64,$I64,0) -> 0
C65: Nouvelles productions 2026 | U65: ='Plan Moyen Terme (PMT)'!C22-BAU_Liquidité_Dynamique!U64 -> 12327.035 | V65: =IF(AND($U$1<V$1, V$1<$F$64),$U$65,0) -> 12327.035 | W65: =IF(AND($U$1<W$1, W$1<$F$64),$U$65,0) -> 12327.035 | X65: =IF(AND($U$1<X$1, X$1<$F$64),$U$65,0) -> 12327.035 | Y65: =IF(AND($U$1<Y$1, Y$1<$F$64),$U$65,0) -> 12327.035 | Z65: =IF(AND($U$1<Z$1, Z$1<$F$64),$U$65,0) -> 12327.035 | AA65: =IF(AND($U$1<AA$1, AA$1<$F$64),$U$65,0) -> 12327.035 | AB65: =IF(AND($U$1<AB$1, AB$1<$F$64),$U$65,0) -> 12327.035 | AC65: =IF(AND($U$1<AC$1, AC$1<$F$64),$U$65,0) -> 12327.035 | ... BQ65: =IF(AND($U$1<BQ$1, BQ$1<$F$64),$U$65,0) -> 0
C66: Nouvelles productions 2027 | AG66: ='Plan Moyen Terme (PMT)'!D22-BAU_Liquidité_Dynamique!AG64 -> 42098.035 | AH66: =IF(AND($AG$1<AH$1, AH$1<$F$64),$AG$66,0) -> 42098.035 | AI66: =IF(AND($AG$1<AI$1, AI$1<$F$64),$AG$66,0) -> 42098.035 | AJ66: =IF(AND($AG$1<AJ$1, AJ$1<$F$64),$AG$66,0) -> 42098.035 | AK66: =IF(AND($AG$1<AK$1, AK$1<$F$64),$AG$66,0) -> 42098.035 | AL66: =IF(AND($AG$1<AL$1, AL$1<$F$64),$AG$66,0) -> 42098.035 | AM66: =IF(AND($AG$1<AM$1, AM$1<$F$64),$AG$66,0) -> 42098.035 | AN66: =IF(AND($AG$1<AN$1, AN$1<$F$64),$AG$66,0) -> 42098.035 | AO66: =IF(AND($AG$1<AO$1, AO$1<$F$64),$AG$66,0) -> 42098.035 | ... BQ66: =IF(AND($AG$1<BQ$1, BQ$1<$F$64),$AG$66,0) -> 0
C67: Nouvelles productions 2028 | AS67: ='Plan Moyen Terme (PMT)'!E22-BAU_Liquidité_Dynamique!AS64 -> 70305.035 | AT67: =IF(AND($AS$1<AT$1, AT$1<$F$64),$AS$67,0) -> 70305.035 | AU67: =IF(AND($AS$1<AU$1, AU$1<$F$64),$AS$67,0) -> 70305.035 | AV67: =IF(AND($AS$1<AV$1, AV$1<$F$64),$AS$67,0) -> 70305.035 | AW67: =IF(AND($AS$1<AW$1, AW$1<$F$64),$AS$67,0) -> 70305.035 | AX67: =IF(AND($AS$1<AX$1, AX$1<$F$64),$AS$67,0) -> 70305.035 | AY67: =IF(AND($AS$1<AY$1, AY$1<$F$64),$AS$67,0) -> 70305.035 | AZ67: =IF(AND($AS$1<AZ$1, AZ$1<$F$64),$AS$67,0) -> 70305.035 | BA67: =IF(AND($AS$1<BA$1, BA$1<$F$64),$AS$67,0) -> 70305.035 | ... BQ67: =IF(AND($AS$1<BQ$1, BQ$1<$F$64),$AS$67,0) -> 0
A68: 46022 | B68: PASSIF | C68: Autres passifs | D68: 0 | E68: Linéaire | F68: 120 | G68: Linéaire | H68: 120 | I68: 2297.337 | J68: =IF(J$1<$F68,$I68*(($F68-J$1)/$F68),0) -> 2278.1925 | K68: =IF(K$1<$F68,$I68*(($F68-K$1)/$F68),0) -> 2259.048 | L68: =IF(L$1<$F68,$I68*(($F68-L$1)/$F68),0) -> 2239.9036 | M68: =IF(M$1<$F68,$I68*(($F68-M$1)/$F68),0) -> 2220.7591 | N68: =IF(N$1<$F68,$I68*(($F68-N$1)/$F68),0) -> 2201.6146 | O68: =IF(O$1<$F68,$I68*(($F68-O$1)/$F68),0) -> 2182.4702 | P68: =IF(P$1<$F68,$I68*(($F68-P$1)/$F68),0) -> 2163.3257 | Q68: =IF(Q$1<$F68,$I68*(($F68-Q$1)/$F68),0) -> 2144.1812 | ... DY68: =IF(DY$1<$F68,$I68*(($F68-DY$1)/$F68),0) -> 0
C69: Nouvelles productions 2026 | U69: ='Plan Moyen Terme (PMT)'!C23-BAU_Liquidité_Dynamique!U68 -> 255.3967 | V69: =IF(AND(U$1<V$1, V$1<=$F68),$U69*($F68-V$1)/($F68-$U$1),0) -> 253.03192 | W69: =IF(AND(V$1<W$1, W$1<=$F68),$U69*($F68-W$1)/($F68-$U$1),0) -> 250.66713 | X69: =IF(AND(W$1<X$1, X$1<=$F68),$U69*($F68-X$1)/($F68-$U$1),0) -> 248.30235 | Y69: =IF(AND(X$1<Y$1, Y$1<=$F68),$U69*($F68-Y$1)/($F68-$U$1),0) -> 245.93756 | Z69: =IF(AND(Y$1<Z$1, Z$1<=$F68),$U69*($F68-Z$1)/($F68-$U$1),0) -> 243.57278 | AA69: =IF(AND(Z$1<AA$1, AA$1<=$F68),$U69*($F68-AA$1)/($F68-$U$1),0) -> 241.20799 | AB69: =IF(AND(AA$1<AB$1, AB$1<=$F68),$U69*($F68-AB$1)/($F68-$U$1),0) -> 238.84321 | AC69: =IF(AND(AB$1<AC$1, AC$1<=$F68),$U69*($F68-AC$1)/($F68-$U$1),0) -> 236.47843 | ... DY69: =IF(AND(DX$1<DY$1, DY$1<=$F68),$U69*($F68-DY$1)/($F68-$U$1),0) -> 0
C70: Nouvelles productions 2027 | AG70: ='Plan Moyen Terme (PMT)'!D23-BAU_Liquidité_Dynamique!AG68 -> 1902.1304 | AH70: =IF(AND(AG$1<AH$1, AH$1<=$F68),$AG70*($F68-AH$1)/($F68-$AG$1),0) -> 1882.3165 | AI70: =IF(AND(AH$1<AI$1, AI$1<=$F68),$AG70*($F68-AI$1)/($F68-$AG$1),0) -> 1862.5027 | AJ70: =IF(AND(AI$1<AJ$1, AJ$1<=$F68),$AG70*($F68-AJ$1)/($F68-$AG$1),0) -> 1842.6888 | AK70: =IF(AND(AJ$1<AK$1, AK$1<=$F68),$AG70*($F68-AK$1)/($F68-$AG$1),0) -> 1822.875 | AL70: =IF(AND(AK$1<AL$1, AL$1<=$F68),$AG70*($F68-AL$1)/($F68-$AG$1),0) -> 1803.0611 | AM70: =IF(AND(AL$1<AM$1, AM$1<=$F68),$AG70*($F68-AM$1)/($F68-$AG$1),0) -> 1783.2473 | AN70: =IF(AND(AM$1<AN$1, AN$1<=$F68),$AG70*($F68-AN$1)/($F68-$AG$1),0) -> 1763.4334 | AO70: =IF(AND(AN$1<AO$1, AO$1<=$F68),$AG70*($F68-AO$1)/($F68-$AG$1),0) -> 1743.6195 | ... DY70: =IF(AND(DX$1<DY$1, DY$1<=$F68),$AG70*($F68-DY$1)/($F68-$AG$1),0) -> 0
C71: Nouvelles productions 2028 | AS71: ='Plan Moyen Terme (PMT)'!E23-BAU_Liquidité_Dynamique!AS68 -> 1277.8641 | AT71: =IF(AND(AS$1<AT$1, AT$1<=$F68),$AS71*($F68-AT$1)/($F68-$AS$1),0) -> 1262.6514 | AU71: =IF(AND(AT$1<AU$1, AU$1<=$F68),$AS71*($F68-AU$1)/($F68-$AS$1),0) -> 1247.4388 | AV71: =IF(AND(AU$1<AV$1, AV$1<=$F68),$AS71*($F68-AV$1)/($F68-$AS$1),0) -> 1232.2261 | AW71: =IF(AND(AV$1<AW$1, AW$1<=$F68),$AS71*($F68-AW$1)/($F68-$AS$1),0) -> 1217.0134 | AX71: =IF(AND(AW$1<AX$1, AX$1<=$F68),$AS71*($F68-AX$1)/($F68-$AS$1),0) -> 1201.8008 | AY71: =IF(AND(AX$1<AY$1, AY$1<=$F68),$AS71*($F68-AY$1)/($F68-$AS$1),0) -> 1186.5881 | AZ71: =IF(AND(AY$1<AZ$1, AZ$1<=$F68),$AS71*($F68-AZ$1)/($F68-$AS$1),0) -> 1171.3754 | BA71: =IF(AND(AZ$1<BA$1, BA$1<=$F68),$AS71*($F68-BA$1)/($F68-$AS$1),0) -> 1156.1628 | ... DY71: =IF(AND(DX$1<DY$1, DY$1<=$F68),$AS71*($F68-DY$1)/($F68-$AS$1),0) -> 0
A72: 46022 | B72: PASSIF | C72: Provisions pour risques et charges | D72: 0 | E72: Linéaire | F72: 120 | G72: Linéaire | H72: 120 | I72: 2994.787 | J72: =IF(J$1<$F72,$I72*(($F72-J$1)/$F72),0) -> 2969.8304 | K72: =IF(K$1<$F72,$I72*(($F72-K$1)/$F72),0) -> 2944.8739 | L72: =IF(L$1<$F72,$I72*(($F72-L$1)/$F72),0) -> 2919.9173 | M72: =IF(M$1<$F72,$I72*(($F72-M$1)/$F72),0) -> 2894.9608 | N72: =IF(N$1<$F72,$I72*(($F72-N$1)/$F72),0) -> 2870.0042 | O72: =IF(O$1<$F72,$I72*(($F72-O$1)/$F72),0) -> 2845.0476 | P72: =IF(P$1<$F72,$I72*(($F72-P$1)/$F72),0) -> 2820.0911 | Q72: =IF(Q$1<$F72,$I72*(($F72-Q$1)/$F72),0) -> 2795.1345 | ... DY72: =IF(DY$1<$F72,$I72*(($F72-DY$1)/$F72),0) -> 0
C73: Nouvelles productions 2026 | U73: ='Plan Moyen Terme (PMT)'!C24-BAU_Liquidité_Dynamique!U72 -> 252.6917 | V73: =IF(AND(U$1<V$1, V$1<=$F72),$U73*($F72-V$1)/($F72-$U$1),0) -> 250.35196 | W73: =IF(AND(V$1<W$1, W$1<=$F72),$U73*($F72-W$1)/($F72-$U$1),0) -> 248.01222 | X73: =IF(AND(W$1<X$1, X$1<=$F72),$U73*($F72-X$1)/($F72-$U$1),0) -> 245.67249 | Y73: =IF(AND(X$1<Y$1, Y$1<=$F72),$U73*($F72-Y$1)/($F72-$U$1),0) -> 243.33275 | Z73: =IF(AND(Y$1<Z$1, Z$1<=$F72),$U73*($F72-Z$1)/($F72-$U$1),0) -> 240.99301 | AA73: =IF(AND(Z$1<AA$1, AA$1<=$F72),$U73*($F72-AA$1)/($F72-$U$1),0) -> 238.65327 | AB73: =IF(AND(AA$1<AB$1, AB$1<=$F72),$U73*($F72-AB$1)/($F72-$U$1),0) -> 236.31353 | AC73: =IF(AND(AB$1<AC$1, AC$1<=$F72),$U73*($F72-AC$1)/($F72-$U$1),0) -> 233.9738 | ... DY73: =IF(AND(DX$1<DY$1, DY$1<=$F72),$U73*($F72-DY$1)/($F72-$U$1),0) -> 0
C74: Nouvelles productions 2027 | AG74: ='Plan Moyen Terme (PMT)'!D24-BAU_Liquidité_Dynamique!AG72 -> -795.8296 | AH74: =IF(AND(AG$1<AH$1, AH$1<=$F72),$AG74*($F72-AH$1)/($F72-$AG$1),0) -> -787.53971 | AI74: =IF(AND(AH$1<AI$1, AI$1<=$F72),$AG74*($F72-AI$1)/($F72-$AG$1),0) -> -779.24982 | AJ74: =IF(AND(AI$1<AJ$1, AJ$1<=$F72),$AG74*($F72-AJ$1)/($F72-$AG$1),0) -> -770.95992 | AK74: =IF(AND(AJ$1<AK$1, AK$1<=$F72),$AG74*($F72-AK$1)/($F72-$AG$1),0) -> -762.67003 | AL74: =IF(AND(AK$1<AL$1, AL$1<=$F72),$AG74*($F72-AL$1)/($F72-$AG$1),0) -> -754.38014 | AM74: =IF(AND(AL$1<AM$1, AM$1<=$F72),$AG74*($F72-AM$1)/($F72-$AG$1),0) -> -746.09025 | AN74: =IF(AND(AM$1<AN$1, AN$1<=$F72),$AG74*($F72-AN$1)/($F72-$AG$1),0) -> -737.80036 | AO74: =IF(AND(AN$1<AO$1, AO$1<=$F72),$AG74*($F72-AO$1)/($F72-$AG$1),0) -> -729.51047 | ... DY74: =IF(AND(DX$1<DY$1, DY$1<=$F72),$AG74*($F72-DY$1)/($F72-$AG$1),0) -> 0
C75: Nouvelles productions 2028 | AS75: ='Plan Moyen Terme (PMT)'!E24-BAU_Liquidité_Dynamique!AS72 -> 38.6491 | AT75: =IF(AND(AS$1<AT$1, AT$1<=$F72),$AS75*($F72-AT$1)/($F72-$AS$1),0) -> 38.188992 | AU75: =IF(AND(AT$1<AU$1, AU$1<=$F72),$AS75*($F72-AU$1)/($F72-$AS$1),0) -> 37.728883 | AV75: =IF(AND(AU$1<AV$1, AV$1<=$F72),$AS75*($F72-AV$1)/($F72-$AS$1),0) -> 37.268775 | AW75: =IF(AND(AV$1<AW$1, AW$1<=$F72),$AS75*($F72-AW$1)/($F72-$AS$1),0) -> 36.808667 | AX75: =IF(AND(AW$1<AX$1, AX$1<=$F72),$AS75*($F72-AX$1)/($F72-$AS$1),0) -> 36.348558 | AY75: =IF(AND(AX$1<AY$1, AY$1<=$F72),$AS75*($F72-AY$1)/($F72-$AS$1),0) -> 35.88845 | AZ75: =IF(AND(AY$1<AZ$1, AZ$1<=$F72),$AS75*($F72-AZ$1)/($F72-$AS$1),0) -> 35.428342 | BA75: =IF(AND(AZ$1<BA$1, BA$1<=$F72),$AS75*($F72-BA$1)/($F72-$AS$1),0) -> 34.968233 | ... DY75: =IF(AND(DX$1<DY$1, DY$1<=$F72),$AS75*($F72-DY$1)/($F72-$AS$1),0) -> 0
A76: 46022 | B76: PASSIF | C76: Financement LT | D76: 0.035 | E76: In fine | F76: 72 | G76: In fine | H76: 72 | I76: 130 | J76: =IF(J$1<$F76,$I76,0) -> 130 | K76: =IF(K$1<$F76,$I76,0) -> 130 | L76: =IF(L$1<$F76,$I76,0) -> 130 | M76: =IF(M$1<$F76,$I76,0) -> 130 | N76: =IF(N$1<$F76,$I76,0) -> 130 | O76: =IF(O$1<$F76,$I76,0) -> 130 | P76: =IF(P$1<$F76,$I76,0) -> 130 | Q76: =IF(Q$1<$F76,$I76,0) -> 130 | ... DY76: =IF(DY$1<$F76,$I76,0) -> 0
C77: Nouvelles productions 2026 | U77: ='Plan Moyen Terme (PMT)'!C25-BAU_Liquidité_Dynamique!U76 -> 6344.151 | V77: =IF(AND($U$1<V$1, V$1<$F$76),$U$77,0) -> 6344.151 | W77: =IF(AND($U$1<W$1, W$1<$F$76),$U$77,0) -> 6344.151 | X77: =IF(AND($U$1<X$1, X$1<$F$76),$U$77,0) -> 6344.151 | Y77: =IF(AND($U$1<Y$1, Y$1<$F$76),$U$77,0) -> 6344.151 | Z77: =IF(AND($U$1<Z$1, Z$1<$F$76),$U$77,0) -> 6344.151 | AA77: =IF(AND($U$1<AA$1, AA$1<$F$76),$U$77,0) -> 6344.151 | AB77: =IF(AND($U$1<AB$1, AB$1<$F$76),$U$77,0) -> 6344.151 | AC77: =IF(AND($U$1<AC$1, AC$1<$F$76),$U$77,0) -> 6344.151 | ... CC77: =IF(AND($U$1<CC$1, CC$1<$F$76),$U$77,0) -> 0
C78: Nouvelles productions 2027 | AG78: ='Plan Moyen Terme (PMT)'!D25-BAU_Liquidité_Dynamique!AG76 -> 3444.0033 | AH78: =IF(AND($AG$1<AH$1, AH$1<$F$76),$AG$78,0) -> 3444.0033 | AI78: =IF(AND($AG$1<AI$1, AI$1<$F$76),$AG$78,0) -> 3444.0033 | AJ78: =IF(AND($AG$1<AJ$1, AJ$1<$F$76),$AG$78,0) -> 3444.0033 | AK78: =IF(AND($AG$1<AK$1, AK$1<$F$76),$AG$78,0) -> 3444.0033 | AL78: =IF(AND($AG$1<AL$1, AL$1<$F$76),$AG$78,0) -> 3444.0033 | AM78: =IF(AND($AG$1<AM$1, AM$1<$F$76),$AG$78,0) -> 3444.0033 | AN78: =IF(AND($AG$1<AN$1, AN$1<$F$76),$AG$78,0) -> 3444.0033 | AO78: =IF(AND($AG$1<AO$1, AO$1<$F$76),$AG$78,0) -> 3444.0033 | ... CC78: =IF(AND($AG$1<CC$1, CC$1<$F$76),$AG$78,0) -> 0
C79: Nouvelles productions 2028 | AS79: ='Plan Moyen Terme (PMT)'!E25-BAU_Liquidité_Dynamique!AS76 -> 116.55586 | AT79: =IF(AND($AS$1<AT$1, AT$1<$F$76),$AS$79,0) -> 116.55586 | AU79: =IF(AND($AS$1<AU$1, AU$1<$F$76),$AS$79,0) -> 116.55586 | AV79: =IF(AND($AS$1<AV$1, AV$1<$F$76),$AS$79,0) -> 116.55586 | AW79: =IF(AND($AS$1<AW$1, AW$1<$F$76),$AS$79,0) -> 116.55586 | AX79: =IF(AND($AS$1<AX$1, AX$1<$F$76),$AS$79,0) -> 116.55586 | AY79: =IF(AND($AS$1<AY$1, AY$1<$F$76),$AS$79,0) -> 116.55586 | AZ79: =IF(AND($AS$1<AZ$1, AZ$1<$F$76),$AS$79,0) -> 116.55586 | BA79: =IF(AND($AS$1<BA$1, BA$1<$F$76),$AS$79,0) -> 116.55586 | ... CC79: =IF(AND($AS$1<CC$1, CC$1<$F$76),$AS$79,0) -> 0
A80: 46022 | B80: PASSIF | C80: Capitaux propres | I80: =I81+I85+I89+I93+I97 -> 25913.849 | J80: =SUM(J81:J105) -> 25697.9 | K80: =SUM(K81:K105) -> 25481.952 | L80: =SUM(L81:L105) -> 25266.003 | M80: =SUM(M81:M105) -> 25050.054 | N80: =SUM(N81:N105) -> 24834.105 | O80: =SUM(O81:O105) -> 24618.157 | P80: =SUM(P81:P105) -> 24402.208 | Q80: =SUM(Q81:Q105) -> 24186.259 | ... DY80: =SUM(DY81:DY105) -> 0
A81: 46022 | B81: PASSIF | C81: FRBG | D81: 0 | E81: Linéaire | F81: 120 | G81: Linéaire | H81: 120 | I81: 476.541 | J81: =IF(J$1<$F81,$I81*(($F81-J$1)/$F81),0) -> 472.56983 | K81: =IF(K$1<$F81,$I81*(($F81-K$1)/$F81),0) -> 468.59865 | L81: =IF(L$1<$F81,$I81*(($F81-L$1)/$F81),0) -> 464.62748 | M81: =IF(M$1<$F81,$I81*(($F81-M$1)/$F81),0) -> 460.6563 | N81: =IF(N$1<$F81,$I81*(($F81-N$1)/$F81),0) -> 456.68513 | O81: =IF(O$1<$F81,$I81*(($F81-O$1)/$F81),0) -> 452.71395 | P81: =IF(P$1<$F81,$I81*(($F81-P$1)/$F81),0) -> 448.74277 | Q81: =IF(Q$1<$F81,$I81*(($F81-Q$1)/$F81),0) -> 444.7716 | ... DY81: =IF(DY$1<$F81,$I81*(($F81-DY$1)/$F81),0) -> 0
C82: Nouvelles productions 2026 | U82: ='Plan Moyen Terme (PMT)'!C27-BAU_Liquidité_Dynamique!U81 -> 47.6541 | V82: =IF(AND(U$1<V$1, V$1<=$F81),$U82*($F81-V$1)/($F81-$U$1),0) -> 47.212858 | W82: =IF(AND(V$1<W$1, W$1<=$F81),$U82*($F81-W$1)/($F81-$U$1),0) -> 46.771617 | X82: =IF(AND(W$1<X$1, X$1<=$F81),$U82*($F81-X$1)/($F81-$U$1),0) -> 46.330375 | Y82: =IF(AND(X$1<Y$1, Y$1<=$F81),$U82*($F81-Y$1)/($F81-$U$1),0) -> 45.889133 | Z82: =IF(AND(Y$1<Z$1, Z$1<=$F81),$U82*($F81-Z$1)/($F81-$U$1),0) -> 45.447892 | AA82: =IF(AND(Z$1<AA$1, AA$1<=$F81),$U82*($F81-AA$1)/($F81-$U$1),0) -> 45.00665 | AB82: =IF(AND(AA$1<AB$1, AB$1<=$F81),$U82*($F81-AB$1)/($F81-$U$1),0) -> 44.565408 | AC82: =IF(AND(AB$1<AC$1, AC$1<=$F81),$U82*($F81-AC$1)/($F81-$U$1),0) -> 44.124167 | ... DY82: =IF(AND(DX$1<DY$1, DY$1<=$F81),$U82*($F81-DY$1)/($F81-$U$1),0) -> 0
C83: Nouvelles productions 2027 | AG83: ='Plan Moyen Terme (PMT)'!D27-BAU_Liquidité_Dynamique!AG81 -> 95.3082 | AH83: =IF(AND(AG$1<AH$1, AH$1<=$F81),$AG83*($F81-AH$1)/($F81-$AG$1),0) -> 94.315406 | AI83: =IF(AND(AH$1<AI$1, AI$1<=$F81),$AG83*($F81-AI$1)/($F81-$AG$1),0) -> 93.322612 | AJ83: =IF(AND(AI$1<AJ$1, AJ$1<=$F81),$AG83*($F81-AJ$1)/($F81-$AG$1),0) -> 92.329819 | AK83: =IF(AND(AJ$1<AK$1, AK$1<=$F81),$AG83*($F81-AK$1)/($F81-$AG$1),0) -> 91.337025 | AL83: =IF(AND(AK$1<AL$1, AL$1<=$F81),$AG83*($F81-AL$1)/($F81-$AG$1),0) -> 90.344231 | AM83: =IF(AND(AL$1<AM$1, AM$1<=$F81),$AG83*($F81-AM$1)/($F81-$AG$1),0) -> 89.351437 | AN83: =IF(AND(AM$1<AN$1, AN$1<=$F81),$AG83*($F81-AN$1)/($F81-$AG$1),0) -> 88.358644 | AO83: =IF(AND(AN$1<AO$1, AO$1<=$F81),$AG83*($F81-AO$1)/($F81-$AG$1),0) -> 87.36585 | ... DY83: =IF(AND(DX$1<DY$1, DY$1<=$F81),$AG83*($F81-DY$1)/($F81-$AG$1),0) -> 0
C84: Nouvelles productions 2028 | AS84: ='Plan Moyen Terme (PMT)'!E27-BAU_Liquidité_Dynamique!AS81 -> 142.9623 | AT84: =IF(AND(AS$1<AT$1, AT$1<=$F81),$AS84*($F81-AT$1)/($F81-$AS$1),0) -> 141.26037 | AU84: =IF(AND(AT$1<AU$1, AU$1<=$F81),$AS84*($F81-AU$1)/($F81-$AS$1),0) -> 139.55844 | AV84: =IF(AND(AU$1<AV$1, AV$1<=$F81),$AS84*($F81-AV$1)/($F81-$AS$1),0) -> 137.8565 | AW84: =IF(AND(AV$1<AW$1, AW$1<=$F81),$AS84*($F81-AW$1)/($F81-$AS$1),0) -> 136.15457 | AX84: =IF(AND(AW$1<AX$1, AX$1<=$F81),$AS84*($F81-AX$1)/($F81-$AS$1),0) -> 134.45264 | AY84: =IF(AND(AX$1<AY$1, AY$1<=$F81),$AS84*($F81-AY$1)/($F81-$AS$1),0) -> 132.75071 | AZ84: =IF(AND(AY$1<AZ$1, AZ$1<=$F81),$AS84*($F81-AZ$1)/($F81-$AS$1),0) -> 131.04878 | BA84: =IF(AND(AZ$1<BA$1, BA$1<=$F81),$AS84*($F81-BA$1)/($F81-$AS$1),0) -> 129.34684 | ... DY84: =IF(AND(DX$1<DY$1, DY$1<=$F81),$AS84*($F81-DY$1)/($F81-$AS$1),0) -> 0
A85: 46022 | B85: PASSIF | C85: Capital souscrit | D85: 0 | E85: Linéaire | F85: 120 | G85: Linéaire | H85: 120 | I85: 18000.179 | J85: =IF(J$1<$F85,$I85*(($F85-J$1)/$F85),0) -> 17850.178 | K85: =IF(K$1<$F85,$I85*(($F85-K$1)/$F85),0) -> 17700.176 | L85: =IF(L$1<$F85,$I85*(($F85-L$1)/$F85),0) -> 17550.175 | M85: =IF(M$1<$F85,$I85*(($F85-M$1)/$F85),0) -> 17400.173 | N85: =IF(N$1<$F85,$I85*(($F85-N$1)/$F85),0) -> 17250.172 | O85: =IF(O$1<$F85,$I85*(($F85-O$1)/$F85),0) -> 17100.17 | P85: =IF(P$1<$F85,$I85*(($F85-P$1)/$F85),0) -> 16950.169 | Q85: =IF(Q$1<$F85,$I85*(($F85-Q$1)/$F85),0) -> 16800.167 | ... DY85: =IF(DY$1<$F85,$I85*(($F85-DY$1)/$F85),0) -> 0
C86: Nouvelles productions 2026 | U86: ='Plan Moyen Terme (PMT)'!C28-BAU_Liquidité_Dynamique!U85 -> 1800.0179 | V86: =IF(AND(U$1<V$1, V$1<=$F85),$U86*($F85-V$1)/($F85-$U$1),0) -> 1783.3511 | W86: =IF(AND(V$1<W$1, W$1<=$F85),$U86*($F85-W$1)/($F85-$U$1),0) -> 1766.6842 | X86: =IF(AND(W$1<X$1, X$1<=$F85),$U86*($F85-X$1)/($F85-$U$1),0) -> 1750.0174 | Y86: =IF(AND(X$1<Y$1, Y$1<=$F85),$U86*($F85-Y$1)/($F85-$U$1),0) -> 1733.3506 | Z86: =IF(AND(Y$1<Z$1, Z$1<=$F85),$U86*($F85-Z$1)/($F85-$U$1),0) -> 1716.6837 | AA86: =IF(AND(Z$1<AA$1, AA$1<=$F85),$U86*($F85-AA$1)/($F85-$U$1),0) -> 1700.0169 | AB86: =IF(AND(AA$1<AB$1, AB$1<=$F85),$U86*($F85-AB$1)/($F85-$U$1),0) -> 1683.3501 | AC86: =IF(AND(AB$1<AC$1, AC$1<=$F85),$U86*($F85-AC$1)/($F85-$U$1),0) -> 1666.6832 | ... DY86: =IF(AND(DX$1<DY$1, DY$1<=$F85),$U86*($F85-DY$1)/($F85-$U$1),0) -> 0
C87: Nouvelles productions 2027 | AG87: ='Plan Moyen Terme (PMT)'!D28-BAU_Liquidité_Dynamique!AG85 -> 3600.0358 | AH87: =IF(AND(AG$1<AH$1, AH$1<=$F85),$AG87*($F85-AH$1)/($F85-$AG$1),0) -> 3562.5354 | AI87: =IF(AND(AH$1<AI$1, AI$1<=$F85),$AG87*($F85-AI$1)/($F85-$AG$1),0) -> 3525.0351 | AJ87: =IF(AND(AI$1<AJ$1, AJ$1<=$F85),$AG87*($F85-AJ$1)/($F85-$AG$1),0) -> 3487.5347 | AK87: =IF(AND(AJ$1<AK$1, AK$1<=$F85),$AG87*($F85-AK$1)/($F85-$AG$1),0) -> 3450.0343 | AL87: =IF(AND(AK$1<AL$1, AL$1<=$F85),$AG87*($F85-AL$1)/($F85-$AG$1),0) -> 3412.5339 | AM87: =IF(AND(AL$1<AM$1, AM$1<=$F85),$AG87*($F85-AM$1)/($F85-$AG$1),0) -> 3375.0336 | AN87: =IF(AND(AM$1<AN$1, AN$1<=$F85),$AG87*($F85-AN$1)/($F85-$AG$1),0) -> 3337.5332 | AO87: =IF(AND(AN$1<AO$1, AO$1<=$F85),$AG87*($F85-AO$1)/($F85-$AG$1),0) -> 3300.0328 | ... DY87: =IF(AND(DX$1<DY$1, DY$1<=$F85),$AG87*($F85-DY$1)/($F85-$AG$1),0) -> 0
C88: Nouvelles productions 2028 | AS88: ='Plan Moyen Terme (PMT)'!E28-BAU_Liquidité_Dynamique!AS85 -> 37857.875 | AT88: =IF(AND(AS$1<AT$1, AT$1<=$F85),$AS88*($F85-AT$1)/($F85-$AS$1),0) -> 37407.186 | AU88: =IF(AND(AT$1<AU$1, AU$1<=$F85),$AS88*($F85-AU$1)/($F85-$AS$1),0) -> 36956.497 | AV88: =IF(AND(AU$1<AV$1, AV$1<=$F85),$AS88*($F85-AV$1)/($F85-$AS$1),0) -> 36505.808 | AW88: =IF(AND(AV$1<AW$1, AW$1<=$F85),$AS88*($F85-AW$1)/($F85-$AS$1),0) -> 36055.119 | AX88: =IF(AND(AW$1<AX$1, AX$1<=$F85),$AS88*($F85-AX$1)/($F85-$AS$1),0) -> 35604.43 | AY88: =IF(AND(AX$1<AY$1, AY$1<=$F85),$AS88*($F85-AY$1)/($F85-$AS$1),0) -> 35153.741 | AZ88: =IF(AND(AY$1<AZ$1, AZ$1<=$F85),$AS88*($F85-AZ$1)/($F85-$AS$1),0) -> 34703.052 | BA88: =IF(AND(AZ$1<BA$1, BA$1<=$F85),$AS88*($F85-BA$1)/($F85-$AS$1),0) -> 34252.363 | ... DY88: =IF(AND(DX$1<DY$1, DY$1<=$F85),$AS88*($F85-DY$1)/($F85-$AS$1),0) -> 0
A89: 46022 | B89: PASSIF | C89: Prime d'émission | D89: 0 | E89: Linéaire | F89: 120 | G89: Linéaire | H89: 120 | I89: 2.22 | J89: =IF(J$1<$F89,$I89*(($F89-J$1)/$F89),0) -> 2.2015 | K89: =IF(K$1<$F89,$I89*(($F89-K$1)/$F89),0) -> 2.183 | L89: =IF(L$1<$F89,$I89*(($F89-L$1)/$F89),0) -> 2.1645 | M89: =IF(M$1<$F89,$I89*(($F89-M$1)/$F89),0) -> 2.146 | N89: =IF(N$1<$F89,$I89*(($F89-N$1)/$F89),0) -> 2.1275 | O89: =IF(O$1<$F89,$I89*(($F89-O$1)/$F89),0) -> 2.109 | P89: =IF(P$1<$F89,$I89*(($F89-P$1)/$F89),0) -> 2.0905 | Q89: =IF(Q$1<$F89,$I89*(($F89-Q$1)/$F89),0) -> 2.072 | ... DY89: =IF(DY$1<$F89,$I89*(($F89-DY$1)/$F89),0) -> 0
C90: Nouvelles productions 2026 | U90: ='Plan Moyen Terme (PMT)'!C29-BAU_Liquidité_Dynamique!U89 -> 0.222 | V90: =IF(AND(U$1<V$1, V$1<=$F89),$U90*($F89-V$1)/($F89-$U$1),0) -> 0.21994444 | W90: =IF(AND(V$1<W$1, W$1<=$F89),$U90*($F89-W$1)/($F89-$U$1),0) -> 0.21788889 | X90: =IF(AND(W$1<X$1, X$1<=$F89),$U90*($F89-X$1)/($F89-$U$1),0) -> 0.21583333 | Y90: =IF(AND(X$1<Y$1, Y$1<=$F89),$U90*($F89-Y$1)/($F89-$U$1),0) -> 0.21377778 | Z90: =IF(AND(Y$1<Z$1, Z$1<=$F89),$U90*($F89-Z$1)/($F89-$U$1),0) -> 0.21172222 | AA90: =IF(AND(Z$1<AA$1, AA$1<=$F89),$U90*($F89-AA$1)/($F89-$U$1),0) -> 0.20966667 | AB90: =IF(AND(AA$1<AB$1, AB$1<=$F89),$U90*($F89-AB$1)/($F89-$U$1),0) -> 0.20761111 | AC90: =IF(AND(AB$1<AC$1, AC$1<=$F89),$U90*($F89-AC$1)/($F89-$U$1),0) -> 0.20555556 | ... DY90: =IF(AND(DX$1<DY$1, DY$1<=$F89),$U90*($F89-DY$1)/($F89-$U$1),0) -> 0
C91: Nouvelles productions 2027 | AG91: ='Plan Moyen Terme (PMT)'!D29-BAU_Liquidité_Dynamique!AG89 -> 0.444 | AH91: =IF(AND(AG$1<AH$1, AH$1<=$F89),$AG91*($F89-AH$1)/($F89-$AG$1),0) -> 0.439375 | AI91: =IF(AND(AH$1<AI$1, AI$1<=$F89),$AG91*($F89-AI$1)/($F89-$AG$1),0) -> 0.43475 | AJ91: =IF(AND(AI$1<AJ$1, AJ$1<=$F89),$AG91*($F89-AJ$1)/($F89-$AG$1),0) -> 0.430125 | AK91: =IF(AND(AJ$1<AK$1, AK$1<=$F89),$AG91*($F89-AK$1)/($F89-$AG$1),0) -> 0.4255 | AL91: =IF(AND(AK$1<AL$1, AL$1<=$F89),$AG91*($F89-AL$1)/($F89-$AG$1),0) -> 0.420875 | AM91: =IF(AND(AL$1<AM$1, AM$1<=$F89),$AG91*($F89-AM$1)/($F89-$AG$1),0) -> 0.41625 | AN91: =IF(AND(AM$1<AN$1, AN$1<=$F89),$AG91*($F89-AN$1)/($F89-$AG$1),0) -> 0.411625 | AO91: =IF(AND(AN$1<AO$1, AO$1<=$F89),$AG91*($F89-AO$1)/($F89-$AG$1),0) -> 0.407 | ... DY91: =IF(AND(DX$1<DY$1, DY$1<=$F89),$AG91*($F89-DY$1)/($F89-$AG$1),0) -> 0
C92: Nouvelles productions 2028 | AS92: ='Plan Moyen Terme (PMT)'!E29-BAU_Liquidité_Dynamique!AS89 -> 2752.446 | AT92: =IF(AND(AS$1<AT$1, AT$1<=$F89),$AS92*($F89-AT$1)/($F89-$AS$1),0) -> 2719.6788 | AU92: =IF(AND(AT$1<AU$1, AU$1<=$F89),$AS92*($F89-AU$1)/($F89-$AS$1),0) -> 2686.9116 | AV92: =IF(AND(AU$1<AV$1, AV$1<=$F89),$AS92*($F89-AV$1)/($F89-$AS$1),0) -> 2654.1444 | AW92: =IF(AND(AV$1<AW$1, AW$1<=$F89),$AS92*($F89-AW$1)/($F89-$AS$1),0) -> 2621.3771 | AX92: =IF(AND(AW$1<AX$1, AX$1<=$F89),$AS92*($F89-AX$1)/($F89-$AS$1),0) -> 2588.6099 | AY92: =IF(AND(AX$1<AY$1, AY$1<=$F89),$AS92*($F89-AY$1)/($F89-$AS$1),0) -> 2555.8427 | AZ92: =IF(AND(AY$1<AZ$1, AZ$1<=$F89),$AS92*($F89-AZ$1)/($F89-$AS$1),0) -> 2523.0755 | BA92: =IF(AND(AZ$1<BA$1, BA$1<=$F89),$AS92*($F89-BA$1)/($F89-$AS$1),0) -> 2490.3083 | ... DY92: =IF(AND(DX$1<DY$1, DY$1<=$F89),$AS92*($F89-DY$1)/($F89-$AS$1),0) -> 0
A93: 46022 | B93: PASSIF | C93: Réserves | D93: 0 | E93: Linéaire | F93: 120 | G93: Linéaire | H93: 120 | I93: 429.975 | J93: =IF(J$1<$F93,$I93*(($F93-J$1)/$F93),0) -> 426.39188 | K93: =IF(K$1<$F93,$I93*(($F93-K$1)/$F93),0) -> 422.80875 | L93: =IF(L$1<$F93,$I93*(($F93-L$1)/$F93),0) -> 419.22563 | M93: =IF(M$1<$F93,$I93*(($F93-M$1)/$F93),0) -> 415.6425 | N93: =IF(N$1<$F93,$I93*(($F93-N$1)/$F93),0) -> 412.05938 | O93: =IF(O$1<$F93,$I93*(($F93-O$1)/$F93),0) -> 408.47625 | P93: =IF(P$1<$F93,$I93*(($F93-P$1)/$F93),0) -> 404.89312 | Q93: =IF(Q$1<$F93,$I93*(($F93-Q$1)/$F93),0) -> 401.31 | ... DY93: =IF(DY$1<$F93,$I93*(($F93-DY$1)/$F93),0) -> 0
C94: Nouvelles productions 2026 | U94: ='Plan Moyen Terme (PMT)'!C30-BAU_Liquidité_Dynamique!U93 -> 49.0225 | V94: =IF(AND(U$1<V$1, V$1<=$F93),$U94*($F93-V$1)/($F93-$U$1),0) -> 48.568588 | W94: =IF(AND(V$1<W$1, W$1<=$F93),$U94*($F93-W$1)/($F93-$U$1),0) -> 48.114676 | X94: =IF(AND(W$1<X$1, X$1<=$F93),$U94*($F93-X$1)/($F93-$U$1),0) -> 47.660764 | Y94: =IF(AND(X$1<Y$1, Y$1<=$F93),$U94*($F93-Y$1)/($F93-$U$1),0) -> 47.206852 | Z94: =IF(AND(Y$1<Z$1, Z$1<=$F93),$U94*($F93-Z$1)/($F93-$U$1),0) -> 46.75294 | AA94: =IF(AND(Z$1<AA$1, AA$1<=$F93),$U94*($F93-AA$1)/($F93-$U$1),0) -> 46.299028 | AB94: =IF(AND(AA$1<AB$1, AB$1<=$F93),$U94*($F93-AB$1)/($F93-$U$1),0) -> 45.845116 | AC94: =IF(AND(AB$1<AC$1, AC$1<=$F93),$U94*($F93-AC$1)/($F93-$U$1),0) -> 45.391204 | ... DY94: =IF(AND(DX$1<DY$1, DY$1<=$F93),$U94*($F93-DY$1)/($F93-$U$1),0) -> 0
C95: Nouvelles productions 2027 | AG95: ='Plan Moyen Terme (PMT)'!D30-BAU_Liquidité_Dynamique!AG93 -> 113.02 | AH95: =IF(AND(AG$1<AH$1, AH$1<=$F93),$AG95*($F93-AH$1)/($F93-$AG$1),0) -> 111.84271 | AI95: =IF(AND(AH$1<AI$1, AI$1<=$F93),$AG95*($F93-AI$1)/($F93-$AG$1),0) -> 110.66542 | AJ95: =IF(AND(AI$1<AJ$1, AJ$1<=$F93),$AG95*($F93-AJ$1)/($F93-$AG$1),0) -> 109.48812 | AK95: =IF(AND(AJ$1<AK$1, AK$1<=$F93),$AG95*($F93-AK$1)/($F93-$AG$1),0) -> 108.31083 | AL95: =IF(AND(AK$1<AL$1, AL$1<=$F93),$AG95*($F93-AL$1)/($F93-$AG$1),0) -> 107.13354 | AM95: =IF(AND(AL$1<AM$1, AM$1<=$F93),$AG95*($F93-AM$1)/($F93-$AG$1),0) -> 105.95625 | AN95: =IF(AND(AM$1<AN$1, AN$1<=$F93),$AG95*($F93-AN$1)/($F93-$AG$1),0) -> 104.77896 | AO95: =IF(AND(AN$1<AO$1, AO$1<=$F93),$AG95*($F93-AO$1)/($F93-$AG$1),0) -> 103.60167 | ... DY95: =IF(AND(DX$1<DY$1, DY$1<=$F93),$AG95*($F93-DY$1)/($F93-$AG$1),0) -> 0
C96: Nouvelles productions 2028 | AS96: ='Plan Moyen Terme (PMT)'!E30-BAU_Liquidité_Dynamique!AS93 -> 256.0175 | AT96: =IF(AND(AS$1<AT$1, AT$1<=$F93),$AS96*($F93-AT$1)/($F93-$AS$1),0) -> 252.96967 | AU96: =IF(AND(AT$1<AU$1, AU$1<=$F93),$AS96*($F93-AU$1)/($F93-$AS$1),0) -> 249.92185 | AV96: =IF(AND(AU$1<AV$1, AV$1<=$F93),$AS96*($F93-AV$1)/($F93-$AS$1),0) -> 246.87402 | AW96: =IF(AND(AV$1<AW$1, AW$1<=$F93),$AS96*($F93-AW$1)/($F93-$AS$1),0) -> 243.82619 | AX96: =IF(AND(AW$1<AX$1, AX$1<=$F93),$AS96*($F93-AX$1)/($F93-$AS$1),0) -> 240.77836 | AY96: =IF(AND(AX$1<AY$1, AY$1<=$F93),$AS96*($F93-AY$1)/($F93-$AS$1),0) -> 237.73054 | AZ96: =IF(AND(AY$1<AZ$1, AZ$1<=$F93),$AS96*($F93-AZ$1)/($F93-$AS$1),0) -> 234.68271 | BA96: =IF(AND(AZ$1<BA$1, BA$1<=$F93),$AS96*($F93-BA$1)/($F93-$AS$1),0) -> 231.63488 | ... DY96: =IF(AND(DX$1<DY$1, DY$1<=$F93),$AS96*($F93-DY$1)/($F93-$AS$1),0) -> 0
A97: 46022 | B97: PASSIF | C97: Report à nouveau | D97: 0 | E97: Linéaire | F97: 120 | G97: Linéaire | H97: 120 | I97: 7004.934 | J97: =IF(J$1<$F97,$I97*(($F97-J$1)/$F97),0) -> 6946.5596 | K97: =IF(K$1<$F97,$I97*(($F97-K$1)/$F97),0) -> 6888.1851 | L97: =IF(L$1<$F97,$I97*(($F97-L$1)/$F97),0) -> 6829.8107 | M97: =IF(M$1<$F97,$I97*(($F97-M$1)/$F97),0) -> 6771.4362 | N97: =IF(N$1<$F97,$I97*(($F97-N$1)/$F97),0) -> 6713.0618 | O97: =IF(O$1<$F97,$I97*(($F97-O$1)/$F97),0) -> 6654.6873 | P97: =IF(P$1<$F97,$I97*(($F97-P$1)/$F97),0) -> 6596.3129 | Q97: =IF(Q$1<$F97,$I97*(($F97-Q$1)/$F97),0) -> 6537.9384 | ... DY97: =IF(DY$1<$F97,$I97*(($F97-DY$1)/$F97),0) -> 0
C98: Nouvelles productions 2026 | U98: ='Plan Moyen Terme (PMT)'!C31-BAU_Liquidité_Dynamique!U97 -> 695.4684 | V98: =IF(AND(U$1<V$1, V$1<=$F97),$U98*($F97-V$1)/($F97-$U$1),0) -> 689.02888 | W98: =IF(AND(V$1<W$1, W$1<=$F97),$U98*($F97-W$1)/($F97-$U$1),0) -> 682.58936 | X98: =IF(AND(W$1<X$1, X$1<=$F97),$U98*($F97-X$1)/($F97-$U$1),0) -> 676.14983 | Y98: =IF(AND(X$1<Y$1, Y$1<=$F97),$U98*($F97-Y$1)/($F97-$U$1),0) -> 669.71031 | Z98: =IF(AND(Y$1<Z$1, Z$1<=$F97),$U98*($F97-Z$1)/($F97-$U$1),0) -> 663.27079 | AA98: =IF(AND(Z$1<AA$1, AA$1<=$F97),$U98*($F97-AA$1)/($F97-$U$1),0) -> 656.83127 | AB98: =IF(AND(AA$1<AB$1, AB$1<=$F97),$U98*($F97-AB$1)/($F97-$U$1),0) -> 650.39174 | AC98: =IF(AND(AB$1<AC$1, AC$1<=$F97),$U98*($F97-AC$1)/($F97-$U$1),0) -> 643.95222 | ... DY98: =IF(AND(DX$1<DY$1, DY$1<=$F97),$U98*($F97-DY$1)/($F97-$U$1),0) -> 0
C99: Nouvelles productions 2027 | AG99: ='Plan Moyen Terme (PMT)'!D31-BAU_Liquidité_Dynamique!AG97 -> 1374.9618 | AH99: =IF(AND(AG$1<AH$1, AH$1<=$F97),$AG99*($F97-AH$1)/($F97-$AG$1),0) -> 1360.6393 | AI99: =IF(AND(AH$1<AI$1, AI$1<=$F97),$AG99*($F97-AI$1)/($F97-$AG$1),0) -> 1346.3168 | AJ99: =IF(AND(AI$1<AJ$1, AJ$1<=$F97),$AG99*($F97-AJ$1)/($F97-$AG$1),0) -> 1331.9942 | AK99: =IF(AND(AJ$1<AK$1, AK$1<=$F97),$AG99*($F97-AK$1)/($F97-$AG$1),0) -> 1317.6717 | AL99: =IF(AND(AK$1<AL$1, AL$1<=$F97),$AG99*($F97-AL$1)/($F97-$AG$1),0) -> 1303.3492 | AM99: =IF(AND(AL$1<AM$1, AM$1<=$F97),$AG99*($F97-AM$1)/($F97-$AG$1),0) -> 1289.0267 | AN99: =IF(AND(AM$1<AN$1, AN$1<=$F97),$AG99*($F97-AN$1)/($F97-$AG$1),0) -> 1274.7042 | AO99: =IF(AND(AN$1<AO$1, AO$1<=$F97),$AG99*($F97-AO$1)/($F97-$AG$1),0) -> 1260.3817 | ... DY99: =IF(AND(DX$1<DY$1, DY$1<=$F97),$AG99*($F97-DY$1)/($F97-$AG$1),0) -> 0
C100: Nouvelles productions 2028 | AS100: ='Plan Moyen Terme (PMT)'!E31-BAU_Liquidité_Dynamique!AS97 -> -2959.4538 | AT100: =IF(AND(AS$1<AT$1, AT$1<=$F97),$AS100*($F97-AT$1)/($F97-$AS$1),0) -> -2924.2222 | AU100: =IF(AND(AT$1<AU$1, AU$1<=$F97),$AS100*($F97-AU$1)/($F97-$AS$1),0) -> -2888.9906 | AV100: =IF(AND(AU$1<AV$1, AV$1<=$F97),$AS100*($F97-AV$1)/($F97-$AS$1),0) -> -2853.759 | AW100: =IF(AND(AV$1<AW$1, AW$1<=$F97),$AS100*($F97-AW$1)/($F97-$AS$1),0) -> -2818.5274 | AX100: =IF(AND(AW$1<AX$1, AX$1<=$F97),$AS100*($F97-AX$1)/($F97-$AS$1),0) -> -2783.2958 | AY100: =IF(AND(AX$1<AY$1, AY$1<=$F97),$AS100*($F97-AY$1)/($F97-$AS$1),0) -> -2748.0642 | AZ100: =IF(AND(AY$1<AZ$1, AZ$1<=$F97),$AS100*($F97-AZ$1)/($F97-$AS$1),0) -> -2712.8327 | BA100: =IF(AND(AZ$1<BA$1, BA$1<=$F97),$AS100*($F97-BA$1)/($F97-$AS$1),0) -> -2677.6011 | ... DY100: =IF(AND(DX$1<DY$1, DY$1<=$F97),$AS100*($F97-DY$1)/($F97-$AS$1),0) -> 0
...

Sheet Loi d'écoulement 
D1: E n liquidité | F1: E n taux
A2: Bilan | B2: Catégories Bilan | C2: Poste du bilan | D2: Loi d'écoulement | E2: Durée moyenne (en mois) | F2: Loi d'écoulement | G2: Durée moyenne (en mois)
A3: ACTIF | B3: CAISSE, BANQUES CENTRALES | C3: - Caisse | D3: Linéaire | E3: 60 | F3: In fine | G3: 60
A4: ACTIF | B4: CAISSE, BANQUES CENTRALES | C4: - Compte courant BDF | D4: Linéaire | E4: 120 | F4: Ine fine | G4: 120
A5: ACTIF | B5: CREANCES SUR LES ETS DE CREDIT | C5: - A vue | D5: Linéaire | E5: 6 | F5: Linéaire | G5: 6
A6: ACTIF | B6: CREANCES SUR LES ETS DE CREDIT | C6: - A terme | D6: In fine | E6: 12 | F6: In fine | G6: 12
A7: ACTIF | B7: CREANCES SUR LA CLIENTELE | C7: - Créances commerciales | D7: Constant | E7: 60 | F7: Constant | G7: 60
A8: ACTIF | B8: CREANCES SUR LA CLIENTELE | C8: - Autres concours à la clientèle | D8: Constant | E8: 10 | F8: Constant | G8: 10
A9: ACTIF | B9: CREANCES SUR LA CLIENTELE | C9: - Comptes ordinaires débiteurs | D9: In fine | E9: 1 | F9: In fine | G9: 1
A10: ACTIF | B10: TITRE D'INVESTISSEMENT | C10: Investissements financiers | D10: Ine fine | E10: 84 | F10: Ine fine | G10: 84
A11: ACTIF | B11: IMMOBILISATIONS | C11: Immobilisations corporelles et incorporelles | D11: Linéaire | E11: 120 | F11: Linéaire | G11: 120
A12: ACTIF | B12: AUTRES | C12: Autres actifs | D12: Linéaire | E12: 120 | F12: Linéaire | G12: 120
A13: PASSIF | B13: DETTES ENVERS ETS DE CREDIT | C13: - A vue | D13: 90%-20%*t, t<=4mois | E13: 4 | F13: In fine | G13: 4
A14: PASSIF | B14: DETTES ENVERS ETS DE CREDIT | C14: - A terme | D14: Ine fine | E14: 24 | F14: Ine fine | G14: 24
... A27: PASSIF | B27: FONDS PROPRES | C27: Dividende | D27: Linéaire | E27: 120 | F27: Linéaire | G27: 120

Sheet Plan Moyen Terme (PMT)
B1: Realisée | C1: Prévision | D1: Prévision | E1: Prévision | F1: Prévision stressé sénario 1 | G1: Prévision stressé sénario 1 | H1: Prévision stressé sénario 1
A2: Poste du bilan | B2: 46022 | C2: 46387 | D2: 46752 | E2: 47118 | F2: 46387 | G2: 46752 | H2: 46752
A3: CAISSE, BANQUES CENTRALES | B3: 1255.124 | C3: 1295 | D3: =D4+D5 -> 7317.8523 | E3: =E4+E5 -> 5537.0969
A4: - Caisse | B4: 40.58686 | C4: 26.68556 | D4: 298.85232 | E4: 246.09686
A5: - Compte courant BDF | B5: 1214.5371 | C5: 1268.3144 | D5: 7019 | E5: 5291
A6: CREANCES SUR LES ETS DE CREDIT | B6: 28006.945 | C6: 24611 | D6: 34452 | E6: 27054 | F6: =C6*(1+5%) -> 25841.55 | G6: =D6*(1+5%)^2 -> 37983.33 | H6: =E6*(1+5%)^3 -> 31318.387
A7: - A vue | B7: 19086.274 | C7: 16458 | D7: 28608 | E7: 26797 | F7: =C7*(1+5%) -> 17280.9 | G7: =D7*(1+5%)^2 -> 31540.32 | H7: =E7*(1+5%)^3 -> 31020.877
A8: - A terme | B8: 8920.671 | C8: 8153 | D8: 5844 | E8: 257 | F8: =C8*(1+5%) -> 8560.65 | G8: =D8*(1+5%)^2 -> 6443.01 | H8: =E8*(1+5%)^3 -> 297.50963
A9: CREANCES SUR LA CLIENTELE | B9: 125650.32 | C9: =C10+C11+C12 -> 157553 | D9: 267467 | E9: 297941 | F9: =C9*(1-6%) -> 148099.82 | G9: =D9*(1-6%)^2 -> 236333.84 | H9: =E9*(1-6%)^3 -> 247465.03
A10: - Créances commerciales | B10: 358.117 | C10: 5939 | D10: 3970 | E10: 18036 | F10: =C10*(1-6%) -> 5582.66 | G10: =D10*(1-6%)^2 -> 3507.892 | H10: =E10*(1-6%)^3 -> 14980.413
A11: - Autres concours à la clientèle | B11: 49615.566 | C11: 60919 | D11: 146749 | E11: 159220 | F11: =C11*(1-6%) -> 57263.86 | G11: =D11*(1-6%)^2 -> 129667.42 | H11: =E11*(1-6%)^3 -> 132245.58
A12: - Comptes ordinaires débiteurs | B12: 75676.636 | C12: 90695 | D12: 116748 | E12: 120685 | F12: =C12*(1-6%) -> 85253.3 | G12: =D12*(1-6%)^2 -> 103158.53 | H12: =E12*(1-6%)^3 -> 100239.03
A13: Investissements financiers | B13: 28 | C13: 28 | D13: 9212 | E13: 9506
A14: Immobilisations corporelles et incorporelles | B14: 82 | C14: 60 | D14: 67 | E14: 53
A15: Autres actifs | B15: 570 | C15: 510 | D15: 1144 | E15: 2027
A16: Total actif | B16: =B3+B6+B9+B13+B14+B15 -> 155592.39 | C16: =C3+C6+C9+C13+C14+C15 -> 184057 | D16: =D3+D6+D9+D13+D14+D15 -> 319659.85 | E16: =E15+E3+E6+E9+E13+E14 -> 342118.1
A17: DETTES ENVERS ETS DE CREDIT | B17: =B18+B19 -> 74095.3 | C17: =C18+C19 -> 89448 | D17: 183319 | E17: 141593 | F17: =C17*(1-25%) -> 67086 | G17: =D17*(1-25%)^2 -> 103116.94 | H17: =E17*(1-25%)^3 -> 59734.547
A18: - A vue | B18: 1890.2 | C18: 438 | D18: 3037 | E18: 4423 | F18: =C18*(1-25%) -> 328.5 | G18: =D18*(1-25%)^2 -> 1708.3125 | H18: =E18*(1-25%)^3 -> 1865.9531
A19: - A terme | B19: 72205.1 | C19: 89010 | D19: 180282 | E19: 137170 | F19: =C19*(1-25%) -> 66757.5 | G19: =D19*(1-25%)^2 -> 101408.62 | H19: =E19*(1-25%)^3 -> 57868.594
A20: CPTES CREDITEURS DE LA CLIENTELE | B20: 50161.059 | C20: 56949 | D20: 101512 | E20: 136089 | F20: =C20*(1-25%) -> 42711.75 | G20: =D20*(1-25%)^2 -> 57100.5 | H20: =E20*(1-25%)^3 -> 57412.547
A21: - A vue | B21: 23989.094 | C21: 18450 | D21: 33242 | E21: 39612 | F21: =C21*(1-25%) -> 13837.5 | G21: =D21*(1-25%)^2 -> 18698.625 | H21: =E21*(1-25%)^3 -> 16711.312
A22: - A terme | B22: 26171.965 | C22: 38499 | D22: 68270 | E22: 96477 | F22: =C22*(1-25%) -> 28874.25 | G22: =D22*(1-25%)^2 -> 38401.875 | H22: =E22*(1-25%)^3 -> 40701.234
A23: Autres passifs | B23: 2297.337 | C23: 2323 | D23: 3740 | E23: 2886
A24: Provisions pour risques et charges | B24: 2994.787 | C24: 2948 | D24: 1600 | E24: 2135
A25: Financement LT | B25: 130 | C25: 6474.151 | D25: 3574.0033 | E25: 246.55586
A26: Capitaux propres | B26: 25913.849 | C26: 25914.849 | D26: 25914.849 | E26: 59168.541 | F26: =C26*(1-7%) -> 24100.81 | G26: =D26*(1-7%)^2 -> 22413.753 | H26: =E26*(1-7%)^3 -> 47592.63
A27: FRBG | B27: 476.541 | C27: 476.541 | D27: 476.541 | E27: 476.541 | F27: =C27*(1-7%) -> 443.18313 | G27: =D27*(1-7%)^2 -> 412.16031 | H27: =E27*(1-7%)^3 -> 383.30909
A28: Capital souscrit | B28: 18000.179 | C28: 18000.179 | D28: 18000.179 | E28: 50458 | F28: =C28*(1-7%) -> 16740.166 | G28: =D28*(1-7%)^2 -> 15568.355 | H28: =E28*(1-7%)^3 -> 40586.246
A29: Prime d'émission | B29: 2.22 | C29: 2.22 | D29: 2.22 | E29: 2754 | F29: =C29*(1-7%) -> 2.0646 | G29: =D29*(1-7%)^2 -> 1.920078 | H29: =E29*(1-7%)^3 -> 2215.1992
A30: Réserves | B30: 429.975 | C30: 436 | D30: 457 | E30: 557 | F30: =C30*(1-7%) -> 405.48 | G30: =D30*(1-7%)^2 -> 395.2593 | H30: =E30*(1-7%)^3 -> 448.02685
A31: Report à nouveau | B31: 7004.934 | C31: 6999.909 | D31: 6978.909 | E31: 1944 | F31: =C31*(1-7%) -> 6509.9154 | G31: =D31*(1-7%)^2 -> 6036.0584 | H31: =E31*(1-7%)^3 -> 1563.67
A32: Résultat de l'exercice | B32: 0 | C32: 0 | D32: 0 | E32: 2979 | F32: =C32*(1-7%) -> 0 | G32: =D32*(1-7%)^2 -> 0 | H32: =E32*(1-7%)^3 -> 2396.1795
A33: Dividende | B33: 0 | F33: =C33*(1-7%) -> 0 | G33: =D33*(1-7%)^2 -> 0 | H33: =E33*(1-7%)^3 -> 0
A34: Total passif | B34: =B26+B24+B23+B20+B17+B25 -> 155592.33 | C34: =C26+C25+C24+C23+C20+C17 -> 184057 | D34: =D17+D20+D23+D24+D26+D25 -> 319659.85 | E34: =E26+E25+E24+E23+E20+E17 -> 342118.1

Sheet Courbe des taux
A1: 46022 | D1: 1 | E1: 2 | F1: 3 | G1: 4 | H1: 5 | I1: 6 | J1: 7 | K1: 8 | L1: 9 | M1: 10 | N1: 11 | O1: 12 | P1: 13 | Q1: 14 | R1: 15 | S1: 16 | T1: 17 | U1: 18 | V1: 19 | W1: 20 | X1: 21 | Y1: 22 | Z1: 23 | AA1: 24 | AB1: 25 | AC1: 26 | AD1: 27 | AE1: 28 | AF1: 29 | AG1: 30 | AH1: 31 | AI1: 32 | AJ1: 33 | AK1: 34 | AL1: 35 | AM1: 36 | AN1: 37 | AO1: 38 | AP1: 39 | AQ1: 40 | AR1: 41 | AS1: 42 | AT1: 43 | AU1: 44 | AV1: 45 | AW1: 46 | AX1: 47 | AY1: 48 | AZ1: 49 | BA1: 50 | BB1: 51 | BC1: 52 | BD1: 53 | BE1: 54 | BF1: 55 | BG1: 56 | BH1: 57 | BI1: 58 | BJ1: 59 | BK1: 60 | BL1: 61 | BM1: 62 | BN1: 63 | BO1: 64 | BP1: 65 | BQ1: 66 | BR1: 67 | BS1: 68 | BT1: 69 | BU1: 70 | BV1: 71 | BW1: 72 | BX1: 73 | BY1: 74 | BZ1: 75 | CA1: 76 | CB1: 77 | CC1: 78 | CD1: 79 | CE1: 80 | CF1: 81 | CG1: 82 | CH1: 83 | CI1: 84 | CJ1: 85 | CK1: 86 | CL1: 87 | CM1: 88 | CN1: 89 | CO1: 90 | CP1: 91 | CQ1: 92 | CR1: 93 | CS1: 94 | CT1: 95 | CU1: 96 | CV1: 97 | CW1: 98 | CX1: 99 | CY1: 100 | CZ1: 101 | DA1: 102 | DB1: 103 | DC1: 104 | DD1: 105 | DE1: 106 | DF1: 107 | DG1: 108 | DH1: 109 | DI1: 110 | DJ1: 111 | DK1: 112 | DL1: 113 | DM1: 114 | DN1: 115 | DO1: 116 | DP1: 117 | DQ1: 118 | DR1: 119 | DS1: 120
A2: Maturité | B2: Zero Coupon | D2: M1 | E2: M2 | F2: M3 | G2: M4 | H2: M5 | I2: M6 | J2: M7 | K2: M8 | L2: M9 | M2: M10 | N2: M11 | O2: M12 | P2: M13 | Q2: M14 | R2: M15 | S2: M16 | T2: M17 | U2: M18 | V2: M19 | W2: M20 | X2: M21 | Y2: M22 | Z2: M23 | AA2: M24 | AB2: M25 | AC2: M26 | AD2: M27 | AE2: M28 | AF2: M29 | AG2: M30 | AH2: M31 | AI2: M32 | AJ2: M33 | AK2: M34 | AL2: M35 | AM2: M36 | AN2: M37 | AO2: M38 | AP2: M39 | AQ2: M40 | AR2: M41 | AS2: M42 | AT2: M43 | AU2: M44 | AV2: M45 | AW2: M46 | AX2: M47 | AY2: M48 | AZ2: M49 | BA2: M50 | BB2: M51 | BC2: M52 | BD2: M53 | BE2: M54 | BF2: M55 | BG2: M56 | BH2: M57 | BI2: M58 | BJ2: M59 | BK2: M60 | BL2: M61 | BM2: M62 | BN2: M63 | BO2: M64 | BP2: M65 | BQ2: M66 | BR2: M67 | BS2: M68 | BT2: M69 | BU2: M70 | BV2: M71 | BW2: M72 | BX2: M73 | BY2: M74 | BZ2: M75 | CA2: M76 | CB2: M77 | CC2: M78 | CD2: M79 | CE2: M80 | CF2: M81 | CG2: M82 | CH2: M83 | CI2: M84 | CJ2: M85 | CK2: M86 | CL2: M87 | CM2: M88 | CN2: M89 | CO2: M90 | CP2: M91 | CQ2: M92 | CR2: M93 | CS2: M94 | CT2: M95 | CU2: M96 | CV2: M97 | CW2: M98 | CX2: M99 | CY2: M100 | CZ2: M101 | DA2: M102 | DB2: M103 | DC2: M104 | DD2: M105 | DE2: M106 | DF2: M107 | DG2: M108 | DH2: M109 | DI2: M110 | DJ2: M111 | DK2: M112 | DL2: M113 | DM2: M114 | DN2: M115 | DO2: M116 | DP2: M117 | DQ2: M118 | DR2: M119 | DS2: M120
A3: 1 mois | B3: 0.051698 | D3: 0.051698 | E3: =D3+(F3-D3)*((E1-D1)/(F1-D1)) -> 0.059998 | F3: 0.068298 | G3: =F3+(I3-F3)*((G1-F1)/(I1-F1)) -> 0.06917 | H3: =F3+(I3-F3)*((H1-F1)/(I1-F1)) -> 0.070042 | I3: 0.070914 | J3: =I3+(L3-I3)*((J1-I1)/(L1-I1)) -> 0.073168333 | K3: =I3+(L3-I3)*((K1-I1)/(L1-I1)) -> 0.075422667 | L3: 0.077677 | M3: =L3+(O3-L3)*((M1-L1)/(O1-L1)) -> 0.075832 | N3: =L3+(O3-L3)*((N1-L1)/(O1-L1)) -> 0.073987 | O3: 0.072142 | P3: =+O3+(AA3-O3)*((P1-O1)/(AA1-O1)) -> 0.072006667 | AA3: 0.070518 | AM3: 0.076427 | AY3: 0.076692 | BK3: 0.076553 | BW3: 0.075965 | CI3: 0.075029 | CU3: 0.07462 | DG3: 0.074201 | DS3: 0.073719
A4: 3 mois | B4: 0.068298
A5: 6 mois | B5: 0.070914
A6: 9 mois | B6: 0.077677
A7: 1 an | B7: 0.072142
A8: 2 ans | B8: 0.070518
A9: 3 ans | B9: 0.076427
A10: 4 ans | B10: 0.076692
A11: 5 ans | B11: 0.076553
A12: 6 ans | B12: 0.075965
A13: 7 ans | B13: 0.075029
A14: 8 ans | B14: 0.07462
A15: 9 ans | B15: 0.074201
A16: 10 ans | B16: 0.073719
A18: Formule de l'interpolation linéaire

Sheet Stress test de liquidité
A1: Scenario 1 : événement idiosyncratique
A2: Actifs | B2: choc | D2: CREANCES SUR LES ETS DE CREDIT | E2: 28006.945 | F2: 24611 | G2: 34452 | H2: 27054
A3: Créances sur les éts de crédit | B3: 0.04997094 | D3: - A vue | E3: 19086.274 | F3: 16458 | G3: 28608 | H3: 26797
A4: Créances sur la clientèle | B4: -0.05804987 | D4: - A terme | E4: 8920.671 | F4: 8153 | G4: 5844 | H4: 257
A5: Passifs | D5: CREANCES SUR LA CLIENTELE | E5: 125650.32 | F5: =F6+F7+F8 -> 157553 | G5: 267467 | H5: 297941
A6: Dettes envers éts de crédit | B6: -0.25307099 | D6: - Créances commerciales | E6: 358.117 | F6: 5939 | G6: 3970 | H6: 18036
A7: Comptes créditeurs de la clientèle | B7: -0.01552861 | D7: - Autres concours à la clientèle | E7: 49615.566 | F7: 60919 | G7: 146749 | H7: 159220
A8: Capitaux propres | B8: -0.074579439 | D8: - Comptes ordinaires débiteurs | E8: 75676.636 | F8: 90695 | G8: 116748 | H8: 120685
A10: Scenario 2 : évènement d’ampleur systémique
A11: Actifs | B11: Choc
A12: Caisse, banques centrales | B12: -0.15
A13: Créances sur les éts de crédit | B13: -0.095576719
A14: Créances sur la clientèle | B14: -0.0059412866
A15: Passifs
A16: Comptes créditeurs de la clientèle | B16: -0.042344284
A17: Capitaux propres | B17: -0.048425808
A19: Scenario 3 : mixte (ou combiné)
A20: Actifs | B20: Choc
A21: Caisse, banques centrales | B21: -0.8772068
A22: Créances sur les éts de crédit | B22: -0.45621183
A23: Créances sur la clientèle | B23: -0.057346031
A24: Passifs
A25: Comptes créditeurs de la clientèle | B25: -0.28354281
A26: Capitaux propres | B26: -0.10822294

Sheet Dynamique stressé
E1: E n liquidité | G1: E n taux | I1: 0 | J1: 1 | K1: 2 | L1: 3 | M1: 4 | N1: 5 | O1: 6 | P1: 7 | Q1: 8 | R1: 9 | S1: 10 | T1: 11 | U1: 12 | V1: 13 | W1: 14 | X1: 15 | Y1: 16 | Z1: 17 | AA1: 18 | AB1: 19 | AC1: 20 | AD1: 21 | AE1: 22 | AF1: 23 | AG1: 24 | AH1: 25 | AI1: 26 | AJ1: 27 | AK1: 28 | AL1: 29 | AM1: 30 | AN1: 31 | AO1: 32 | AP1: 33 | AQ1: 34 | AR1: 35 | AS1: 36 | AT1: 37 | AU1: 38 | AV1: 39 | AW1: 40 | AX1: 41 | AY1: 42 | AZ1: 43 | BA1: 44 | BB1: 45 | BC1: 46 | BD1: 47 | BE1: 48 | BF1: 49 | BG1: 50 | BH1: 51 | BI1: 52 | BJ1: 53 | BK1: 54 | BL1: 55 | BM1: 56 | BN1: 57 | BO1: 58 | BP1: 59 | BQ1: 60 | BR1: 61 | BS1: 62 | BT1: 63 | BU1: 64 | BV1: 65 | BW1: 66 | BX1: 67 | BY1: 68 | BZ1: 69 | CA1: 70 | CB1: 71 | CC1: 72 | CD1: 73 | CE1: 74 | CF1: 75 | CG1: 76 | CH1: 77 | CI1: 78 | CJ1: 79 | CK1: 80 | CL1: 81 | CM1: 82 | CN1: 83 | CO1: 84 | CP1: 85 | CQ1: 86 | CR1: 87 | CS1: 88 | CT1: 89 | CU1: 90 | CV1: 91 | CW1: 92 | CX1: 93 | CY1: 94 | CZ1: 95 | DA1: 96 | DB1: 97 | DC1: 98 | DD1: 99 | DE1: 100 | DF1: 101 | DG1: 102 | DH1: 103 | DI1: 104 | DJ1: 105 | DK1: 106 | DL1: 107 | DM1: 108 | DN1: 109 | DO1: 110 | DP1: 111 | DQ1: 112 | DR1: 113 | DS1: 114 | DT1: 115 | DU1: 116 | DV1: 117 | DW1: 118 | DX1: 119 | DY1: 120
A2: Date d’arrêté | B2: Bilan | C2: Poste du bilan | D2: Taux d'intérèt moyen | E2: Loi d'écoulement | F2: Durée moyenne (en mois) | G2: Loi d'écoulement | H2: Durée moyenne (en mois) | I2: Montant (en k€) | J2: M1 | K2: M2 | L2: M3 | M2: M4 | N2: M5 | O2: M6 | P2: M7 | Q2: M8 | R2: M9 | S2: M10 | T2: M11 | U2: M12 | V2: M13 | W2: M14 | X2: M15 | Y2: M16 | Z2: M17 | AA2: M18 | AB2: M19 | AC2: M20 | AD2: M21 | AE2: M22 | AF2: M23 | AG2: M24 | AH2: M25 | AI2: M26 | AJ2: M27 | AK2: M28 | AL2: M29 | AM2: M30 | AN2: M31 | AO2: M32 | AP2: M33 | AQ2: M34 | AR2: M35 | AS2: M36 | AT2: M37 | AU2: M38 | AV2: M39 | AW2: M40 | AX2: M41 | AY2: M42 | AZ2: M43 | BA2: M44 | BB2: M45 | BC2: M46 | BD2: M47 | BE2: M48 | BF2: M49 | BG2: M50 | BH2: M51 | BI2: M52 | BJ2: M53 | BK2: M54 | BL2: M55 | BM2: M56 | BN2: M57 | BO2: M58 | BP2: M59 | BQ2: M60 | BR2: M61 | BS2: M62 | BT2: M63 | BU2: M64 | BV2: M65 | BW2: M66 | BX2: M67 | BY2: M68 | BZ2: M69 | CA2: M70 | CB2: M71 | CC2: M72 | CD2: M73 | CE2: M74 | CF2: M75 | CG2: M76 | CH2: M77 | CI2: M78 | CJ2: M79 | CK2: M80 | CL2: M81 | CM2: M82 | CN2: M83 | CO2: M84 | CP2: M85 | CQ2: M86 | CR2: M87 | CS2: M88 | CT2: M89 | CU2: M90 | CV2: M91 | CW2: M92 | CX2: M93 | CY2: M94 | CZ2: M95 | DA2: M96 | DB2: M97 | DC2: M98 | DD2: M99 | DE2: M100 | DF2: M101 | DG2: M102 | DH2: M103 | DI2: M104 | DJ2: M105 | DK2: M106 | DL2: M107 | DM2: M108 | DN2: M109 | DO2: M110 | DP2: M111 | DQ2: M112 | DR2: M113 | DS2: M114 | DT2: M115 | DU2: M116 | DV2: M117 | DW2: M118 | DX2: M119 | DY2: M120
A3: 46022 | B3: ACTIF | C3: CAISSE, BANQUES CENTRALES | I3: =I4+I8 -> 1255.124 | J3: =SUM(J4:J8) -> 1244.3264 | K3: =SUM(K4:K8) -> 1233.5288 | L3: =SUM(L4:L8) -> 1222.7312 | M3: =SUM(M4:M8) -> 1211.9336 | N3: =SUM(N4:N8) -> 1201.136 | O3: =SUM(O4:O8) -> 1190.3384 | P3: =SUM(P4:P8) -> 1179.5408 | Q3: =SUM(Q4:Q8) -> 1168.7433 | ... DY3: =SUM(DY4:DY8) -> 0
A4: 46022 | B4: ACTIF | C4: - Caisse | D4: 0 | E4: Linéaire | F4: 60 | G4: In fine | H4: 60 | I4: 40.58686 | J4: =IF(J$1<$F4,$I4*(($F4-J$1)/$F4),0) -> 39.910412 | K4: =IF(K$1<$F4,$I4*(($F4-K$1)/$F4),0) -> 39.233965 | L4: =IF(L$1<$F4,$I4*(($F4-L$1)/$F4),0) -> 38.557517 | M4: =IF(M$1<$F4,$I4*(($F4-M$1)/$F4),0) -> 37.881069 | N4: =IF(N$1<$F4,$I4*(($F4-N$1)/$F4),0) -> 37.204622 | O4: =IF(O$1<$F4,$I4*(($F4-O$1)/$F4),0) -> 36.528174 | P4: =IF(P$1<$F4,$I4*(($F4-P$1)/$F4),0) -> 35.851726 | Q4: =IF(Q$1<$F4,$I4*(($F4-Q$1)/$F4),0) -> 35.175279 | ... DY4: =IF(DY$1<$F4,$I4*(($F4-DY$1)/$F4),0) -> 0
C5: Nouvelles productions 2026 | U5: ='Plan Moyen Terme (PMT)'!C4-BAU_Liquidité_Dynamique!U4 -> -5.783928 | V5: =IF(AND(U1<V$1, V$1<=$F4),$U5*($F4-V$1)/($F4-$U1),0) -> -5.6634295 | W5: =IF(AND(V1<W$1, W$1<=$F4),$U5*($F4-W$1)/($F4-$U1),0) -> -5.542931 | X5: =IF(AND(W1<X$1, X$1<=$F4),$U5*($F4-X$1)/($F4-$U1),0) -> -5.4224325 | Y5: =IF(AND(X1<Y$1, Y$1<=$F4),$U5*($F4-Y$1)/($F4-$U1),0) -> -5.301934 | Z5: =IF(AND(Y1<Z$1, Z$1<=$F4),$U5*($F4-Z$1)/($F4-$U1),0) -> -5.1814355 | AA5: =IF(AND(Z1<AA$1, AA$1<=$F4),$U5*($F4-AA$1)/($F4-$U1),0) -> -5.060937 | AB5: =IF(AND(AA1<AB$1, AB$1<=$F4),$U5*($F4-AB$1)/($F4-$U1),0) -> -4.9404385 | AC5: =IF(AND(AB1<AC$1, AC$1<=$F4),$U5*($F4-AC$1)/($F4-$U1),0) -> -4.81994 | ... BQ5: =IF(AND(BP1<BQ$1, BQ$1<=$F4),$U5*($F4-BQ$1)/($F4-$U1),0) -> 0 | BR5: =IF(BR$1<$F4-$U1,$U5*($F4-BR$1)/($F4-$U1),0) -> 0 | BS5: =IF(BS$1<$F4-$U1,$U5*($F4-BS$1)/($F4-$U1),0) -> 0 | BT5: =IF(BT$1<$F4-$U1,$U5*($F4-BT$1)/($F4-$U1),0) -> 0 | BU5: =IF(BU$1<$F4-$U1,$U5*($F4-BU$1)/($F4-$U1),0) -> 0 | BV5: =IF(BV$1<$F4-$U1,$U5*($F4-BV$1)/($F4-$U1),0) -> 0 | BW5: =IF(BW$1<$F4-$U1,$U5*($F4-BW$1)/($F4-$U1),0) -> 0 | BX5: =IF(BX$1<$F4-$U1,$U5*($F4-BX$1)/($F4-$U1),0) -> 0 | BY5: =IF(BY$1<$F4-$U1,$U5*($F4-BY$1)/($F4-$U1),0) -> 0 | ... DY5: =IF(DY$1<$F4-$U1,$U5*($F4-DY$1)/($F4-$U1),0) -> 0
C6: Nouvelles productions 2027 | AG6: ='Plan Moyen Terme (PMT)'!D4-BAU_Liquidité_Dynamique!AG4 -> 274.5002 | AH6: =IF(AND(AG1<AH$1, AH$1<=$F4),$AG6*($F4-AH1)/($F4-$AG1),0) -> 266.8752 | AI6: =IF(AND(AH1<AI$1, AI$1<=$F4),$AG6*($F4-AI1)/($F4-$AG1),0) -> 259.25019 | AJ6: =IF(AND(AI1<AJ$1, AJ$1<=$F4),$AG6*($F4-AJ1)/($F4-$AG1),0) -> 251.62519 | AK6: =IF(AND(AJ1<AK$1, AK$1<=$F4),$AG6*($F4-AK1)/($F4-$AG1),0) -> 244.00018 | AL6: =IF(AND(AK1<AL$1, AL$1<=$F4),$AG6*($F4-AL1)/($F4-$AG1),0) -> 236.37518 | AM6: =IF(AND(AL1<AM$1, AM$1<=$F4),$AG6*($F4-AM1)/($F4-$AG1),0) -> 228.75017 | AN6: =IF(AND(AM1<AN$1, AN$1<=$F4),$AG6*($F4-AN1)/($F4-$AG1),0) -> 221.12516 | AO6: =IF(AND(AN1<AO$1, AO$1<=$F4),$AG6*($F4-AO1)/($F4-$AG1),0) -> 213.50016 | ... BQ6: =IF(AND(BP1<BQ$1, BQ$1<=$F4),$AG6*($F4-BQ1)/($F4-$AG1),0) -> 0 | BR6: =IF(BR$1<$F4-$AG1,$AG6*($F4-BR1)/($F4-$AG1),0) -> 0 | BS6: =IF(BS$1<$F4-$AG1,$AG6*($F4-BS1)/($F4-$AG1),0) -> 0 | BT6: =IF(BT$1<$F4-$AG1,$AG6*($F4-BT1)/($F4-$AG1),0) -> 0 | BU6: =IF(BU$1<$F4-$AG1,$AG6*($F4-BU1)/($F4-$AG1),0) -> 0 | BV6: =IF(BV$1<$F4-$AG1,$AG6*($F4-BV1)/($F4-$AG1),0) -> 0 | BW6: =IF(BW$1<$F4-$AG1,$AG6*($F4-BW1)/($F4-$AG1),0) -> 0 | BX6: =IF(BX$1<$F4-$AG1,$AG6*($F4-BX1)/($F4-$AG1),0) -> 0 | BY6: =IF(BY$1<$F4-$AG1,$AG6*($F4-BY1)/($F4-$AG1),0) -> 0 | ... DY6: =IF(DY$1<$F4-$AG1,$AG6*($F4-DY1)/($F4-$AG1),0) -> 0
C7: Nouvelles productions 2028 | AS7: ='Plan Moyen Terme (PMT)'!E4-BAU_Liquidité_Dynamique!AS4 -> 229.86212 | AT7: =IF(AND(AS1<AT$1, AT$1<=$F4),$AS$7*($F$4-AT1)/($F$4-$AS1),0) -> 220.28453 | AU7: =IF(AND(AT1<AU$1, AU$1<=$F4),$AS$7*($F$4-AU1)/($F$4-$AS1),0) -> 210.70694 | AV7: =IF(AND(AU1<AV$1, AV$1<=$F4),$AS$7*($F$4-AV1)/($F$4-$AS1),0) -> 201.12935 | AW7: =IF(AND(AV1<AW$1, AW$1<=$F4),$AS$7*($F$4-AW1)/($F$4-$AS1),0) -> 191.55176 | AX7: =IF(AND(AW1<AX$1, AX$1<=$F4),$AS$7*($F$4-AX1)/($F$4-$AS1),0) -> 181.97418 | AY7: =IF(AND(AX1<AY$1, AY$1<=$F4),$AS$7*($F$4-AY1)/($F$4-$AS1),0) -> 172.39659 | AZ7: =IF(AND(AY1<AZ$1, AZ$1<=$F4),$AS$7*($F$4-AZ1)/($F$4-$AS1),0) -> 162.819 | BA7: =IF(AND(AZ1<BA$1, BA$1<=$F4),$AS$7*($F$4-BA1)/($F$4-$AS1),0) -> 153.24141 | ... BQ7: =IF(AND(BP1<BQ$1, BQ$1<=$F4),$AS$7*($F$4-BQ1)/($F$4-$AS1),0) -> 0
A8: 46022 | B8: ACTIF | C8: - Compte courant BDF | D8: 0.00040572687 | E8: Linéaire | F8: 120 | G8: Ine fine | H8: 120 | I8: 1214.5371 | J8: =IF(J$1<$F8,$I8*(($F8-J$1)/$F8),0) -> 1204.416 | K8: =IF(K$1<$F8,$I8*(($F8-K$1)/$F8),0) -> 1194.2948 | L8: =IF(L$1<$F8,$I8*(($F8-L$1)/$F8),0) -> 1184.1737 | M8: =IF(M$1<$F8,$I8*(($F8-M$1)/$F8),0) -> 1174.0525 | N8: =IF(N$1<$F8,$I8*(($F8-N$1)/$F8),0) -> 1163.9314 | O8: =IF(O$1<$F8,$I8*(($F8-O$1)/$F8),0) -> 1153.8103 | P8: =IF(P$1<$F8,$I8*(($F8-P$1)/$F8),0) -> 1143.6891 | Q8: =IF(Q$1<$F8,$I8*(($F8-Q$1)/$F8),0) -> 1133.568 | ... DY8: =IF(DY$1<$F8,$I8*(($F8-DY$1)/$F8),0) -> 0
C9: Nouvelles productions 2026 | U9: ='Plan Moyen Terme (PMT)'!C5-BAU_Liquidité_Dynamique!U8 -> 175.23103 | V9: =IF(AND(U1<V$1, V$1<=$F8),$U9*($F8-V$1)/($F8-$U$1),0) -> 173.60852 | W9: =IF(AND(V1<W$1, W$1<=$F8),$U9*($F8-W$1)/($F8-$U$1),0) -> 171.98601 | X9: =IF(AND(W1<X$1, X$1<=$F8),$U9*($F8-X$1)/($F8-$U$1),0) -> 170.3635 | Y9: =IF(AND(X1<Y$1, Y$1<=$F8),$U9*($F8-Y$1)/($F8-$U$1),0) -> 168.74099 | Z9: =IF(AND(Y1<Z$1, Z$1<=$F8),$U9*($F8-Z$1)/($F8-$U$1),0) -> 167.11848 | AA9: =IF(AND(Z1<AA$1, AA$1<=$F8),$U9*($F8-AA$1)/($F8-$U$1),0) -> 165.49597 | AB9: =IF(AND(AA1<AB$1, AB$1<=$F8),$U9*($F8-AB$1)/($F8-$U$1),0) -> 163.87347 | AC9: =IF(AND(AB1<AC$1, AC$1<=$F8),$U9*($F8-AC$1)/($F8-$U$1),0) -> 162.25096 | ... DY9: =IF(AND(DX1<DY$1, DY$1<=$F8),$U9*($F8-DY$1)/($F8-$U$1),0) -> 0
C10: Nouvelles productions 2027 | AG10: ='Plan Moyen Terme (PMT)'!D5-BAU_Liquidité_Dynamique!AG8 -> 6047.3703 | AH10: =IF(AND(AG1<AH$1, AH$1<=$F8),$AG10*($F8-AH$1)/($F8-$AG$1),0) -> 5984.3769 | AI10: =IF(AND(AH1<AI$1, AI$1<=$F8),$AG10*($F8-AI$1)/($F8-$AG$1),0) -> 5921.3834 | AJ10: =IF(AND(AI1<AJ$1, AJ$1<=$F8),$AG10*($F8-AJ$1)/($F8-$AG$1),0) -> 5858.39 | AK10: =IF(AND(AJ1<AK$1, AK$1<=$F8),$AG10*($F8-AK$1)/($F8-$AG$1),0) -> 5795.3965 | AL10: =IF(AND(AK1<AL$1, AL$1<=$F8),$AG10*($F8-AL$1)/($F8-$AG$1),0) -> 5732.4031 | AM10: =IF(AND(AL1<AM$1, AM$1<=$F8),$AG10*($F8-AM$1)/($F8-$AG$1),0) -> 5669.4097 | AN10: =IF(AND(AM1<AN$1, AN$1<=$F8),$AG10*($F8-AN$1)/($F8-$AG$1),0) -> 5606.4162 | AO10: =IF(AND(AN1<AO$1, AO$1<=$F8),$AG10*($F8-AO$1)/($F8-$AG$1),0) -> 5543.4228 | ... DY10: =IF(AND(DX1<DY$1, DY$1<=$F8),$AG10*($F8-DY$1)/($F8-$AG$1),0) -> 0
C11: Nouvelles productions 2028 | AS11: ='Plan Moyen Terme (PMT)'!E5-BAU_Liquidité_Dynamique!AS8 -> 4440.824 | AT11: =IF(AND(AS1<AT$1, AT$1<=$F8),$AS11*($F8-AT$1)/($F8-$AS$1),0) -> 4387.9571 | AU11: =IF(AND(AT1<AU$1, AU$1<=$F8),$AS11*($F8-AU$1)/($F8-$AS$1),0) -> 4335.0901 | AV11: =IF(AND(AU1<AV$1, AV$1<=$F8),$AS11*($F8-AV$1)/($F8-$AS$1),0) -> 4282.2232 | AW11: =IF(AND(AV1<AW$1, AW$1<=$F8),$AS11*($F8-AW$1)/($F8-$AS$1),0) -> 4229.3562 | AX11: =IF(AND(AW1<AX$1, AX$1<=$F8),$AS11*($F8-AX$1)/($F8-$AS$1),0) -> 4176.4893 | AY11: =IF(AND(AX1<AY$1, AY$1<=$F8),$AS11*($F8-AY$1)/($F8-$AS$1),0) -> 4123.6223 | AZ11: =IF(AND(AY1<AZ$1, AZ$1<=$F8),$AS11*($F8-AZ$1)/($F8-$AS$1),0) -> 4070.7553 | BA11: =IF(AND(AZ1<BA$1, BA$1<=$F8),$AS11*($F8-BA$1)/($F8-$AS$1),0) -> 4017.8884 | ... DY11: =IF(AND(DX1<DY$1, DY$1<=$F8),$AS11*($F8-DY$1)/($F8-$AS$1),0) -> 0
A12: 46022 | B12: ACTIF | C12: CREANCES SUR LES ETS DE CREDIT | I12: =I13+I17 -> 28006.945 | J12: =SUM(J13:J17) -> 24825.899 | K12: =SUM(K13:K17) -> 21644.854 | L12: =SUM(L13:L17) -> 18463.808 | M12: =SUM(M13:M17) -> 15282.762 | N12: =SUM(N13:N17) -> 12101.717 | O12: =SUM(O13:O17) -> 8920.671 | P12: =SUM(P13:P17) -> 8920.671 | Q12: =SUM(Q13:Q17) -> 8920.671 | ... DY12: =SUM(DY13:DY17) -> 0
A13: 46022 | B13: ACTIF | C13: - A vue | D13: 0 | E13: Linéaire | F13: 6 | G13: Linéaire | H13: 6 | I13: 19086.274 | J13: =IF(J$1<$F13,$I13*(($F13-J$1)/$F13),0) -> 15905.228 | K13: =IF(K$1<$F13,$I13*(($F13-K$1)/$F13),0) -> 12724.183 | L13: =IF(L$1<$F13,$I13*(($F13-L$1)/$F13),0) -> 9543.137 | M13: =IF(M$1<$F13,$I13*(($F13-M$1)/$F13),0) -> 6362.0913 | N13: =IF(N$1<$F13,$I13*(($F13-N$1)/$F13),0) -> 3181.0457 | O13: =IF(O$1<$F13,$I13*(($F13-O$1)/$F13),0) -> 0 | P13: =IF(P$1<$F13,$I13*(($F13-P$1)/$F13),0) -> 0 | Q13: =IF(Q$1<$F13,$I13*(($F13-Q$1)/$F13),0) -> 0 | ... DY13: =IF(DY$1<$F13,$I13*(($F13-DY$1)/$F13),0) -> 0
C14: Nouvelles productions 2026=0
C15: Nouvelles productions 2027=0
C16: Nouvelles productions 2028=0
A17: 46022 | B17: ACTIF | C17: - A terme | D17: 0.02489751 | E17: In fine | F17: 12 | G17: In fine | H17: 12 | I17: 8920.671 | J17: =IF(J$1<$F17,$I17,0) -> 8920.671 | K17: =IF(K$1<$F17,$I17,0) -> 8920.671 | L17: =IF(L$1<$F17,$I17,0) -> 8920.671 | M17: =IF(M$1<$F17,$I17,0) -> 8920.671 | N17: =IF(N$1<$F17,$I17,0) -> 8920.671 | O17: =IF(O$1<$F17,$I17,0) -> 8920.671 | P17: =IF(P$1<$F17,$I17,0) -> 8920.671 | Q17: =IF(Q$1<$F17,$I17,0) -> 8920.671 | ... DY17: =IF(DY$1<$F17,$I17,0) -> 0
C18: Nouvelles productions 2026=0
C19: Nouvelles productions 2027=0 | J19: =PMT($D22/12,$F22,$I22) -> -6.7325943 | K19: =I22*D22/12 -> 1.4456894 | AH19: =AH17 -> 0 | AI19: =AG23*D22/12 -> 17.499894
C20: Nouvelles productions 2028=0
A21: 46022 | B21: ACTIF | C21: CREANCES SUR LA CLIENTELE | I21: =I22+I26+I30 -> 125650.32 | J21: =SUM(J22:J30) -> 45066.509 | K21: =SUM(K22:K30) -> 40146.149 | L21: =SUM(L22:L30) -> 35212.566 | M21: =SUM(M22:M30) -> 30265.727 | N21: =SUM(N22:N30) -> 25305.594 | O21: =SUM(O22:O30) -> 20332.132 | P21: =SUM(P22:P30) -> 15345.305 | Q21: =SUM(Q22:Q30) -> 10345.078 | ... DY21: =SUM(DY22:DY30) -> 0
A22: 46022 | B22: ACTIF | C22: - Créances commerciales | D22: 0.048443032 | E22: Constant | F22: 60 | G22: Constant | H22: 60 | I22: 358.117 | J22: =IF(J$1<$F22,(I22*(1+($D22/12)))-(-PMT($D22/12,$F22,$I22)),0) -> 352.8301 | K22: =IF(K$1<$F22,(J22*(1+($D22/12)))-(-PMT($D22/12,$F22,$I22)),0) -> 347.52185 | L22: =IF(L$1<$F22,(K22*(1+($D22/12)))-(-PMT($D22/12,$F22,$I22)),0) -> 342.19217 | M22: =IF(M$1<$F22,(L22*(1+($D22/12)))-(-PMT($D22/12,$F22,$I22)),0) -> 336.84098 | N22: =IF(N$1<$F22,(M22*(1+($D22/12)))-(-PMT($D22/12,$F22,$I22)),0) -> 331.46818 | O22: =IF(O$1<$F22,(N22*(1+($D22/12)))-(-PMT($D22/12,$F22,$I22)),0) -> 326.0737 | P22: =IF(P$1<$F22,(O22*(1+($D22/12)))-(-PMT($D22/12,$F22,$I22)),0) -> 320.65744 | Q22: =IF(Q$1<$F22,(P22*(1+($D22/12)))-(-PMT($D22/12,$F22,$I22)),0) -> 315.21931 | ... DY22: =IF(DY$1<$F22,(DX22*(1+($D22/12)))-(-PMT($D22/12,$F22,$I22)),0) -> 0
C23: Nouvelles productions 2026 | U23: ='Plan Moyen Terme (PMT)'!C10-BAU_Liquidité_Dynamique!U22 -> 5645.7536 | V23: =IF(AND(U1<V$1, V$1<=$F$22),(U23*(1+($D$22/12)))-(-PMT($D$22/12,$F$22-$U1,$U$23)),0) -> 5538.9252 | W23: =IF(AND(V1<W$1, W$1<=$F$22),(V23*(1+($D$22/12)))-(-PMT($D$22/12,$F$22-$U1,$U$23)),0) -> 5431.6655 | X23: =IF(AND(W1<X$1, X$1<=$F$22),(W23*(1+($D$22/12)))-(-PMT($D$22/12,$F$22-$U1,$U$23)),0) -> 5323.9727 | Y23: =IF(AND(X1<Y$1, Y$1<=$F$22),(X23*(1+($D$22/12)))-(-PMT($D$22/12,$F$22-$U1,$U$23)),0) -> 5215.8453 | Z23: =IF(AND(Y1<Z$1, Z$1<=$F$22),(Y23*(1+($D$22/12)))-(-PMT($D$22/12,$F$22-$U1,$U$23)),0) -> 5107.2813 | AA23: =IF(AND(Z1<AA$1, AA$1<=$F$22),(Z23*(1+($D$22/12)))-(-PMT($D$22/12,$F$22-$U1,$U$23)),0) -> 4998.2791 | AB23: =IF(AND(AA1<AB$1, AB$1<=$F$22),(AA23*(1+($D$22/12)))-(-PMT($D$22/12,$F$22-$U1,$U$23)),0) -> 4888.8369 | AC23: =IF(AND(AB1<AC$1, AC$1<=$F$22),(AB23*(1+($D$22/12)))-(-PMT($D$22/12,$F$22-$U1,$U$23)),0) -> 4778.9528 | ... BQ23: =IF(AND(BP1<BQ$1, BQ$1<=$F$22),(BP23*(1+($D$22/12)))-(-PMT($D$22/12,$F$22-$U1,$U$23)),0) -> -5.1727511e-12
C24: Nouvelles productions 2027 | AG24: ='Plan Moyen Terme (PMT)'!D10-BAU_Liquidité_Dynamique!AG22 -> 3744.8375 | AH24: =IF(AND(AG1<AH$1, AH$1<=$F22),(AG24*(1+$D22/12))+(PMT($D22/12,$F22-$AG1,$AG24)),0) -> 3647.9805 | AI24: =IF(AND(AH1<AI$1, AI$1<=$F22),(AH24*(1+$D22/12))+(PMT($D22/12,$F22-$AG1,$AG24)),0) -> 3550.7326 | AJ24: =IF(AND(AI1<AJ$1, AJ$1<=$F22),(AI24*(1+$D22/12))+(PMT($D22/12,$F22-$AG1,$AG24)),0) -> 3453.0921 | AK24: =IF(AND(AJ1<AK$1, AK$1<=$F22),(AJ24*(1+$D22/12))+(PMT($D22/12,$F22-$AG1,$AG24)),0) -> 3355.0574 | AL24: =IF(AND(AK1<AL$1, AL$1<=$F22),(AK24*(1+$D22/12))+(PMT($D22/12,$F22-$AG1,$AG24)),0) -> 3256.6269 | AM24: =IF(AND(AL1<AM$1, AM$1<=$F22),(AL24*(1+$D22/12))+(PMT($D22/12,$F22-$AG1,$AG24)),0) -> 3157.7991 | AN24: =IF(AND(AM1<AN$1, AN$1<=$F22),(AM24*(1+$D22/12))+(PMT($D22/12,$F22-$AG1,$AG24)),0) -> 3058.5724 | AO24: =IF(AND(AN1<AO$1, AO$1<=$F22),(AN24*(1+$D22/12))+(PMT($D22/12,$F22-$AG1,$AG24)),0) -> 2958.945 | ... BQ24: =IF(AND(BP1<BQ$1, BQ$1<=$F22),(BP24*(1+$D22/12))+(PMT($D22/12,$F22-$AG1,$AG24)),0) -> -1.7337243e-12
C25: Nouvelles productions 2028 | AS25: ='Plan Moyen Terme (PMT)'!E10-BAU_Liquidité_Dynamique!AS22 -> 17882.294 | AT25: =IF(AND($AS1<AT$1, AT$1<=$F22),(AS25*(1+$D22/12))+(PMT($D22/12,$F22-$AS1,$AS25)),0) -> 17171.208 | AU25: =IF(AND($AS1<AU$1, AU$1<=$F22),(AT25*(1+$D22/12))+(PMT($D22/12,$F22-$AS1,$AS25)),0) -> 16457.252 | AV25: =IF(AND($AS1<AV$1, AV$1<=$F22),(AU25*(1+$D22/12))+(PMT($D22/12,$F22-$AS1,$AS25)),0) -> 15740.414 | AW25: =IF(AND($AS1<AW$1, AW$1<=$F22),(AV25*(1+$D22/12))+(PMT($D22/12,$F22-$AS1,$AS25)),0) -> 15020.682 | AX25: =IF(AND($AS1<AX$1, AX$1<=$F22),(AW25*(1+$D22/12))+(PMT($D22/12,$F22-$AS1,$AS25)),0) -> 14298.045 | AY25: =IF(AND($AS1<AY$1, AY$1<=$F22),(AX25*(1+$D22/12))+(PMT($D22/12,$F22-$AS1,$AS25)),0) -> 13572.49 | AZ25: =IF(AND($AS1<AZ$1, AZ$1<=$F22),(AY25*(1+$D22/12))+(PMT($D22/12,$F22-$AS1,$AS25)),0) -> 12844.006 | BA25: =IF(AND($AS1<BA$1, BA$1<=$F22),(AZ25*(1+$D22/12))+(PMT($D22/12,$F22-$AS1,$AS25)),0) -> 12112.582 | ... BQ25: =IF(AND($AS1<BQ$1, BQ$1<=$F22),(BP25*(1+$D22/12))+(PMT($D22/12,$F22-$AS1,$AS25)),0) -> -6.9348971e-12
A26: 46022 | B26: ACTIF | C26: - Autres concours à la clientèle | D26: 0.032228873 | E26: Constant | F26: 10 | G26: Constant | H26: 10 | I26: 49615.566 | J26: =IF(J$1<$F26,(I26*(1+($D26/12)))-(-PMT($D26/12,$F26,$I26)),0) -> 44713.679 | K26: =IF(K$1<$F26,(J26*(1+($D26/12)))-(-PMT($D26/12,$F26,$I26)),0) -> 39798.627 | L26: =IF(L$1<$F26,(K26*(1+($D26/12)))-(-PMT($D26/12,$F26,$I26)),0) -> 34870.374 | M26: =IF(M$1<$F26,(L26*(1+($D26/12)))-(-PMT($D26/12,$F26,$I26)),0) -> 29928.886 | N26: =IF(N$1<$F26,(M26*(1+($D26/12)))-(-PMT($D26/12,$F26,$I26)),0) -> 24974.125 | O26: =IF(O$1<$F26,(N26*(1+($D26/12)))-(-PMT($D26/12,$F26,$I26)),0) -> 20006.058 | P26: =IF(P$1<$F26,(O26*(1+($D26/12)))-(-PMT($D26/12,$F26,$I26)),0) -> 15024.648 | Q26: =IF(Q$1<$F26,(P26*(1+($D26/12)))-(-PMT($D26/12,$F26,$I26)),0) -> 10029.858 | ... DY26: =IF(DY$1<$F26,(DX26*(1+($D26/12)))-(-PMT($D26/12,$F26,$I26)),0) -> 0
C27: Nouvelles productions 2026=0
C28: Nouvelles productions 2027=0
C29: Nouvelles productions 2028=0
A30: 46022 | B30: ACTIF | C30: - Comptes ordinaires débiteurs | D30: 0.039912213 | E30: In fine | F30: 1 | G30: In fine | H30: 1 | I30: 75676.636 | J30: =IF(J$1<$F30,$I30,0) -> 0 | K30: =IF(K$1<$F30,$I30,0) -> 0 | L30: =IF(L$1<$F30,$I30,0) -> 0 | M30: =IF(M$1<$F30,$I30,0) -> 0 | N30: =IF(N$1<$F30,$I30,0) -> 0 | O30: =IF(O$1<$F30,$I30,0) -> 0 | P30: =IF(P$1<$F30,$I30,0) -> 0 | Q30: =IF(Q$1<$F30,$I30,0) -> 0 | ... DY30: =IF(DY$1<$F30,$I30,0) -> 0
C31: Nouvelles productions 2026=0
C32: Nouvelles productions 2027=0
C33: Nouvelles productions 2028=0
A34: 46022 | B34: ACTIF | C34: Investissements financiers | D34: 0.05 | E34: Ine fine | F34: 84 | G34: Ine fine | H34: 84 | I34: 28 | J34: =IF(J$1<$F34,$I34,0) -> 28 | K34: =IF(K$1<$F34,$I34,0) -> 28 | L34: =IF(L$1<$F34,$I34,0) -> 28 | M34: =IF(M$1<$F34,$I34,0) -> 28 | N34: =IF(N$1<$F34,$I34,0) -> 28 | O34: =IF(O$1<$F34,$I34,0) -> 28 | P34: =IF(P$1<$F34,$I34,0) -> 28 | Q34: =IF(Q$1<$F34,$I34,0) -> 28 | ... DY34: =IF(DY$1<$F34,$I34,0) -> 0
C35: Nouvelles productions 2026 | U35: ='Plan Moyen Terme (PMT)'!C13-U34 -> 0 | V35: =IF(AND($U1<V$1, V$1<$F$34),$U$35,0) -> 0 | W35: =IF(AND($U1<W$1, W$1<$F$34),$U$35,0) -> 0 | X35: =IF(AND($U1<X$1, X$1<$F$34),$U$35,0) -> 0 | Y35: =IF(AND($U1<Y$1, Y$1<$F$34),$U$35,0) -> 0 | Z35: =IF(AND($U1<Z$1, Z$1<$F$34),$U$35,0) -> 0 | AA35: =IF(AND($U1<AA$1, AA$1<$F$34),$U$35,0) -> 0 | AB35: =IF(AND($U1<AB$1, AB$1<$F$34),$U$35,0) -> 0 | AC35: =IF(AND($U1<AC$1, AC$1<$F$34),$U$35,0) -> 0 | ... CO35: =IF(AND($U1<CO$1, CO$1<$F$34),$U$35,0) -> 0
C36: Nouvelles productions 2027 | AG36: ='Plan Moyen Terme (PMT)'!D13-BAU_Liquidité_Dynamique!AG34 -> 9184 | AH36: =IF(AND($AG1<AH$1, AH$1<$F$34),$AG$36,0) -> 9184 | AI36: =IF(AND($AG1<AI$1, AI$1<$F$34),$AG$36,0) -> 9184 | AJ36: =IF(AND($AG1<AJ$1, AJ$1<$F$34),$AG$36,0) -> 9184 | AK36: =IF(AND($AG1<AK$1, AK$1<$F$34),$AG$36,0) -> 9184 | AL36: =IF(AND($AG1<AL$1, AL$1<$F$34),$AG$36,0) -> 9184 | AM36: =IF(AND($AG1<AM$1, AM$1<$F$34),$AG$36,0) -> 9184 | AN36: =IF(AND($AG1<AN$1, AN$1<$F$34),$AG$36,0) -> 9184 | AO36: =IF(AND($AG1<AO$1, AO$1<$F$34),$AG$36,0) -> 9184 | ... CO36: =IF(AND($AG1<CO$1, CO$1<$F$34),$AG$36,0) -> 0
C37: Nouvelles productions 2028 | AS37: ='Plan Moyen Terme (PMT)'!E13-BAU_Liquidité_Dynamique!AS34 -> 9478 | AT37: =IF(AND($AS1<AT$1, AT$1<$F$34),$AS$37,0) -> 9478 | AU37: =IF(AND($AS1<AU$1, AU$1<$F$34),$AS$37,0) -> 9478 | AV37: =IF(AND($AS1<AV$1, AV$1<$F$34),$AS$37,0) -> 9478 | AW37: =IF(AND($AS1<AW$1, AW$1<$F$34),$AS$37,0) -> 9478 | AX37: =IF(AND($AS1<AX$1, AX$1<$F$34),$AS$37,0) -> 9478 | AY37: =IF(AND($AS1<AY$1, AY$1<$F$34),$AS$37,0) -> 9478 | AZ37: =IF(AND($AS1<AZ$1, AZ$1<$F$34),$AS$37,0) -> 9478 | BA37: =IF(AND($AS1<BA$1, BA$1<$F$34),$AS$37,0) -> 9478 | ... CO37: =IF(AND($AS1<CO$1, CO$1<$F$34),$AS$37,0) -> 0
A38: 46022 | B38: ACTIF | C38: Immobilisations corporelles et incorporelles | E38: Linéaire | F38: 120 | G38: Linéaire | H38: 120 | I38: 82 | J38: =IF(J$1<$F38,$I38*(($F38-J$1)/$F38),0) -> 81.316667 | K38: =IF(K$1<$F38,$I38*(($F38-K$1)/$F38),0) -> 80.633333 | L38: =IF(L$1<$F38,$I38*(($F38-L$1)/$F38),0) -> 79.95 | M38: =IF(M$1<$F38,$I38*(($F38-M$1)/$F38),0) -> 79.266667 | N38: =IF(N$1<$F38,$I38*(($F38-N$1)/$F38),0) -> 78.583333 | O38: =IF(O$1<$F38,$I38*(($F38-O$1)/$F38),0) -> 77.9 | P38: =IF(P$1<$F38,$I38*(($F38-P$1)/$F38),0) -> 77.216667 | Q38: =IF(Q$1<$F38,$I38*(($F38-Q$1)/$F38),0) -> 76.533333 | ... DY38: =IF(DY$1<$F38,$I38*(($F38-DY$1)/$F38),0) -> 0
C39: Nouvelles productions 2026 | U39: ='Plan Moyen Terme (PMT)'!C14-BAU_Liquidité_Dynamique!U38 -> -13.8 | V39: =IF(AND(U$1<V$1, V$1<=$F38),$U39*($F38-V$1)/($F38-$U$1),0) -> -13.672222 | W39: =IF(AND(V$1<W$1, W$1<=$F38),$U39*($F38-W$1)/($F38-$U$1),0) -> -13.544444 | X39: =IF(AND(W$1<X$1, X$1<=$F38),$U39*($F38-X$1)/($F38-$U$1),0) -> -13.416667 | Y39: =IF(AND(X$1<Y$1, Y$1<=$F38),$U39*($F38-Y$1)/($F38-$U$1),0) -> -13.288889 | Z39: =IF(AND(Y$1<Z$1, Z$1<=$F38),$U39*($F38-Z$1)/($F38-$U$1),0) -> -13.161111 | AA39: =IF(AND(Z$1<AA$1, AA$1<=$F38),$U39*($F38-AA$1)/($F38-$U$1),0) -> -13.033333 | AB39: =IF(AND(AA$1<AB$1, AB$1<=$F38),$U39*($F38-AB$1)/($F38-$U$1),0) -> -12.905556 | AC39: =IF(AND(AB$1<AC$1, AC$1<=$F38),$U39*($F38-AC$1)/($F38-$U$1),0) -> -12.777778 | ... DY39: =IF(AND(DX$1<DY$1, DY$1<=$F38),$U39*($F38-DY$1)/($F38-$U$1),0) -> 0
C40: Nouvelles productions 2027 | AG40: ='Plan Moyen Terme (PMT)'!D14-BAU_Liquidité_Dynamique!AG38 -> 1.4 | AH40: =IF(AND(AG$1<AH$1, AH$1<=$F38),$AG40*($F38-AH$1)/($F38-$AG$1),0) -> 1.3854167 | AI40: =IF(AND(AH$1<AI$1, AI$1<=$F38),$AG40*($F38-AI$1)/($F38-$AG$1),0) -> 1.3708333 | AJ40: =IF(AND(AI$1<AJ$1, AJ$1<=$F38),$AG40*($F38-AJ$1)/($F38-$AG$1),0) -> 1.35625 | AK40: =IF(AND(AJ$1<AK$1, AK$1<=$F38),$AG40*($F38-AK$1)/($F38-$AG$1),0) -> 1.3416667 | AL40: =IF(AND(AK$1<AL$1, AL$1<=$F38),$AG40*($F38-AL$1)/($F38-$AG$1),0) -> 1.3270833 | AM40: =IF(AND(AL$1<AM$1, AM$1<=$F38),$AG40*($F38-AM$1)/($F38-$AG$1),0) -> 1.3125 | AN40: =IF(AND(AM$1<AN$1, AN$1<=$F38),$AG40*($F38-AN$1)/($F38-$AG$1),0) -> 1.2979167 | AO40: =IF(AND(AN$1<AO$1, AO$1<=$F38),$AG40*($F38-AO$1)/($F38-$AG$1),0) -> 1.2833333 | ... DY40: =IF(AND(DX$1<DY$1, DY$1<=$F38),$AG40*($F38-DY$1)/($F38-$AG$1),0) -> 0
C41: Nouvelles productions 2028 | AS41: ='Plan Moyen Terme (PMT)'!E14-BAU_Liquidité_Dynamique!AS38 -> -4.4 | AT41: =IF(AND(AS$1<AT$1, AT$1<=$F38),$AS41*($F38-AT$1)/($F38-$AS$1),0) -> -4.347619 | AU41: =IF(AND(AT$1<AU$1, AU$1<=$F38),$AS41*($F38-AU$1)/($F38-$AS$1),0) -> -4.2952381 | AV41: =IF(AND(AU$1<AV$1, AV$1<=$F38),$AS41*($F38-AV$1)/($F38-$AS$1),0) -> -4.2428571 | AW41: =IF(AND(AV$1<AW$1, AW$1<=$F38),$AS41*($F38-AW$1)/($F38-$AS$1),0) -> -4.1904762 | AX41: =IF(AND(AW$1<AX$1, AX$1<=$F38),$AS41*($F38-AX$1)/($F38-$AS$1),0) -> -4.1380952 | AY41: =IF(AND(AX$1<AY$1, AY$1<=$F38),$AS41*($F38-AY$1)/($F38-$AS$1),0) -> -4.0857143 | AZ41: =IF(AND(AY$1<AZ$1, AZ$1<=$F38),$AS41*($F38-AZ$1)/($F38-$AS$1),0) -> -4.0333333 | BA41: =IF(AND(AZ$1<BA$1, BA$1<=$F38),$AS41*($F38-BA$1)/($F38-$AS$1),0) -> -3.9809524 | ... DY41: =IF(AND(DX$1<DY$1, DY$1<=$F38),$AS41*($F38-DY$1)/($F38-$AS$1),0) -> 0
A42: 46022 | B42: ACTIF | C42: Autres actifs | E42: Linéaire | F42: 120 | G42: Linéaire | H42: 120 | I42: 570 | J42: =IF(J$1<$F42,$I42*(($F42-J$1)/$F42),0) -> 565.25 | K42: =IF(K$1<$F42,$I42*(($F42-K$1)/$F42),0) -> 560.5 | L42: =IF(L$1<$F42,$I42*(($F42-L$1)/$F42),0) -> 555.75 | M42: =IF(M$1<$F42,$I42*(($F42-M$1)/$F42),0) -> 551 | N42: =IF(N$1<$F42,$I42*(($F42-N$1)/$F42),0) -> 546.25 | O42: =IF(O$1<$F42,$I42*(($F42-O$1)/$F42),0) -> 541.5 | P42: =IF(P$1<$F42,$I42*(($F42-P$1)/$F42),0) -> 536.75 | Q42: =IF(Q$1<$F42,$I42*(($F42-Q$1)/$F42),0) -> 532 | ... DY42: =IF(DY$1<$F42,$I42*(($F42-DY$1)/$F42),0) -> 0
C43: Nouvelles productions 2026 | U43: ='Plan Moyen Terme (PMT)'!C15-BAU_Liquidité_Dynamique!U42 -> -3 | V43: =IF(AND(U$1<V$1, V$1<=$F42),$U43*($F42-V$1)/($F42-$U$1),0) -> -2.9722222 | W43: =IF(AND(V$1<W$1, W$1<=$F42),$U43*($F42-W$1)/($F42-$U$1),0) -> -2.9444444 | X43: =IF(AND(W$1<X$1, X$1<=$F42),$U43*($F42-X$1)/($F42-$U$1),0) -> -2.9166667 | Y43: =IF(AND(X$1<Y$1, Y$1<=$F42),$U43*($F42-Y$1)/($F42-$U$1),0) -> -2.8888889 | Z43: =IF(AND(Y$1<Z$1, Z$1<=$F42),$U43*($F42-Z$1)/($F42-$U$1),0) -> -2.8611111 | AA43: =IF(AND(Z$1<AA$1, AA$1<=$F42),$U43*($F42-AA$1)/($F42-$U$1),0) -> -2.8333333 | AB43: =IF(AND(AA$1<AB$1, AB$1<=$F42),$U43*($F42-AB$1)/($F42-$U$1),0) -> -2.8055556 | AC43: =IF(AND(AB$1<AC$1, AC$1<=$F42),$U43*($F42-AC$1)/($F42-$U$1),0) -> -2.7777778 | ... DY43: =IF(AND(DX$1<DY$1, DY$1<=$F42),$U43*($F42-DY$1)/($F42-$U$1),0) -> 0
C44: Nouvelles productions 2027 | AG44: ='Plan Moyen Terme (PMT)'!D15-BAU_Liquidité_Dynamique!AG42 -> 688 | AH44: =IF(AND(AG$1<AH$1, AH$1<=$F42),$AG44*($F42-AH$1)/($F42-$AG$1),0) -> 680.83333 | AI44: =IF(AND(AH$1<AI$1, AI$1<=$F42),$AG44*($F42-AI$1)/($F42-$AG$1),0) -> 673.66667 | AJ44: =IF(AND(AI$1<AJ$1, AJ$1<=$F42),$AG44*($F42-AJ$1)/($F42-$AG$1),0) -> 666.5 | AK44: =IF(AND(AJ$1<AK$1, AK$1<=$F42),$AG44*($F42-AK$1)/($F42-$AG$1),0) -> 659.33333 | AL44: =IF(AND(AK$1<AL$1, AL$1<=$F42),$AG44*($F42-AL$1)/($F42-$AG$1),0) -> 652.16667 | AM44: =IF(AND(AL$1<AM$1, AM$1<=$F42),$AG44*($F42-AM$1)/($F42-$AG$1),0) -> 645 | AN44: =IF(AND(AM$1<AN$1, AN$1<=$F42),$AG44*($F42-AN$1)/($F42-$AG$1),0) -> 637.83333 | AO44: =IF(AND(AN$1<AO$1, AO$1<=$F42),$AG44*($F42-AO$1)/($F42-$AG$1),0) -> 630.66667 | ... DY44: =IF(AND(DX$1<DY$1, DY$1<=$F42),$AG44*($F42-DY$1)/($F42-$AG$1),0) -> 0
C45: Nouvelles productions 2028 | AS45: ='Plan Moyen Terme (PMT)'!E15-BAU_Liquidité_Dynamique!AS42 -> 1628 | AT45: =IF(AND(AS$1<AT$1, AT$1<=$F42),$AS45*($F42-AT$1)/($F42-$AS$1),0) -> 1608.619 | AU45: =IF(AND(AT$1<AU$1, AU$1<=$F42),$AS45*($F42-AU$1)/($F42-$AS$1),0) -> 1589.2381 | AV45: =IF(AND(AU$1<AV$1, AV$1<=$F42),$AS45*($F42-AV$1)/($F42-$AS$1),0) -> 1569.8571 | AW45: =IF(AND(AV$1<AW$1, AW$1<=$F42),$AS45*($F42-AW$1)/($F42-$AS$1),0) -> 1550.4762 | AX45: =IF(AND(AW$1<AX$1, AX$1<=$F42),$AS45*($F42-AX$1)/($F42-$AS$1),0) -> 1531.0952 | AY45: =IF(AND(AX$1<AY$1, AY$1<=$F42),$AS45*($F42-AY$1)/($F42-$AS$1),0) -> 1511.7143 | AZ45: =IF(AND(AY$1<AZ$1, AZ$1<=$F42),$AS45*($F42-AZ$1)/($F42-$AS$1),0) -> 1492.3333 | BA45: =IF(AND(AZ$1<BA$1, BA$1<=$F42),$AS45*($F42-BA$1)/($F42-$AS$1),0) -> 1472.9524 | ... DY45: =IF(AND(DX$1<DY$1, DY$1<=$F42),$AS45*($F42-DY$1)/($F42-$AS$1),0) -> 0
C46: Total nouvelle production actif-2026 | I46: =SUM(I5+I9+I14+I18+I23+I27+I31+I35+I39+I43) -> 0 | J46: =SUM(J5+J9+J14+J18+J23+J27+J31+J35+J39+J43) -> 0 | K46: =SUM(K5+K9+K14+K18+K23+K27+K31+K35+K39+K43) -> 0 | L46: =SUM(L5+L9+L14+L18+L23+L27+L31+L35+L39+L43) -> 0 | M46: =SUM(M5+M9+M14+M18+M23+M27+M31+M35+M39+M43) -> 0 | N46: =SUM(N5+N9+N14+N18+N23+N27+N31+N35+N39+N43) -> 0 | O46: =SUM(O5+O9+O14+O18+O23+O27+O31+O35+O39+O43) -> 0 | P46: =SUM(P5+P9+P14+P18+P23+P27+P31+P35+P39+P43) -> 0 | ... DY46: =SUM(DY5+DY9+DY14+DY18+DY23+DY27+DY31+DY35+DY39+DY43) -> 0
C47: Total nouvelle production actif-2027 | I47: =SUM(I6+I10+I15+I19+I24+I28+I32+I36+I40+I44) -> 0 | J47: =SUM(J6+J10+J15+J19+J24+J28+J32+J36+J40+J44) -> -6.7325943 | K47: =SUM(K6+K10+K15+K19+K24+K28+K32+K36+K40+K44) -> 1.4456894 | L47: =SUM(L6+L10+L15+L19+L24+L28+L32+L36+L40+L44) -> 0 | M47: =SUM(M6+M10+M15+M19+M24+M28+M32+M36+M40+M44) -> 0 | N47: =SUM(N6+N10+N15+N19+N24+N28+N32+N36+N40+N44) -> 0 | O47: =SUM(O6+O10+O15+O19+O24+O28+O32+O36+O40+O44) -> 0 | P47: =SUM(P6+P10+P15+P19+P24+P28+P32+P36+P40+P44) -> 0 | ... DY47: =SUM(DY6+DY10+DY15+DY19+DY24+DY28+DY32+DY36+DY40+DY44) -> 0
C48: Total nouvelle production actif-2028 | I48: =SUM(I7+I11+I16+I20+I25+I29+I33+I37+I41+I45) -> 0 | J48: =SUM(J7+J11+J16+J20+J25+J29+J33+J37+J41+J45) -> 0 | K48: =SUM(K7+K11+K16+K20+K25+K29+K33+K37+K41+K45) -> 0 | L48: =SUM(L7+L11+L16+L20+L25+L29+L33+L37+L41+L45) -> 0 | M48: =SUM(M7+M11+M16+M20+M25+M29+M33+M37+M41+M45) -> 0 | N48: =SUM(N7+N11+N16+N20+N25+N29+N33+N37+N41+N45) -> 0 | O48: =SUM(O7+O11+O16+O20+O25+O29+O33+O37+O41+O45) -> 0 | P48: =SUM(P7+P11+P16+P20+P25+P29+P33+P37+P41+P45) -> 0 | ... DY48: =SUM(DY7+DY11+DY16+DY20+DY25+DY29+DY33+DY37+DY41+DY45) -> 0
A49: 46022 | B49: ACTIF | C49: Total actif | I49: =I3+I12+I21+I34+I38+I42 -> 155592.39 | J49: =J3+J12+J21+J34+J38+J42 -> 71811.302 | K49: =K3+K12+K21+K34+K38+K42 -> 63693.665 | L49: =L3+L12+L21+L34+L38+L42 -> 55562.806 | M49: =M3+M12+M21+M34+M38+M42 -> 47418.689 | N49: =N3+N12+N21+N34+N38+N42 -> 39261.28 | O49: =O3+O12+O21+O34+O38+O42 -> 31090.541 | P49: =P3+P12+P21+P34+P38+P42 -> 26087.483 | ... DY49: =DY3+DY12+DY21+DY34+DY38+DY42 -> 0
A50: 46022 | B50: PASSIF | C50: DETTES ENVERS ETS DE CREDIT | I50: =I51+I55 -> 74095.3 | J50: =SUM(J51:J55) -> 73528.24 | K50: =SUM(K51:K55) -> 73150.2 | L50: =SUM(L51:L55) -> 72772.16 | M50: =SUM(M51:M55) -> 72394.12 | N50: =SUM(N51:N55) -> 72205.1 | O50: =SUM(O51:O55) -> 72205.1 | P50: =SUM(P51:P55) -> 72205.1 | Q50: =SUM(Q51:Q55) -> 72205.1 | ... DY50: =SUM(DY51:DY55) -> 0
A51: 46022 | B51: PASSIF | C51: - A vue | D51: 0 | E51: 90%-20%*t, t<=4mois | F51: 4 | G51: In fine | H51: 4 | I51: 1890.2 | J51: =IF(J$1<=$F51,$I51*(90%-(20%*J$1)),0) -> 1323.14 | K51: =IF(K$1<=$F51,$I51*(90%-(20%*K$1)),0) -> 945.1 | L51: =IF(L$1<=$F51,$I51*(90%-(20%*L$1)),0) -> 567.06 | M51: =IF(M$1<=$F51,$I51*(90%-(20%*M$1)),0) -> 189.02 | N51: =IF(N$1<=$F51,$I51*(90%-(20%*N$1)),0) -> 0 | O51: =IF(O$1<=$F51,$I51*(90%-(20%*O$1)),0) -> 0 | P51: =IF(P$1<=$F51,$I51*(90%-(20%*P$1)),0) -> 0 | Q51: =IF(Q$1<=$F51,$I51*(90%-(20%*Q$1)),0) -> 0 | ... DY51: =IF(DY$1<=$F51,$I51*(90%-(20%*DY$1)),0) -> 0
C52: Nouvelles productions 2026=0
C53: Nouvelles productions 2027=0
C54: Nouvelles productions 2028=0
A55: 46022 | B55: PASSIF | C55: - A terme | D55: 0.0138965 | E55: Ine fine | F55: 24 | G55: Ine fine | H55: 24 | I55: 72205.1 | J55: =IF(J$1<$F55,$I55,0) -> 72205.1 | K55: =IF(K$1<$F55,$I55,0) -> 72205.1 | L55: =IF(L$1<$F55,$I55,0) -> 72205.1 | M55: =IF(M$1<$F55,$I55,0) -> 72205.1 | N55: =IF(N$1<$F55,$I55,0) -> 72205.1 | O55: =IF(O$1<$F55,$I55,0) -> 72205.1 | P55: =IF(P$1<$F55,$I55,0) -> 72205.1 | Q55: =IF(Q$1<$F55,$I55,0) -> 72205.1 | ... DY55: =IF(DY$1<$F55,$I55,0) -> 0
C56: Nouvelles productions 2026 | U56: ='Plan Moyen Terme (PMT)'!C19-BAU_Liquidité_Dynamique!U55 -> 16804.9 | V56: =IF(AND($U$1<V$1, V$1<$F$55),$U$56,0) -> 16804.9 | W56: =IF(AND($U$1<W$1, W$1<$F$55),$U$56,0) -> 16804.9 | X56: =IF(AND($U$1<X$1, X$1<$F$55),$U$56,0) -> 16804.9 | Y56: =IF(AND($U$1<Y$1, Y$1<$F$55),$U$56,0) -> 16804.9 | Z56: =IF(AND($U$1<Z$1, Z$1<$F$55),$U$56,0) -> 16804.9 | AA56: =IF(AND($U$1<AA$1, AA$1<$F$55),$U$56,0) -> 16804.9 | AB56: =IF(AND($U$1<AB$1, AB$1<$F$55),$U$56,0) -> 16804.9 | AC56: =IF(AND($U$1<AC$1, AC$1<$F$55),$U$56,0) -> 16804.9 | ... AG56: =IF(AND($U$1<AG$1, AG$1<$F$55),$U$56,0) -> 0
C57: Nouvelles productions 2027=0
C58: Nouvelles productions 2028=0
A59: 46022 | B59: PASSIF | C59: CPTES CREDITEURS DE LA CLIENTELE | I59: =I60+I64 -> 50161.059 | J59: =SUM(J60:J64) -> 43848.513 | K59: =SUM(K60:K64) -> 40644.299 | L59: =SUM(L60:L64) -> 38020.91 | M59: =SUM(M60:M64) -> 35873.06 | N59: =SUM(N60:N64) -> 34114.55 | O59: =SUM(O60:O64) -> 32674.804 | P59: =SUM(P60:P64) -> 31496.039 | Q59: =SUM(Q60:Q64) -> 30530.948 | ... DY59: =SUM(DY60:DY64) -> 8.1505852e-07
A60: 46022 | B60: PASSIF | C60: - A vue | D60: 0 | E60: 90%*exp(-20%*t), t<=120 mois | F60: 120 | G60: Linéaire | H60: 120 | I60: 23989.094 | J60: =IF(J$1<=$F60,$I60*(90%*EXP(-20%*J$1)),0) -> 17676.548 | K60: =IF(K$1<=$F60,$I60*(90%*EXP(-20%*K$1)),0) -> 14472.334 | L60: =IF(L$1<=$F60,$I60*(90%*EXP(-20%*L$1)),0) -> 11848.945 | M60: =IF(M$1<=$F60,$I60*(90%*EXP(-20%*M$1)),0) -> 9701.0953 | N60: =IF(N$1<=$F60,$I60*(90%*EXP(-20%*N$1)),0) -> 7942.585 | O60: =IF(O$1<=$F60,$I60*(90%*EXP(-20%*O$1)),0) -> 6502.8386 | P60: =IF(P$1<=$F60,$I60*(90%*EXP(-20%*P$1)),0) -> 5324.074 | Q60: =IF(Q$1<=$F60,$I60*(90%*EXP(-20%*Q$1)),0) -> 4358.9831 | ... DY60: =IF(DY$1<=$F60,$I60*(90%*EXP(-20%*DY$1)),0) -> 8.1505852e-07
C61: Nouvelles productions 2026 | U61: ='Plan Moyen Terme (PMT)'!C21-BAU_Liquidité_Dynamique!U60 -> 16491.383 | V61: =IF(AND($U$1<V$1, V$1<$F$60),$U61*(90%*EXP(-20%*(V$1-$U$1))),0) -> 12151.802 | W61: =IF(AND($U$1<W$1, W$1<$F$60),$U61*(90%*EXP(-20%*(W$1-$U$1))),0) -> 9949.0539 | X61: =IF(AND($U$1<X$1, X$1<$F$60),$U61*(90%*EXP(-20%*(X$1-$U$1))),0) -> 8145.5964 | Y61: =IF(AND($U$1<Y$1, Y$1<$F$60),$U61*(90%*EXP(-20%*(Y$1-$U$1))),0) -> 6669.0503 | Z61: =IF(AND($U$1<Z$1, Z$1<$F$60),$U61*(90%*EXP(-20%*(Z$1-$U$1))),0) -> 5460.1566 | AA61: =IF(AND($U$1<AA$1, AA$1<$F$60),$U61*(90%*EXP(-20%*(AA$1-$U$1))),0) -> 4470.3981 | AB61: =IF(AND($U$1<AB$1, AB$1<$F$60),$U61*(90%*EXP(-20%*(AB$1-$U$1))),0) -> 3660.0524 | AC61: =IF(AND($U$1<AC$1, AC$1<$F$60),$U61*(90%*EXP(-20%*(AC$1-$U$1))),0) -> 2996.5975 | ... DY61: =IF(AND($U$1<DY$1, DY$1<$F$60),$U61*(90%*EXP(-20%*(DY$1-$U$1))),0) -> 0
C62: Nouvelles productions 2027 | AG62: ='Plan Moyen Terme (PMT)'!D21-BAU_Liquidité_Dynamique!AG60 -> 33064.318 | AH62: =IF(AND($AG$1<AH$1, AH$1<$F$60),$AG62*(90%*EXP(-20%*(AH$1-$AG$1))),0) -> 24363.697 | AI62: =IF(AND($AG$1<AI$1, AI$1<$F$60),$AG62*(90%*EXP(-20%*(AI$1-$AG$1))),0) -> 19947.308 | AJ62: =IF(AND($AG$1<AJ$1, AJ$1<$F$60),$AG62*(90%*EXP(-20%*(AJ$1-$AG$1))),0) -> 16331.474 | AK62: =IF(AND($AG$1<AK$1, AK$1<$F$60),$AG62*(90%*EXP(-20%*(AK$1-$AG$1))),0) -> 13371.08 | AL62: =IF(AND($AG$1<AL$1, AL$1<$F$60),$AG62*(90%*EXP(-20%*(AL$1-$AG$1))),0) -> 10947.315 | AM62: =IF(AND($AG$1<AM$1, AM$1<$F$60),$AG62*(90%*EXP(-20%*(AM$1-$AG$1))),0) -> 8962.9031 | AN62: =IF(AND($AG$1<AN$1, AN$1<$F$60),$AG62*(90%*EXP(-20%*(AN$1-$AG$1))),0) -> 7338.2044 | AO62: =IF(AND($AG$1<AO$1, AO$1<$F$60),$AG62*(90%*EXP(-20%*(AO$1-$AG$1))),0) -> 6008.0137 | ... DY62: =IF(AND($AG$1<DY$1, DY$1<$F$60),$AG62*(90%*EXP(-20%*(DY$1-$AG$1))),0) -> 0
C63: Nouvelles productions 2028 | AS63: ='Plan Moyen Terme (PMT)'!E21-BAU_Liquidité_Dynamique!AS60 -> 39595.881 | AT63: =IF(AND($AS$1<AT$1, AT$1<$F$60),$AS63*(90%*EXP(-20%*(AT$1-$AS$1))),0) -> 29176.529 | AU63: =IF(AND($AS$1<AU$1, AU$1<$F$60),$AS63*(90%*EXP(-20%*(AU$1-$AS$1))),0) -> 23887.722 | AV63: =IF(AND($AS$1<AV$1, AV$1<$F$60),$AS63*(90%*EXP(-20%*(AV$1-$AS$1))),0) -> 19557.612 | AW63: =IF(AND($AS$1<AW$1, AW$1<$F$60),$AS63*(90%*EXP(-20%*(AW$1-$AS$1))),0) -> 16012.419 | AX63: =IF(AND($AS$1<AX$1, AX$1<$F$60),$AS63*(90%*EXP(-20%*(AX$1-$AS$1))),0) -> 13109.86 | AY63: =IF(AND($AS$1<AY$1, AY$1<$F$60),$AS63*(90%*EXP(-20%*(AY$1-$AS$1))),0) -> 10733.445 | AZ63: =IF(AND($AS$1<AZ$1, AZ$1<$F$60),$AS63*(90%*EXP(-20%*(AZ$1-$AS$1))),0) -> 8787.8017 | BA63: =IF(AND($AS$1<BA$1, BA$1<$F$60),$AS63*(90%*EXP(-20%*(BA$1-$AS$1))),0) -> 7194.8435 | ... DY63: =IF(AND($AS$1<DY$1, DY$1<$F$60),$AS63*(90%*EXP(-20%*(DY$1-$AS$1))),0) -> 0
A64: 46022 | B64: PASSIF | C64: - A terme | D64: 0.0083386457 | E64: In fine | F64: 60 | G64: In fine | H64: 60 | I64: 26171.965 | J64: =IF(J$1<$F64,$I64,0) -> 26171.965 | K64: =IF(K$1<$F64,$I64,0) -> 26171.965 | L64: =IF(L$1<$F64,$I64,0) -> 26171.965 | M64: =IF(M$1<$F64,$I64,0) -> 26171.965 | N64: =IF(N$1<$F64,$I64,0) -> 26171.965 | O64: =IF(O$1<$F64,$I64,0) -> 26171.965 | P64: =IF(P$1<$F64,$I64,0) -> 26171.965 | Q64: =IF(Q$1<$F64,$I64,0) -> 26171.965 | ... DY64: =IF(DY$1<$F64,$I64,0) -> 0
C65: Nouvelles productions 2026 | U65: ='Plan Moyen Terme (PMT)'!C22-BAU_Liquidité_Dynamique!U64 -> 12327.035 | V65: =IF(AND($U$1<V$1, V$1<$F$64),$U$65,0) -> 12327.035 | W65: =IF(AND($U$1<W$1, W$1<$F$64),$U$65,0) -> 12327.035 | X65: =IF(AND($U$1<X$1, X$1<$F$64),$U$65,0) -> 12327.035 | Y65: =IF(AND($U$1<Y$1, Y$1<$F$64),$U$65,0) -> 12327.035 | Z65: =IF(AND($U$1<Z$1, Z$1<$F$64),$U$65,0) -> 12327.035 | AA65: =IF(AND($U$1<AA$1, AA$1<$F$64),$U$65,0) -> 12327.035 | AB65: =IF(AND($U$1<AB$1, AB$1<$F$64),$U$65,0) -> 12327.035 | AC65: =IF(AND($U$1<AC$1, AC$1<$F$64),$U$65,0) -> 12327.035 | ... BQ65: =IF(AND($U$1<BQ$1, BQ$1<$F$64),$U$65,0) -> 0
C66: Nouvelles productions 2027 | AG66: ='Plan Moyen Terme (PMT)'!D22-BAU_Liquidité_Dynamique!AG64 -> 42098.035 | AH66: =IF(AND($AG$1<AH$1, AH$1<$F$64),$AG$66,0) -> 42098.035 | AI66: =IF(AND($AG$1<AI$1, AI$1<$F$64),$AG$66,0) -> 42098.035 | AJ66: =IF(AND($AG$1<AJ$1, AJ$1<$F$64),$AG$66,0) -> 42098.035 | AK66: =IF(AND($AG$1<AK$1, AK$1<$F$64),$AG$66,0) -> 42098.035 | AL66: =IF(AND($AG$1<AL$1, AL$1<$F$64),$AG$66,0) -> 42098.035 | AM66: =IF(AND($AG$1<AM$1, AM$1<$F$64),$AG$66,0) -> 42098.035 | AN66: =IF(AND($AG$1<AN$1, AN$1<$F$64),$AG$66,0) -> 42098.035 | AO66: =IF(AND($AG$1<AO$1, AO$1<$F$64),$AG$66,0) -> 42098.035 | ... BQ66: =IF(AND($AG$1<BQ$1, BQ$1<$F$64),$AG$66,0) -> 0
C67: Nouvelles productions 2028 | AS67: ='Plan Moyen Terme (PMT)'!E22-BAU_Liquidité_Dynamique!AS64 -> 70305.035 | AT67: =IF(AND($AS$1<AT$1, AT$1<$F$64),$AS$67,0) -> 70305.035 | AU67: =IF(AND($AS$1<AU$1, AU$1<$F$64),$AS$67,0) -> 70305.035 | AV67: =IF(AND($AS$1<AV$1, AV$1<$F$64),$AS$67,0) -> 70305.035 | AW67: =IF(AND($AS$1<AW$1, AW$1<$F$64),$AS$67,0) -> 70305.035 | AX67: =IF(AND($AS$1<AX$1, AX$1<$F$64),$AS$67,0) -> 70305.035 | AY67: =IF(AND($AS$1<AY$1, AY$1<$F$64),$AS$67,0) -> 70305.035 | AZ67: =IF(AND($AS$1<AZ$1, AZ$1<$F$64),$AS$67,0) -> 70305.035 | BA67: =IF(AND($AS$1<BA$1, BA$1<$F$64),$AS$67,0) -> 70305.035 | ... BQ67: =IF(AND($AS$1<BQ$1, BQ$1<$F$64),$AS$67,0) -> 0
A68: 46022 | B68: PASSIF | C68: Autres passifs | D68: 0 | E68: Linéaire | F68: 120 | G68: Linéaire | H68: 120 | I68: 2297.337 | J68: =IF(J$1<$F68,$I68*(($F68-J$1)/$F68),0) -> 2278.1925 | K68: =IF(K$1<$F68,$I68*(($F68-K$1)/$F68),0) -> 2259.048 | L68: =IF(L$1<$F68,$I68*(($F68-L$1)/$F68),0) -> 2239.9036 | M68: =IF(M$1<$F68,$I68*(($F68-M$1)/$F68),0) -> 2220.7591 | N68: =IF(N$1<$F68,$I68*(($F68-N$1)/$F68),0) -> 2201.6146 | O68: =IF(O$1<$F68,$I68*(($F68-O$1)/$F68),0) -> 2182.4702 | P68: =IF(P$1<$F68,$I68*(($F68-P$1)/$F68),0) -> 2163.3257 | Q68: =IF(Q$1<$F68,$I68*(($F68-Q$1)/$F68),0) -> 2144.1812 | ... DY68: =IF(DY$1<$F68,$I68*(($F68-DY$1)/$F68),0) -> 0
C69: Nouvelles productions 2026 | U69: ='Plan Moyen Terme (PMT)'!C23-BAU_Liquidité_Dynamique!U68 -> 255.3967 | V69: =IF(AND(U$1<V$1, V$1<=$F68),$U69*($F68-V$1)/($F68-$U$1),0) -> 253.03192 | W69: =IF(AND(V$1<W$1, W$1<=$F68),$U69*($F68-W$1)/($F68-$U$1),0) -> 250.66713 | X69: =IF(AND(W$1<X$1, X$1<=$F68),$U69*($F68-X$1)/($F68-$U$1),0) -> 248.30235 | Y69: =IF(AND(X$1<Y$1, Y$1<=$F68),$U69*($F68-Y$1)/($F68-$U$1),0) -> 245.93756 | Z69: =IF(AND(Y$1<Z$1, Z$1<=$F68),$U69*($F68-Z$1)/($F68-$U$1),0) -> 243.57278 | AA69: =IF(AND(Z$1<AA$1, AA$1<=$F68),$U69*($F68-AA$1)/($F68-$U$1),0) -> 241.20799 | AB69: =IF(AND(AA$1<AB$1, AB$1<=$F68),$U69*($F68-AB$1)/($F68-$U$1),0) -> 238.84321 | AC69: =IF(AND(AB$1<AC$1, AC$1<=$F68),$U69*($F68-AC$1)/($F68-$U$1),0) -> 236.47843 | ... DY69: =IF(AND(DX$1<DY$1, DY$1<=$F68),$U69*($F68-DY$1)/($F68-$U$1),0) -> 0
C70: Nouvelles productions 2027 | AG70: ='Plan Moyen Terme (PMT)'!D23-BAU_Liquidité_Dynamique!AG68 -> 1902.1304 | AH70: =IF(AND(AG$1<AH$1, AH$1<=$F68),$AG70*($F68-AH$1)/($F68-$AG$1),0) -> 1882.3165 | AI70: =IF(AND(AH$1<AI$1, AI$1<=$F68),$AG70*($F68-AI$1)/($F68-$AG$1),0) -> 1862.5027 | AJ70: =IF(AND(AI$1<AJ$1, AJ$1<=$F68),$AG70*($F68-AJ$1)/($F68-$AG$1),0) -> 1842.6888 | AK70: =IF(AND(AJ$1<AK$1, AK$1<=$F68),$AG70*($F68-AK$1)/($F68-$AG$1),0) -> 1822.875 | AL70: =IF(AND(AK$1<AL$1, AL$1<=$F68),$AG70*($F68-AL$1)/($F68-$AG$1),0) -> 1803.0611 | AM70: =IF(AND(AL$1<AM$1, AM$1<=$F68),$AG70*($F68-AM$1)/($F68-$AG$1),0) -> 1783.2473 | AN70: =IF(AND(AM$1<AN$1, AN$1<=$F68),$AG70*($F68-AN$1)/($F68-$AG$1),0) -> 1763.4334 | AO70: =IF(AND(AN$1<AO$1, AO$1<=$F68),$AG70*($F68-AO$1)/($F68-$AG$1),0) -> 1743.6195 | ... DY70: =IF(AND(DX$1<DY$1, DY$1<=$F68),$AG70*($F68-DY$1)/($F68-$AG$1),0) -> 0
C71: Nouvelles productions 2028 | AS71: ='Plan Moyen Terme (PMT)'!E23-BAU_Liquidité_Dynamique!AS68 -> 1277.8641 | AT71: =IF(AND(AS$1<AT$1, AT$1<=$F68),$AS71*($F68-AT$1)/($F68-$AS$1),0) -> 1262.6514 | AU71: =IF(AND(AT$1<AU$1, AU$1<=$F68),$AS71*($F68-AU$1)/($F68-$AS$1),0) -> 1247.4388 | AV71: =IF(AND(AU$1<AV$1, AV$1<=$F68),$AS71*($F68-AV$1)/($F68-$AS$1),0) -> 1232.2261 | AW71: =IF(AND(AV$1<AW$1, AW$1<=$F68),$AS71*($F68-AW$1)/($F68-$AS$1),0) -> 1217.0134 | AX71: =IF(AND(AW$1<AX$1, AX$1<=$F68),$AS71*($F68-AX$1)/($F68-$AS$1),0) -> 1201.8008 | AY71: =IF(AND(AX$1<AY$1, AY$1<=$F68),$AS71*($F68-AY$1)/($F68-$AS$1),0) -> 1186.5881 | AZ71: =IF(AND(AY$1<AZ$1, AZ$1<=$F68),$AS71*($F68-AZ$1)/($F68-$AS$1),0) -> 1171.3754 | BA71: =IF(AND(AZ$1<BA$1, BA$1<=$F68),$AS71*($F68-BA$1)/($F68-$AS$1),0) -> 1156.1628 | ... DY71: =IF(AND(DX$1<DY$1, DY$1<=$F68),$AS71*($F68-DY$1)/($F68-$AS$1),0) -> 0
A72: 46022 | B72: PASSIF | C72: Provisions pour risques et charges | D72: 0 | E72: Linéaire | F72: 120 | G72: Linéaire | H72: 120 | I72: 2994.787 | J72: =IF(J$1<$F72,$I72*(($F72-J$1)/$F72),0) -> 2969.8304 | K72: =IF(K$1<$F72,$I72*(($F72-K$1)/$F72),0) -> 2944.8739 | L72: =IF(L$1<$F72,$I72*(($F72-L$1)/$F72),0) -> 2919.9173 | M72: =IF(M$1<$F72,$I72*(($F72-M$1)/$F72),0) -> 2894.9608 | N72: =IF(N$1<$F72,$I72*(($F72-N$1)/$F72),0) -> 2870.0042 | O72: =IF(O$1<$F72,$I72*(($F72-O$1)/$F72),0) -> 2845.0476 | P72: =IF(P$1<$F72,$I72*(($F72-P$1)/$F72),0) -> 2820.0911 | Q72: =IF(Q$1<$F72,$I72*(($F72-Q$1)/$F72),0) -> 2795.1345 | ... DY72: =IF(DY$1<$F72,$I72*(($F72-DY$1)/$F72),0) -> 0
C73: Nouvelles productions 2026 | U73: ='Plan Moyen Terme (PMT)'!C24-BAU_Liquidité_Dynamique!U72 -> 252.6917 | V73: =IF(AND(U$1<V$1, V$1<=$F72),$U73*($F72-V$1)/($F72-$U$1),0) -> 250.35196 | W73: =IF(AND(V$1<W$1, W$1<=$F72),$U73*($F72-W$1)/($F72-$U$1),0) -> 248.01222 | X73: =IF(AND(W$1<X$1, X$1<=$F72),$U73*($F72-X$1)/($F72-$U$1),0) -> 245.67249 | Y73: =IF(AND(X$1<Y$1, Y$1<=$F72),$U73*($F72-Y$1)/($F72-$U$1),0) -> 243.33275 | Z73: =IF(AND(Y$1<Z$1, Z$1<=$F72),$U73*($F72-Z$1)/($F72-$U$1),0) -> 240.99301 | AA73: =IF(AND(Z$1<AA$1, AA$1<=$F72),$U73*($F72-AA$1)/($F72-$U$1),0) -> 238.65327 | AB73: =IF(AND(AA$1<AB$1, AB$1<=$F72),$U73*($F72-AB$1)/($F72-$U$1),0) -> 236.31353 | AC73: =IF(AND(AB$1<AC$1, AC$1<=$F72),$U73*($F72-AC$1)/($F72-$U$1),0) -> 233.9738 | ... DY73: =IF(AND(DX$1<DY$1, DY$1<=$F72),$U73*($F72-DY$1)/($F72-$U$1),0) -> 0
C74: Nouvelles productions 2027 | AG74: ='Plan Moyen Terme (PMT)'!D24-BAU_Liquidité_Dynamique!AG72 -> -795.8296 | AH74: =IF(AND(AG$1<AH$1, AH$1<=$F72),$AG74*($F72-AH$1)/($F72-$AG$1),0) -> -787.53971 | AI74: =IF(AND(AH$1<AI$1, AI$1<=$F72),$AG74*($F72-AI$1)/($F72-$AG$1),0) -> -779.24982 | AJ74: =IF(AND(AI$1<AJ$1, AJ$1<=$F72),$AG74*($F72-AJ$1)/($F72-$AG$1),0) -> -770.95992 | AK74: =IF(AND(AJ$1<AK$1, AK$1<=$F72),$AG74*($F72-AK$1)/($F72-$AG$1),0) -> -762.67003 | AL74: =IF(AND(AK$1<AL$1, AL$1<=$F72),$AG74*($F72-AL$1)/($F72-$AG$1),0) -> -754.38014 | AM74: =IF(AND(AL$1<AM$1, AM$1<=$F72),$AG74*($F72-AM$1)/($F72-$AG$1),0) -> -746.09025 | AN74: =IF(AND(AM$1<AN$1, AN$1<=$F72),$AG74*($F72-AN$1)/($F72-$AG$1),0) -> -737.80036 | AO74: =IF(AND(AN$1<AO$1, AO$1<=$F72),$AG74*($F72-AO$1)/($F72-$AG$1),0) -> -729.51047 | ... DY74: =IF(AND(DX$1<DY$1, DY$1<=$F72),$AG74*($F72-DY$1)/($F72-$AG$1),0) -> 0
C75: Nouvelles productions 2028 | AS75: ='Plan Moyen Terme (PMT)'!E24-BAU_Liquidité_Dynamique!AS72 -> 38.6491 | AT75: =IF(AND(AS$1<AT$1, AT$1<=$F72),$AS75*($F72-AT$1)/($F72-$AS$1),0) -> 38.188992 | AU75: =IF(AND(AT$1<AU$1, AU$1<=$F72),$AS75*($F72-AU$1)/($F72-$AS$1),0) -> 37.728883 | AV75: =IF(AND(AU$1<AV$1, AV$1<=$F72),$AS75*($F72-AV$1)/($F72-$AS$1),0) -> 37.268775 | AW75: =IF(AND(AV$1<AW$1, AW$1<=$F72),$AS75*($F72-AW$1)/($F72-$AS$1),0) -> 36.808667 | AX75: =IF(AND(AW$1<AX$1, AX$1<=$F72),$AS75*($F72-AX$1)/($F72-$AS$1),0) -> 36.348558 | AY75: =IF(AND(AX$1<AY$1, AY$1<=$F72),$AS75*($F72-AY$1)/($F72-$AS$1),0) -> 35.88845 | AZ75: =IF(AND(AY$1<AZ$1, AZ$1<=$F72),$AS75*($F72-AZ$1)/($F72-$AS$1),0) -> 35.428342 | BA75: =IF(AND(AZ$1<BA$1, BA$1<=$F72),$AS75*($F72-BA$1)/($F72-$AS$1),0) -> 34.968233 | ... DY75: =IF(AND(DX$1<DY$1, DY$1<=$F72),$AS75*($F72-DY$1)/($F72-$AS$1),0) -> 0
A76: 46022 | B76: PASSIF | C76: Financement LT | D76: 0.035 | E76: In fine | F76: 72 | G76: In fine | H76: 72 | I76: 130 | J76: =IF(J$1<$F76,$I76,0) -> 130 | K76: =IF(K$1<$F76,$I76,0) -> 130 | L76: =IF(L$1<$F76,$I76,0) -> 130 | M76: =IF(M$1<$F76,$I76,0) -> 130 | N76: =IF(N$1<$F76,$I76,0) -> 130 | O76: =IF(O$1<$F76,$I76,0) -> 130 | P76: =IF(P$1<$F76,$I76,0) -> 130 | Q76: =IF(Q$1<$F76,$I76,0) -> 130 | ... DY76: =IF(DY$1<$F76,$I76,0) -> 0
C77: Nouvelles productions 2026 | U77: ='Plan Moyen Terme (PMT)'!C25-BAU_Liquidité_Dynamique!U76 -> 6344.151 | V77: =IF(AND($U$1<V$1, V$1<$F$76),$U$77,0) -> 6344.151 | W77: =IF(AND($U$1<W$1, W$1<$F$76),$U$77,0) -> 6344.151 | X77: =IF(AND($U$1<X$1, X$1<$F$76),$U$77,0) -> 6344.151 | Y77: =IF(AND($U$1<Y$1, Y$1<$F$76),$U$77,0) -> 6344.151 | Z77: =IF(AND($U$1<Z$1, Z$1<$F$76),$U$77,0) -> 6344.151 | AA77: =IF(AND($U$1<AA$1, AA$1<$F$76),$U$77,0) -> 6344.151 | AB77: =IF(AND($U$1<AB$1, AB$1<$F$76),$U$77,0) -> 6344.151 | AC77: =IF(AND($U$1<AC$1, AC$1<$F$76),$U$77,0) -> 6344.151 | ... CC77: =IF(AND($U$1<CC$1, CC$1<$F$76),$U$77,0) -> 0
C78: Nouvelles productions 2027 | AG78: ='Plan Moyen Terme (PMT)'!D25-BAU_Liquidité_Dynamique!AG76 -> 3444.0033 | AH78: =IF(AND($AG$1<AH$1, AH$1<$F$76),$AG$78,0) -> 3444.0033 | AI78: =IF(AND($AG$1<AI$1, AI$1<$F$76),$AG$78,0) -> 3444.0033 | AJ78: =IF(AND($AG$1<AJ$1, AJ$1<$F$76),$AG$78,0) -> 3444.0033 | AK78: =IF(AND($AG$1<AK$1, AK$1<$F$76),$AG$78,0) -> 3444.0033 | AL78: =IF(AND($AG$1<AL$1, AL$1<$F$76),$AG$78,0) -> 3444.0033 | AM78: =IF(AND($AG$1<AM$1, AM$1<$F$76),$AG$78,0) -> 3444.0033 | AN78: =IF(AND($AG$1<AN$1, AN$1<$F$76),$AG$78,0) -> 3444.0033 | AO78: =IF(AND($AG$1<AO$1, AO$1<$F$76),$AG$78,0) -> 3444.0033 | ... CC78: =IF(AND($AG$1<CC$1, CC$1<$F$76),$AG$78,0) -> 0
C79: Nouvelles productions 2028 | AS79: ='Plan Moyen Terme (PMT)'!E25-BAU_Liquidité_Dynamique!AS76 -> 116.55586 | AT79: =IF(AND($AS$1<AT$1, AT$1<$F$76),$AS$79,0) -> 116.55586 | AU79: =IF(AND($AS$1<AU$1, AU$1<$F$76),$AS$79,0) -> 116.55586 | AV79: =IF(AND($AS$1<AV$1, AV$1<$F$76),$AS$79,0) -> 116.55586 | AW79: =IF(AND($AS$1<AW$1, AW$1<$F$76),$AS$79,0) -> 116.55586 | AX79: =IF(AND($AS$1<AX$1, AX$1<$F$76),$AS$79,0) -> 116.55586 | AY79: =IF(AND($AS$1<AY$1, AY$1<$F$76),$AS$79,0) -> 116.55586 | AZ79: =IF(AND($AS$1<AZ$1, AZ$1<$F$76),$AS$79,0) -> 116.55586 | BA79: =IF(AND($AS$1<BA$1, BA$1<$F$76),$AS$79,0) -> 116.55586 | ... CC79: =IF(AND($AS$1<CC$1, CC$1<$F$76),$AS$79,0) -> 0
A80: 46022 | B80: PASSIF | C80: Capitaux propres | I80: =I81+I85+I89+I93+I97 -> 25913.849 | J80: =SUM(J81:J105) -> 25697.9 | K80: =SUM(K81:K105) -> 25481.952 | L80: =SUM(L81:L105) -> 25266.003 | M80: =SUM(M81:M105) -> 25050.054 | N80: =SUM(N81:N105) -> 24834.105 | O80: =SUM(O81:O105) -> 24618.157 | P80: =SUM(P81:P105) -> 24402.208 | Q80: =SUM(Q81:Q105) -> 24186.259 | ... DY80: =SUM(DY81:DY105) -> 0
A81: 46022 | B81: PASSIF | C81: FRBG | D81: 0 | E81: Linéaire | F81: 120 | G81: Linéaire | H81: 120 | I81: 476.541 | J81: =IF(J$1<$F81,$I81*(($F81-J$1)/$F81),0) -> 472.56983 | K81: =IF(K$1<$F81,$I81*(($F81-K$1)/$F81),0) -> 468.59865 | L81: =IF(L$1<$F81,$I81*(($F81-L$1)/$F81),0) -> 464.62748 | M81: =IF(M$1<$F81,$I81*(($F81-M$1)/$F81),0) -> 460.6563 | N81: =IF(N$1<$F81,$I81*(($F81-N$1)/$F81),0) -> 456.68513 | O81: =IF(O$1<$F81,$I81*(($F81-O$1)/$F81),0) -> 452.71395 | P81: =IF(P$1<$F81,$I81*(($F81-P$1)/$F81),0) -> 448.74277 | Q81: =IF(Q$1<$F81,$I81*(($F81-Q$1)/$F81),0) -> 444.7716 | ... DY81: =IF(DY$1<$F81,$I81*(($F81-DY$1)/$F81),0) -> 0
C82: Nouvelles productions 2026 | U82: ='Plan Moyen Terme (PMT)'!C27-BAU_Liquidité_Dynamique!U81 -> 47.6541 | V82: =IF(AND(U$1<V$1, V$1<=$F81),$U82*($F81-V$1)/($F81-$U$1),0) -> 47.212858 | W82: =IF(AND(V$1<W$1, W$1<=$F81),$U82*($F81-W$1)/($F81-$U$1),0) -> 46.771617 | X82: =IF(AND(W$1<X$1, X$1<=$F81),$U82*($F81-X$1)/($F81-$U$1),0) -> 46.330375 | Y82: =IF(AND(X$1<Y$1, Y$1<=$F81),$U82*($F81-Y$1)/($F81-$U$1),0) -> 45.889133 | Z82: =IF(AND(Y$1<Z$1, Z$1<=$F81),$U82*($F81-Z$1)/($F81-$U$1),0) -> 45.447892 | AA82: =IF(AND(Z$1<AA$1, AA$1<=$F81),$U82*($F81-AA$1)/($F81-$U$1),0) -> 45.00665 | AB82: =IF(AND(AA$1<AB$1, AB$1<=$F81),$U82*($F81-AB$1)/($F81-$U$1),0) -> 44.565408 | AC82: =IF(AND(AB$1<AC$1, AC$1<=$F81),$U82*($F81-AC$1)/($F81-$U$1),0) -> 44.124167 | ... DY82: =IF(AND(DX$1<DY$1, DY$1<=$F81),$U82*($F81-DY$1)/($F81-$U$1),0) -> 0
C83: Nouvelles productions 2027 | AG83: ='Plan Moyen Terme (PMT)'!D27-BAU_Liquidité_Dynamique!AG81 -> 95.3082 | AH83: =IF(AND(AG$1<AH$1, AH$1<=$F81),$AG83*($F81-AH$1)/($F81-$AG$1),0) -> 94.315406 | AI83: =IF(AND(AH$1<AI$1, AI$1<=$F81),$AG83*($F81-AI$1)/($F81-$AG$1),0) -> 93.322612 | AJ83: =IF(AND(AI$1<AJ$1, AJ$1<=$F81),$AG83*($F81-AJ$1)/($F81-$AG$1),0) -> 92.329819 | AK83: =IF(AND(AJ$1<AK$1, AK$1<=$F81),$AG83*($F81-AK$1)/($F81-$AG$1),0) -> 91.337025 | AL83: =IF(AND(AK$1<AL$1, AL$1<=$F81),$AG83*($F81-AL$1)/($F81-$AG$1),0) -> 90.344231 | AM83: =IF(AND(AL$1<AM$1, AM$1<=$F81),$AG83*($F81-AM$1)/($F81-$AG$1),0) -> 89.351437 | AN83: =IF(AND(AM$1<AN$1, AN$1<=$F81),$AG83*($F81-AN$1)/($F81-$AG$1),0) -> 88.358644 | AO83: =IF(AND(AN$1<AO$1, AO$1<=$F81),$AG83*($F81-AO$1)/($F81-$AG$1),0) -> 87.36585 | ... DY83: =IF(AND(DX$1<DY$1, DY$1<=$F81),$AG83*($F81-DY$1)/($F81-$AG$1),0) -> 0
C84: Nouvelles productions 2028 | AS84: ='Plan Moyen Terme (PMT)'!E27-BAU_Liquidité_Dynamique!AS81 -> 142.9623 | AT84: =IF(AND(AS$1<AT$1, AT$1<=$F81),$AS84*($F81-AT$1)/($F81-$AS$1),0) -> 141.26037 | AU84: =IF(AND(AT$1<AU$1, AU$1<=$F81),$AS84*($F81-AU$1)/($F81-$AS$1),0) -> 139.55844 | AV84: =IF(AND(AU$1<AV$1, AV$1<=$F81),$AS84*($F81-AV$1)/($F81-$AS$1),0) -> 137.8565 | AW84: =IF(AND(AV$1<AW$1, AW$1<=$F81),$AS84*($F81-AW$1)/($F81-$AS$1),0) -> 136.15457 | AX84: =IF(AND(AW$1<AX$1, AX$1<=$F81),$AS84*($F81-AX$1)/($F81-$AS$1),0) -> 134.45264 | AY84: =IF(AND(AX$1<AY$1, AY$1<=$F81),$AS84*($F81-AY$1)/($F81-$AS$1),0) -> 132.75071 | AZ84: =IF(AND(AY$1<AZ$1, AZ$1<=$F81),$AS84*($F81-AZ$1)/($F81-$AS$1),0) -> 131.04878 | BA84: =IF(AND(AZ$1<BA$1, BA$1<=$F81),$AS84*($F81-BA$1)/($F81-$AS$1),0) -> 129.34684 | ... DY84: =IF(AND(DX$1<DY$1, DY$1<=$F81),$AS84*($F81-DY$1)/($F81-$AS$1),0) -> 0
A85: 46022 | B85: PASSIF | C85: Capital souscrit | D85: 0 | E85: Linéaire | F85: 120 | G85: Linéaire | H85: 120 | I85: 18000.179 | J85: =IF(J$1<$F85,$I85*(($F85-J$1)/$F85),0) -> 17850.178 | K85: =IF(K$1<$F85,$I85*(($F85-K$1)/$F85),0) -> 17700.176 | L85: =IF(L$1<$F85,$I85*(($F85-L$1)/$F85),0) -> 17550.175 | M85: =IF(M$1<$F85,$I85*(($F85-M$1)/$F85),0) -> 17400.173 | N85: =IF(N$1<$F85,$I85*(($F85-N$1)/$F85),0) -> 17250.172 | O85: =IF(O$1<$F85,$I85*(($F85-O$1)/$F85),0) -> 17100.17 | P85: =IF(P$1<$F85,$I85*(($F85-P$1)/$F85),0) -> 16950.169 | Q85: =IF(Q$1<$F85,$I85*(($F85-Q$1)/$F85),0) -> 16800.167 | ... DY85: =IF(DY$1<$F85,$I85*(($F85-DY$1)/$F85),0) -> 0
C86: Nouvelles productions 2026 | U86: ='Plan Moyen Terme (PMT)'!C28-BAU_Liquidité_Dynamique!U85 -> 1800.0179 | V86: =IF(AND(U$1<V$1, V$1<=$F85),$U86*($F85-V$1)/($F85-$U$1),0) -> 1783.3511 | W86: =IF(AND(V$1<W$1, W$1<=$F85),$U86*($F85-W$1)/($F85-$U$1),0) -> 1766.6842 | X86: =IF(AND(W$1<X$1, X$1<=$F85),$U86*($F85-X$1)/($F85-$U$1),0) -> 1750.0174 | Y86: =IF(AND(X$1<Y$1, Y$1<=$F85),$U86*($F85-Y$1)/($F85-$U$1),0) -> 1733.3506 | Z86: =IF(AND(Y$1<Z$1, Z$1<=$F85),$U86*($F85-Z$1)/($F85-$U$1),0) -> 1716.6837 | AA86: =IF(AND(Z$1<AA$1, AA$1<=$F85),$U86*($F85-AA$1)/($F85-$U$1),0) -> 1700.0169 | AB86: =IF(AND(AA$1<AB$1, AB$1<=$F85),$U86*($F85-AB$1)/($F85-$U$1),0) -> 1683.3501 | AC86: =IF(AND(AB$1<AC$1, AC$1<=$F85),$U86*($F85-AC$1)/($F85-$U$1),0) -> 1666.6832 | ... DY86: =IF(AND(DX$1<DY$1, DY$1<=$F85),$U86*($F85-DY$1)/($F85-$U$1),0) -> 0
C87: Nouvelles productions 2027 | AG87: ='Plan Moyen Terme (PMT)'!D28-BAU_Liquidité_Dynamique!AG85 -> 3600.0358 | AH87: =IF(AND(AG$1<AH$1, AH$1<=$F85),$AG87*($F85-AH$1)/($F85-$AG$1),0) -> 3562.5354 | AI87: =IF(AND(AH$1<AI$1, AI$1<=$F85),$AG87*($F85-AI$1)/($F85-$AG$1),0) -> 3525.0351 | AJ87: =IF(AND(AI$1<AJ$1, AJ$1<=$F85),$AG87*($F85-AJ$1)/($F85-$AG$1),0) -> 3487.5347 | AK87: =IF(AND(AJ$1<AK$1, AK$1<=$F85),$AG87*($F85-AK$1)/($F85-$AG$1),0) -> 3450.0343 | AL87: =IF(AND(AK$1<AL$1, AL$1<=$F85),$AG87*($F85-AL$1)/($F85-$AG$1),0) -> 3412.5339 | AM87: =IF(AND(AL$1<AM$1, AM$1<=$F85),$AG87*($F85-AM$1)/($F85-$AG$1),0) -> 3375.0336 | AN87: =IF(AND(AM$1<AN$1, AN$1<=$F85),$AG87*($F85-AN$1)/($F85-$AG$1),0) -> 3337.5332 | AO87: =IF(AND(AN$1<AO$1, AO$1<=$F85),$AG87*($F85-AO$1)/($F85-$AG$1),0) -> 3300.0328 | ... DY87: =IF(AND(DX$1<DY$1, DY$1<=$F85),$AG87*($F85-DY$1)/($F85-$AG$1),0) -> 0
C88: Nouvelles productions 2028 | AS88: ='Plan Moyen Terme (PMT)'!E28-BAU_Liquidité_Dynamique!AS85 -> 37857.875 | AT88: =IF(AND(AS$1<AT$1, AT$1<=$F85),$AS88*($F85-AT$1)/($F85-$AS$1),0) -> 37407.186 | AU88: =IF(AND(AT$1<AU$1, AU$1<=$F85),$AS88*($F85-AU$1)/($F85-$AS$1),0) -> 36956.497 | AV88: =IF(AND(AU$1<AV$1, AV$1<=$F85),$AS88*($F85-AV$1)/($F85-$AS$1),0) -> 36505.808 | AW88: =IF(AND(AV$1<AW$1, AW$1<=$F85),$AS88*($F85-AW$1)/($F85-$AS$1),0) -> 36055.119 | AX88: =IF(AND(AW$1<AX$1, AX$1<=$F85),$AS88*($F85-AX$1)/($F85-$AS$1),0) -> 35604.43 | AY88: =IF(AND(AX$1<AY$1, AY$1<=$F85),$AS88*($F85-AY$1)/($F85-$AS$1),0) -> 35153.741 | AZ88: =IF(AND(AY$1<AZ$1, AZ$1<=$F85),$AS88*($F85-AZ$1)/($F85-$AS$1),0) -> 34703.052 | BA88: =IF(AND(AZ$1<BA$1, BA$1<=$F85),$AS88*($F85-BA$1)/($F85-$AS$1),0) -> 34252.363 | ... DY88: =IF(AND(DX$1<DY$1, DY$1<=$F85),$AS88*($F85-DY$1)/($F85-$AS$1),0) -> 0
A89: 46022 | B89: PASSIF | C89: Prime d'émission | D89: 0 | E89: Linéaire | F89: 120 | G89: Linéaire | H89: 120 | I89: 2.22 | J89: =IF(J$1<$F89,$I89*(($F89-J$1)/$F89),0) -> 2.2015 | K89: =IF(K$1<$F89,$I89*(($F89-K$1)/$F89),0) -> 2.183 | L89: =IF(L$1<$F89,$I89*(($F89-L$1)/$F89),0) -> 2.1645 | M89: =IF(M$1<$F89,$I89*(($F89-M$1)/$F89),0) -> 2.146 | N89: =IF(N$1<$F89,$I89*(($F89-N$1)/$F89),0) -> 2.1275 | O89: =IF(O$1<$F89,$I89*(($F89-O$1)/$F89),0) -> 2.109 | P89: =IF(P$1<$F89,$I89*(($F89-P$1)/$F89),0) -> 2.0905 | Q89: =IF(Q$1<$F89,$I89*(($F89-Q$1)/$F89),0) -> 2.072 | ... DY89: =IF(DY$1<$F89,$I89*(($F89-DY$1)/$F89),0) -> 0
C90: Nouvelles productions 2026 | U90: ='Plan Moyen Terme (PMT)'!C29-BAU_Liquidité_Dynamique!U89 -> 0.222 | V90: =IF(AND(U$1<V$1, V$1<=$F89),$U90*($F89-V$1)/($F89-$U$1),0) -> 0.21994444 | W90: =IF(AND(V$1<W$1, W$1<=$F89),$U90*($F89-W$1)/($F89-$U$1),0) -> 0.21788889 | X90: =IF(AND(W$1<X$1, X$1<=$F89),$U90*($F89-X$1)/($F89-$U$1),0) -> 0.21583333 | Y90: =IF(AND(X$1<Y$1, Y$1<=$F89),$U90*($F89-Y$1)/($F89-$U$1),0) -> 0.21377778 | Z90: =IF(AND(Y$1<Z$1, Z$1<=$F89),$U90*($F89-Z$1)/($F89-$U$1),0) -> 0.21172222 | AA90: =IF(AND(Z$1<AA$1, AA$1<=$F89),$U90*($F89-AA$1)/($F89-$U$1),0) -> 0.20966667 | AB90: =IF(AND(AA$1<AB$1, AB$1<=$F89),$U90*($F89-AB$1)/($F89-$U$1),0) -> 0.20761111 | AC90: =IF(AND(AB$1<AC$1, AC$1<=$F89),$U90*($F89-AC$1)/($F89-$U$1),0) -> 0.20555556 | ... DY90: =IF(AND(DX$1<DY$1, DY$1<=$F89),$U90*($F89-DY$1)/($F89-$U$1),0) -> 0
C91: Nouvelles productions 2027 | AG91: ='Plan Moyen Terme (PMT)'!D29-BAU_Liquidité_Dynamique!AG89 -> 0.444 | AH91: =IF(AND(AG$1<AH$1, AH$1<=$F89),$AG91*($F89-AH$1)/($F89-$AG$1),0) -> 0.439375 | AI91: =IF(AND(AH$1<AI$1, AI$1<=$F89),$AG91*($F89-AI$1)/($F89-$AG$1),0) -> 0.43475 | AJ91: =IF(AND(AI$1<AJ$1, AJ$1<=$F89),$AG91*($F89-AJ$1)/($F89-$AG$1),0) -> 0.430125 | AK91: =IF(AND(AJ$1<AK$1, AK$1<=$F89),$AG91*($F89-AK$1)/($F89-$AG$1),0) -> 0.4255 | AL91: =IF(AND(AK$1<AL$1, AL$1<=$F89),$AG91*($F89-AL$1)/($F89-$AG$1),0) -> 0.420875 | AM91: =IF(AND(AL$1<AM$1, AM$1<=$F89),$AG91*($F89-AM$1)/($F89-$AG$1),0) -> 0.41625 | AN91: =IF(AND(AM$1<AN$1, AN$1<=$F89),$AG91*($F89-AN$1)/($F89-$AG$1),0) -> 0.411625 | AO91: =IF(AND(AN$1<AO$1, AO$1<=$F89),$AG91*($F89-AO$1)/($F89-$AG$1),0) -> 0.407 | ... DY91: =IF(AND(DX$1<DY$1, DY$1<=$F89),$AG91*($F89-DY$1)/($F89-$AG$1),0) -> 0
C92: Nouvelles productions 2028 | AS92: ='Plan Moyen Terme (PMT)'!E29-BAU_Liquidité_Dynamique!AS89 -> 2752.446 | AT92: =IF(AND(AS$1<AT$1, AT$1<=$F89),$AS92*($F89-AT$1)/($F89-$AS$1),0) -> 2719.6788 | AU92: =IF(AND(AT$1<AU$1, AU$1<=$F89),$AS92*($F89-AU$1)/($F89-$AS$1),0) -> 2686.9116 | AV92: =IF(AND(AU$1<AV$1, AV$1<=$F89),$AS92*($F89-AV$1)/($F89-$AS$1),0) -> 2654.1444 | AW92: =IF(AND(AV$1<AW$1, AW$1<=$F89),$AS92*($F89-AW$1)/($F89-$AS$1),0) -> 2621.3771 | AX92: =IF(AND(AW$1<AX$1, AX$1<=$F89),$AS92*($F89-AX$1)/($F89-$AS$1),0) -> 2588.6099 | AY92: =IF(AND(AX$1<AY$1, AY$1<=$F89),$AS92*($F89-AY$1)/($F89-$AS$1),0) -> 2555.8427 | AZ92: =IF(AND(AY$1<AZ$1, AZ$1<=$F89),$AS92*($F89-AZ$1)/($F89-$AS$1),0) -> 2523.0755 | BA92: =IF(AND(AZ$1<BA$1, BA$1<=$F89),$AS92*($F89-BA$1)/($F89-$AS$1),0) -> 2490.3083 | ... DY92: =IF(AND(DX$1<DY$1, DY$1<=$F89),$AS92*($F89-DY$1)/($F89-$AS$1),0) -> 0
A93: 46022 | B93: PASSIF | C93: Réserves | D93: 0 | E93: Linéaire | F93: 120 | G93: Linéaire | H93: 120 | I93: 429.975 | J93: =IF(J$1<$F93,$I93*(($F93-J$1)/$F93),0) -> 426.39188 | K93: =IF(K$1<$F93,$I93*(($F93-K$1)/$F93),0) -> 422.80875 | L93: =IF(L$1<$F93,$I93*(($F93-L$1)/$F93),0) -> 419.22563 | M93: =IF(M$1<$F93,$I93*(($F93-M$1)/$F93),0) -> 415.6425 | N93: =IF(N$1<$F93,$I93*(($F93-N$1)/$F93),0) -> 412.05938 | O93: =IF(O$1<$F93,$I93*(($F93-O$1)/$F93),0) -> 408.47625 | P93: =IF(P$1<$F93,$I93*(($F93-P$1)/$F93),0) -> 404.89312 | Q93: =IF(Q$1<$F93,$I93*(($F93-Q$1)/$F93),0) -> 401.31 | ... DY93: =IF(DY$1<$F93,$I93*(($F93-DY$1)/$F93),0) -> 0
C94: Nouvelles productions 2026 | U94: ='Plan Moyen Terme (PMT)'!C30-BAU_Liquidité_Dynamique!U93 -> 49.0225 | V94: =IF(AND(U$1<V$1, V$1<=$F93),$U94*($F93-V$1)/($F93-$U$1),0) -> 48.568588 | W94: =IF(AND(V$1<W$1, W$1<=$F93),$U94*($F93-W$1)/($F93-$U$1),0) -> 48.114676 | X94: =IF(AND(W$1<X$1, X$1<=$F93),$U94*($F93-X$1)/($F93-$U$1),0) -> 47.660764 | Y94: =IF(AND(X$1<Y$1, Y$1<=$F93),$U94*($F93-Y$1)/($F93-$U$1),0) -> 47.206852 | Z94: =IF(AND(Y$1<Z$1, Z$1<=$F93),$U94*($F93-Z$1)/($F93-$U$1),0) -> 46.75294 | AA94: =IF(AND(Z$1<AA$1, AA$1<=$F93),$U94*($F93-AA$1)/($F93-$U$1),0) -> 46.299028 | AB94: =IF(AND(AA$1<AB$1, AB$1<=$F93),$U94*($F93-AB$1)/($F93-$U$1),0) -> 45.845116 | AC94: =IF(AND(AB$1<AC$1, AC$1<=$F93),$U94*($F93-AC$1)/($F93-$U$1),0) -> 45.391204 | ... DY94: =IF(AND(DX$1<DY$1, DY$1<=$F93),$U94*($F93-DY$1)/($F93-$U$1),0) -> 0
C95: Nouvelles productions 2027 | AG95: ='Plan Moyen Terme (PMT)'!D30-BAU_Liquidité_Dynamique!AG93 -> 113.02 | AH95: =IF(AND(AG$1<AH$1, AH$1<=$F93),$AG95*($F93-AH$1)/($F93-$AG$1),0) -> 111.84271 | AI95: =IF(AND(AH$1<AI$1, AI$1<=$F93),$AG95*($F93-AI$1)/($F93-$AG$1),0) -> 110.66542 | AJ95: =IF(AND(AI$1<AJ$1, AJ$1<=$F93),$AG95*($F93-AJ$1)/($F93-$AG$1),0) -> 109.48812 | AK95: =IF(AND(AJ$1<AK$1, AK$1<=$F93),$AG95*($F93-AK$1)/($F93-$AG$1),0) -> 108.31083 | AL95: =IF(AND(AK$1<AL$1, AL$1<=$F93),$AG95*($F93-AL$1)/($F93-$AG$1),0) -> 107.13354 | AM95: =IF(AND(AL$1<AM$1, AM$1<=$F93),$AG95*($F93-AM$1)/($F93-$AG$1),0) -> 105.95625 | AN95: =IF(AND(AM$1<AN$1, AN$1<=$F93),$AG95*($F93-AN$1)/($F93-$AG$1),0) -> 104.77896 | AO95: =IF(AND(AN$1<AO$1, AO$1<=$F93),$AG95*($F93-AO$1)/($F93-$AG$1),0) -> 103.60167 | ... DY95: =IF(AND(DX$1<DY$1, DY$1<=$F93),$AG95*($F93-DY$1)/($F93-$AG$1),0) -> 0
C96: Nouvelles productions 2028 | AS96: ='Plan Moyen Terme (PMT)'!E30-BAU_Liquidité_Dynamique!AS93 -> 256.0175 | AT96: =IF(AND(AS$1<AT$1, AT$1<=$F93),$AS96*($F93-AT$1)/($F93-$AS$1),0) -> 252.96967 | AU96: =IF(AND(AT$1<AU$1, AU$1<=$F93),$AS96*($F93-AU$1)/($F93-$AS$1),0) -> 249.92185 | AV96: =IF(AND(AU$1<AV$1, AV$1<=$F93),$AS96*($F93-AV$1)/($F93-$AS$1),0) -> 246.87402 | AW96: =IF(AND(AV$1<AW$1, AW$1<=$F93),$AS96*($F93-AW$1)/($F93-$AS$1),0) -> 243.82619 | AX96: =IF(AND(AW$1<AX$1, AX$1<=$F93),$AS96*($F93-AX$1)/($F93-$AS$1),0) -> 240.77836 | AY96: =IF(AND(AX$1<AY$1, AY$1<=$F93),$AS96*($F93-AY$1)/($F93-$AS$1),0) -> 237.73054 | AZ96: =IF(AND(AY$1<AZ$1, AZ$1<=$F93),$AS96*($F93-AZ$1)/($F93-$AS$1),0) -> 234.68271 | BA96: =IF(AND(AZ$1<BA$1, BA$1<=$F93),$AS96*($F93-BA$1)/($F93-$AS$1),0) -> 231.63488 | ... DY96: =IF(AND(DX$1<DY$1, DY$1<=$F93),$AS96*($F93-DY$1)/($F93-$AS$1),0) -> 0
A97: 46022 | B97: PASSIF | C97: Report à nouveau | D97: 0 | E97: Linéaire | F97: 120 | G97: Linéaire | H97: 120 | I97: 7004.934 | J97: =IF(J$1<$F97,$I97*(($F97-J$1)/$F97),0) -> 6946.5596 | K97: =IF(K$1<$F97,$I97*(($F97-K$1)/$F97),0) -> 6888.1851 | L97: =IF(L$1<$F97,$I97*(($F97-L$1)/$F97),0) -> 6829.8107 | M97: =IF(M$1<$F97,$I97*(($F97-M$1)/$F97),0) -> 6771.4362 | N97: =IF(N$1<$F97,$I97*(($F97-N$1)/$F97),0) -> 6713.0618 | O97: =IF(O$1<$F97,$I97*(($F97-O$1)/$F97),0) -> 6654.6873 | P97: =IF(P$1<$F97,$I97*(($F97-P$1)/$F97),0) -> 6596.3129 | Q97: =IF(Q$1<$F97,$I97*(($F97-Q$1)/$F97),0) -> 6537.9384 | ... DY97: =IF(DY$1<$F97,$I97*(($F97-DY$1)/$F97),0) -> 0
C98: Nouvelles productions 2026 | U98: ='Plan Moyen Terme (PMT)'!C31-BAU_Liquidité_Dynamique!U97 -> 695.4684 | V98: =IF(AND(U$1<V$1, V$1<=$F97),$U98*($F97-V$1)/($F97-$U$1),0) -> 689.02888 | W98: =IF(AND(V$1<W$1, W$1<=$F97),$U98*($F97-W$1)/($F97-$U$1),0) -> 682.58936 | X98: =IF(AND(W$1<X$1, X$1<=$F97),$U98*($F97-X$1)/($F97-$U$1),0) -> 676.14983 | Y98: =IF(AND(X$1<Y$1, Y$1<=$F97),$U98*($F97-Y$1)/($F97-$U$1),0) -> 669.71031 | Z98: =IF(AND(Y$1<Z$1, Z$1<=$F97),$U98*($F97-Z$1)/($F97-$U$1),0) -> 663.27079 | AA98: =IF(AND(Z$1<AA$1, AA$1<=$F97),$U98*($F97-AA$1)/($F97-$U$1),0) -> 656.83127 | AB98: =IF(AND(AA$1<AB$1, AB$1<=$F97),$U98*($F97-AB$1)/($F97-$U$1),0) -> 650.39174 | AC98: =IF(AND(AB$1<AC$1, AC$1<=$F97),$U98*($F97-AC$1)/($F97-$U$1),0) -> 643.95222 | ... DY98: =IF(AND(DX$1<DY$1, DY$1<=$F97),$U98*($F97-DY$1)/($F97-$U$1),0) -> 0
C99: Nouvelles productions 2027 | AG99: ='Plan Moyen Terme (PMT)'!D31-BAU_Liquidité_Dynamique!AG97 -> 1374.9618 | AH99: =IF(AND(AG$1<AH$1, AH$1<=$F97),$AG99*($F97-AH$1)/($F97-$AG$1),0) -> 1360.6393 | AI99: =IF(AND(AH$1<AI$1, AI$1<=$F97),$AG99*($F97-AI$1)/($F97-$AG$1),0) -> 1346.3168 | AJ99: =IF(AND(AI$1<AJ$1, AJ$1<=$F97),$AG99*($F97-AJ$1)/($F97-$AG$1),0) -> 1331.9942 | AK99: =IF(AND(AJ$1<AK$1, AK$1<=$F97),$AG99*($F97-AK$1)/($F97-$AG$1),0) -> 1317.6717 | AL99: =IF(AND(AK$1<AL$1, AL$1<=$F97),$AG99*($F97-AL$1)/($F97-$AG$1),0) -> 1303.3492 | AM99: =IF(AND(AL$1<AM$1, AM$1<=$F97),$AG99*($F97-AM$1)/($F97-$AG$1),0) -> 1289.0267 | AN99: =IF(AND(AM$1<AN$1, AN$1<=$F97),$AG99*($F97-AN$1)/($F97-$AG$1),0) -> 1274.7042 | AO99: =IF(AND(AN$1<AO$1, AO$1<=$F97),$AG99*($F97-AO$1)/($F97-$AG$1),0) -> 1260.3817 | ... DY99: =IF(AND(DX$1<DY$1, DY$1<=$F97),$AG99*($F97-DY$1)/($F97-$AG$1),0) -> 0
C100: Nouvelles productions 2028 | AS100: ='Plan Moyen Terme (PMT)'!E31-BAU_Liquidité_Dynamique!AS97 -> -2959.4538 | AT100: =IF(AND(AS$1<AT$1, AT$1<=$F97),$AS100*($F97-AT$1)/($F97-$AS$1),0) -> -2924.2222 | AU100: =IF(AND(AT$1<AU$1, AU$1<=$F97),$AS100*($F97-AU$1)/($F97-$AS$1),0) -> -2888.9906 | AV100: =IF(AND(AU$1<AV$1, AV$1<=$F97),$AS100*($F97-AV$1)/($F97-$AS$1),0) -> -2853.759 | AW100: =IF(AND(AV$1<AW$1, AW$1<=$F97),$AS100*($F97-AW$1)/($F97-$AS$1),0) -> -2818.5274 | AX100: =IF(AND(AW$1<AX$1, AX$1<=$F97),$AS100*($F97-AX$1)/($F97-$AS$1),0) -> -2783.2958 | AY100: =IF(AND(AX$1<AY$1, AY$1<=$F97),$AS100*($F97-AY$1)/($F97-$AS$1),0) -> -2748.0642 | AZ100: =IF(AND(AY$1<AZ$1, AZ$1<=$F97),$AS100*($F97-AZ$1)/($F97-$AS$1),0) -> -2712.8327 | BA100: =IF(AND(AZ$1<BA$1, BA$1<=$F97),$AS100*($F97-BA$1)/($F97-$AS$1),0) -> -2677.6011 | ... DY100: =IF(AND(DX$1<DY$1, DY$1<=$F97),$AS100*($F97-DY$1)/($F97-$AS$1),0) -> 0
...

Sheet stress test de taux
A1: Type de scenarios | B1: Catégories | C1: scenarios | D1: 1 | E1: 2 | F1: 3 | G1: 4 | H1: 5 | I1: 6 | J1: 7 | K1: 8 | L1: 9 | M1: 10 | N1: 11 | O1: 12 | P1: 13 | Q1: 14 | R1: 15 | S1: 16 | T1: 17 | U1: 18 | V1: 19 | W1: 20 | X1: 21 | Y1: 22 | Z1: 23 | AA1: 24 | AB1: 25 | AC1: 26 | AD1: 27 | AE1: 28 | AF1: 29 | AG1: 30 | AH1: 31 | AI1: 32 | AJ1: 33 | AK1: 34 | AL1: 35 | AM1: 36 | AN1: 37 | AO1: 38 | AP1: 39 | AQ1: 40 | AR1: 41 | AS1: 42 | AT1: 43 | AU1: 44 | AV1: 45 | AW1: 46 | AX1: 47 | AY1: 48 | AZ1: 49 | BA1: 50 | BB1: 51 | BC1: 52 | BD1: 53 | BE1: 54 | BF1: 55 | BG1: 56 | BH1: 57 | BI1: 58 | BJ1: 59 | BK1: 60 | BL1: 61 | BM1: 62 | BN1: 63 | BO1: 64 | BP1: 65 | BQ1: 66 | BR1: 67 | BS1: 68 | BT1: 69 | BU1: 70 | BV1: 71 | BW1: 72 | BX1: 73 | BY1: 74 | BZ1: 75 | CA1: 76 | CB1: 77 | CC1: 78 | CD1: 79 | CE1: 80 | CF1: 81 | CG1: 82 | CH1: 83 | CI1: 84 | CJ1: 85 | CK1: 86 | CL1: 87 | CM1: 88 | CN1: 89 | CO1: 90 | CP1: 91 | CQ1: 92 | CR1: 93 | CS1: 94 | CT1: 95 | CU1: 96 | CV1: 97 | CW1: 98 | CX1: 99 | CY1: 100 | CZ1: 101 | DA1: 102 | DB1: 103 | DC1: 104 | DD1: 105 | DE1: 106 | DF1: 107 | DG1: 108 | DH1: 109 | DI1: 110 | DJ1: 111 | DK1: 112 | DL1: 113 | DM1: 114 | DN1: 115 | DO1: 116 | DP1: 117 | DQ1: 118 | DR1: 119 | DS1: 120 | DT1: 121 | DU1: 122 | DV1: 123 | DW1: 124 | DX1: 125 | DY1: 126 | DZ1: 127 | EA1: 128 | EB1: 129 | EC1: 130 | ED1: 131 | EE1: 132 | EF1: 133 | EG1: 134 | EH1: 135 | EI1: 136 | EJ1: 137 | EK1: 138 | EL1: 139 | EM1: 140 | EN1: 141 | EO1: 142 | EP1: 143 | EQ1: 144 | ER1: 145 | ES1: 146 | ET1: 147 | EU1: 148 | EV1: 149 | EW1: 150 | EX1: 151 | EY1: 152 | EZ1: 153 | FA1: 154 | FB1: 155 | FC1: 156 | FD1: 157 | FE1: 158 | FF1: 159 | FG1: 160 | FH1: 161 | FI1: 162 | FJ1: 163 | FK1: 164 | FL1: 165 | FM1: 166 | FN1: 167 | FO1: 168 | FP1: 169 | FQ1: 170 | FR1: 171 | FS1: 172 | FT1: 173 | FU1: 174 | FV1: 175 | FW1: 176 | FX1: 177 | FY1: 178 | FZ1: 179 | GA1: 180 | GB1: 181 | GC1: 182 | GD1: 183 | GE1: 184 | GF1: 185 | GG1: 186 | GH1: 187 | GI1: 188 | GJ1: 189 | GK1: 190 | GL1: 191 | GM1: 192 | GN1: 193 | GO1: 194 | GP1: 195 | GQ1: 196 | GR1: 197 | GS1: 198 | GT1: 199 | GU1: 200 | GV1: 201 | GW1: 202 | GX1: 203 | GY1: 204 | GZ1: 205 | HA1: 206 | HB1: 207 | HC1: 208 | HD1: 209 | HE1: 210 | HF1: 211 | HG1: 212 | HH1: 213 | HI1: 214 | HJ1: 215 | HK1: 216 | HL1: 217 | HM1: 218 | HN1: 219 | HO1: 220 | HP1: 221 | HQ1: 222 | HR1: 223 | HS1: 224 | HT1: 225 | HU1: 226 | HV1: 227 | HW1: 228 | HX1: 229 | HY1: 230 | HZ1: 231 | IA1: 232 | IB1: 233 | IC1: 234 | ID1: 235 | IE1: 236 | IF1: 237 | IG1: 238 | IH1: 239 | II1: 240
A2: Reglementaire _SOT MNI&SOT EVE | B2: Parallel | C2: +200BPS | D2: 0.02 | E2: 0.02 | F2: 0.02 | G2: 0.02 | H2: 0.02 | I2: 0.02 | J2: 0.02 | K2: 0.02 | L2: 0.02 | M2: 0.02 | N2: 0.02 | O2: 0.02 | P2: 0.02 | Q2: 0.02 | R2: 0.02 | S2: 0.02 | T2: 0.02 | U2: 0.02 | V2: 0.02 | W2: 0.02 | X2: 0.02 | Y2: 0.02 | Z2: 0.02 | AA2: 0.02 | AB2: 0.02 | AC2: 0.02 | AD2: 0.02 | AE2: 0.02 | AF2: 0.02 | AG2: 0.02 | AH2: 0.02 | AI2: 0.02 | AJ2: 0.02 | AK2: 0.02 | AL2: 0.02 | AM2: 0.02 | AN2: 0.02 | AO2: 0.02 | AP2: 0.02 | AQ2: 0.02 | AR2: 0.02 | AS2: 0.02 | AT2: 0.02 | AU2: 0.02 | AV2: 0.02 | AW2: 0.02 | AX2: 0.02 | AY2: 0.02 | AZ2: 0.02 | BA2: 0.02 | BB2: 0.02 | BC2: 0.02 | BD2: 0.02 | BE2: 0.02 | BF2: 0.02 | BG2: 0.02 | BH2: 0.02 | BI2: 0.02 | BJ2: 0.02 | BK2: 0.02 | BL2: 0.02 | BM2: 0.02 | BN2: 0.02 | BO2: 0.02 | BP2: 0.02 | BQ2: 0.02 | BR2: 0.02 | BS2: 0.02 | BT2: 0.02 | BU2: 0.02 | BV2: 0.02 | BW2: 0.02 | BX2: 0.02 | BY2: 0.02 | BZ2: 0.02 | CA2: 0.02 | CB2: 0.02 | CC2: 0.02 | CD2: 0.02 | CE2: 0.02 | CF2: 0.02 | CG2: 0.02 | CH2: 0.02 | CI2: 0.02 | CJ2: 0.02 | CK2: 0.02 | CL2: 0.02 | CM2: 0.02 | CN2: 0.02 | CO2: 0.02 | CP2: 0.02 | CQ2: 0.02 | CR2: 0.02 | CS2: 0.02 | CT2: 0.02 | CU2: 0.02 | CV2: 0.02 | CW2: 0.02 | CX2: 0.02 | CY2: 0.02 | CZ2: 0.02 | DA2: 0.02 | DB2: 0.02 | DC2: 0.02 | DD2: 0.02 | DE2: 0.02 | DF2: 0.02 | DG2: 0.02 | DH2: 0.02 | DI2: 0.02 | DJ2: 0.02 | DK2: 0.02 | DL2: 0.02 | DM2: 0.02 | DN2: 0.02 | DO2: 0.02 | DP2: 0.02 | DQ2: 0.02 | DR2: 0.02 | DS2: 0.02 | DT2: 0.02 | DU2: 0.02 | DV2: 0.02 | DW2: 0.02 | DX2: 0.02 | DY2: 0.02 | DZ2: 0.02 | EA2: 0.02 | EB2: 0.02 | EC2: 0.02 | ED2: 0.02 | EE2: 0.02 | EF2: 0.02 | EG2: 0.02 | EH2: 0.02 | EI2: 0.02 | EJ2: 0.02 | EK2: 0.02 | EL2: 0.02 | EM2: 0.02 | EN2: 0.02 | EO2: 0.02 | EP2: 0.02 | EQ2: 0.02 | ER2: 0.02 | ES2: 0.02 | ET2: 0.02 | EU2: 0.02 | EV2: 0.02 | EW2: 0.02 | EX2: 0.02 | EY2: 0.02 | EZ2: 0.02 | FA2: 0.02 | FB2: 0.02 | FC2: 0.02 | FD2: 0.02 | FE2: 0.02 | FF2: 0.02 | FG2: 0.02 | FH2: 0.02 | FI2: 0.02 | FJ2: 0.02 | FK2: 0.02 | FL2: 0.02 | FM2: 0.02 | FN2: 0.02 | FO2: 0.02 | FP2: 0.02 | FQ2: 0.02 | FR2: 0.02 | FS2: 0.02 | FT2: 0.02 | FU2: 0.02 | FV2: 0.02 | FW2: 0.02 | FX2: 0.02 | FY2: 0.02 | FZ2: 0.02 | GA2: 0.02 | GB2: 0.02 | GC2: 0.02 | GD2: 0.02 | GE2: 0.02 | GF2: 0.02 | GG2: 0.02 | GH2: 0.02 | GI2: 0.02 | GJ2: 0.02 | GK2: 0.02 | GL2: 0.02 | GM2: 0.02 | GN2: 0.02 | GO2: 0.02 | GP2: 0.02 | GQ2: 0.02 | GR2: 0.02 | GS2: 0.02 | GT2: 0.02 | GU2: 0.02 | GV2: 0.02 | GW2: 0.02 | GX2: 0.02 | GY2: 0.02 | GZ2: 0.02 | HA2: 0.02 | HB2: 0.02 | HC2: 0.02 | HD2: 0.02 | HE2: 0.02 | HF2: 0.02 | HG2: 0.02 | HH2: 0.02 | HI2: 0.02 | HJ2: 0.02 | HK2: 0.02 | HL2: 0.02 | HM2: 0.02 | HN2: 0.02 | HO2: 0.02 | HP2: 0.02 | HQ2: 0.02 | HR2: 0.02 | HS2: 0.02 | HT2: 0.02 | HU2: 0.02 | HV2: 0.02 | HW2: 0.02 | HX2: 0.02 | HY2: 0.02 | HZ2: 0.02 | IA2: 0.02 | IB2: 0.02 | IC2: 0.02 | ID2: 0.02 | IE2: 0.02 | IF2: 0.02 | IG2: 0.02 | IH2: 0.02 | II2: 0.02
A3: Reglementaire _SOT MNI&SOT EVE | B3: Parallel | C3: -200BPS | D3: -0.02 | E3: -0.02 | F3: -0.02 | G3: -0.02 | H3: -0.02 | I3: -0.02 | J3: -0.02 | K3: -0.02 | L3: -0.02 | M3: -0.02 | N3: -0.02 | O3: -0.02 | P3: -0.02 | Q3: -0.02 | R3: -0.02 | S3: -0.02 | T3: -0.02 | U3: -0.02 | V3: -0.02 | W3: -0.02 | X3: -0.02 | Y3: -0.02 | Z3: -0.02 | AA3: -0.02 | AB3: -0.02 | AC3: -0.02 | AD3: -0.02 | AE3: -0.02 | AF3: -0.02 | AG3: -0.02 | AH3: -0.02 | AI3: -0.02 | AJ3: -0.02 | AK3: -0.02 | AL3: -0.02 | AM3: -0.02 | AN3: -0.02 | AO3: -0.02 | AP3: -0.02 | AQ3: -0.02 | AR3: -0.02 | AS3: -0.02 | AT3: -0.02 | AU3: -0.02 | AV3: -0.02 | AW3: -0.02 | AX3: -0.02 | AY3: -0.02 | AZ3: -0.02 | BA3: -0.02 | BB3: -0.02 | BC3: -0.02 | BD3: -0.02 | BE3: -0.02 | BF3: -0.02 | BG3: -0.02 | BH3: -0.02 | BI3: -0.02 | BJ3: -0.02 | BK3: -0.02 | BL3: -0.02 | BM3: -0.02 | BN3: -0.02 | BO3: -0.02 | BP3: -0.02 | BQ3: -0.02 | BR3: -0.02 | BS3: -0.02 | BT3: -0.02 | BU3: -0.02 | BV3: -0.02 | BW3: -0.02 | BX3: -0.02 | BY3: -0.02 | BZ3: -0.02 | CA3: -0.02 | CB3: -0.02 | CC3: -0.02 | CD3: -0.02 | CE3: -0.02 | CF3: -0.02 | CG3: -0.02 | CH3: -0.02 | CI3: -0.02 | CJ3: -0.02 | CK3: -0.02 | CL3: -0.02 | CM3: -0.02 | CN3: -0.02 | CO3: -0.02 | CP3: -0.02 | CQ3: -0.02 | CR3: -0.02 | CS3: -0.02 | CT3: -0.02 | CU3: -0.02 | CV3: -0.02 | CW3: -0.02 | CX3: -0.02 | CY3: -0.02 | CZ3: -0.02 | DA3: -0.02 | DB3: -0.02 | DC3: -0.02 | DD3: -0.02 | DE3: -0.02 | DF3: -0.02 | DG3: -0.02 | DH3: -0.02 | DI3: -0.02 | DJ3: -0.02 | DK3: -0.02 | DL3: -0.02 | DM3: -0.02 | DN3: -0.02 | DO3: -0.02 | DP3: -0.02 | DQ3: -0.02 | DR3: -0.02 | DS3: -0.02 | DT3: -0.02 | DU3: -0.02 | DV3: -0.02 | DW3: -0.02 | DX3: -0.02 | DY3: -0.02 | DZ3: -0.02 | EA3: -0.02 | EB3: -0.02 | EC3: -0.02 | ED3: -0.02 | EE3: -0.02 | EF3: -0.02 | EG3: -0.02 | EH3: -0.02 | EI3: -0.02 | EJ3: -0.02 | EK3: -0.02 | EL3: -0.02 | EM3: -0.02 | EN3: -0.02 | EO3: -0.02 | EP3: -0.02 | EQ3: -0.02 | ER3: -0.02 | ES3: -0.02 | ET3: -0.02 | EU3: -0.02 | EV3: -0.02 | EW3: -0.02 | EX3: -0.02 | EY3: -0.02 | EZ3: -0.02 | FA3: -0.02 | FB3: -0.02 | FC3: -0.02 | FD3: -0.02 | FE3: -0.02 | FF3: -0.02 | FG3: -0.02 | FH3: -0.02 | FI3: -0.02 | FJ3: -0.02 | FK3: -0.02 | FL3: -0.02 | FM3: -0.02 | FN3: -0.02 | FO3: -0.02 | FP3: -0.02 | FQ3: -0.02 | FR3: -0.02 | FS3: -0.02 | FT3: -0.02 | FU3: -0.02 | FV3: -0.02 | FW3: -0.02 | FX3: -0.02 | FY3: -0.02 | FZ3: -0.02 | GA3: -0.02 | GB3: -0.02 | GC3: -0.02 | GD3: -0.02 | GE3: -0.02 | GF3: -0.02 | GG3: -0.02 | GH3: -0.02 | GI3: -0.02 | GJ3: -0.02 | GK3: -0.02 | GL3: -0.02 | GM3: -0.02 | GN3: -0.02 | GO3: -0.02 | GP3: -0.02 | GQ3: -0.02 | GR3: -0.02 | GS3: -0.02 | GT3: -0.02 | GU3: -0.02 | GV3: -0.02 | GW3: -0.02 | GX3: -0.02 | GY3: -0.02 | GZ3: -0.02 | HA3: -0.02 | HB3: -0.02 | HC3: -0.02 | HD3: -0.02 | HE3: -0.02 | HF3: -0.02 | HG3: -0.02 | HH3: -0.02 | HI3: -0.02 | HJ3: -0.02 | HK3: -0.02 | HL3: -0.02 | HM3: -0.02 | HN3: -0.02 | HO3: -0.02 | HP3: -0.02 | HQ3: -0.02 | HR3: -0.02 | HS3: -0.02 | HT3: -0.02 | HU3: -0.02 | HV3: -0.02 | HW3: -0.02 | HX3: -0.02 | HY3: -0.02 | HZ3: -0.02 | IA3: -0.02 | IB3: -0.02 | IC3: -0.02 | ID3: -0.02 | IE3: -0.02 | IF3: -0.02 | IG3: -0.02 | IH3: -0.02 | II3: -0.02
A4: Reglementaire _SOT EVE | B4: No Parallel | C4: Short_up | D4: =EXP((-D1/12)/4)*2.5% -> 0.024484555 | E4: =EXP((-E1/12)/4)*2.5% -> 0.023979736 | F4: =EXP((-F1/12)/4)*2.5% -> 0.023485327 | G4: =EXP((-G1/12)/4)*2.5% -> 0.02300111 | H4: =EXP((-H1/12)/4)*2.5% -> 0.022526878 | I4: =EXP((-I1/12)/4)*2.5% -> 0.022062423 | J4: =EXP((-J1/12)/4)*2.5% -> 0.021607544 | K4: =EXP((-K1/12)/4)*2.5% -> 0.021162043 | ... II4: =EXP((-II1/12)/4)*2.5% -> 0.00016844867
A5: Reglementaire _SOT EVE | B5: No Parallel | C5: Short_down | D5: =-D4 -> -0.024484555 | E5: =-E4 -> -0.023979736 | F5: =-F4 -> -0.023485327 | G5: =-G4 -> -0.02300111 | H5: =-H4 -> -0.022526878 | I5: =-I4 -> -0.022062423 | J5: =-J4 -> -0.021607544 | K5: =-K4 -> -0.021162043 | ... II5: =-II4 -> -0.00016844867
A6: Reglementaire _SOT EVE | B6: No Parallel | C6: Steepener | D6: =-0.65*EXP((-D1/12)/4)*2.5%+0.9*(1-EXP((-D1/12)/4))*1% -> -0.0157294 | E6: =-0.65*EXP((-E1/12)/4)*2.5%+0.9*(1-EXP((-E1/12)/4))*1% -> -0.015219534 | F6: =-0.65*EXP((-F1/12)/4)*2.5%+0.9*(1-EXP((-F1/12)/4))*1% -> -0.01472018 | G6: =-0.65*EXP((-G1/12)/4)*2.5%+0.9*(1-EXP((-G1/12)/4))*1% -> -0.014231121 | H6: =-0.65*EXP((-H1/12)/4)*2.5%+0.9*(1-EXP((-H1/12)/4))*1% -> -0.013752146 | I6: =-0.65*EXP((-I1/12)/4)*2.5%+0.9*(1-EXP((-I1/12)/4))*1% -> -0.013283047 | J6: =-0.65*EXP((-J1/12)/4)*2.5%+0.9*(1-EXP((-J1/12)/4))*1% -> -0.012823619 | K6: =-0.65*EXP((-K1/12)/4)*2.5%+0.9*(1-EXP((-K1/12)/4))*1% -> -0.012373664 | ... II6: =-0.65*EXP((-II1/12)/4)*2.5%+0.9*(1-EXP((-II1/12)/4))*1% -> 0.0088298668
A7: Reglementaire _SOT EVE | B7: No Parallel | C7: Flattener | D7: =0.8*EXP((-D1/12)/4)*2.5%-0.6*(1-EXP((-D1/12)/4))*1% -> 0.019463937 | E7: =0.8*EXP((-E1/12)/4)*2.5%-0.6*(1-EXP((-E1/12)/4))*1% -> 0.018938926 | F7: =0.8*EXP((-F1/12)/4)*2.5%-0.6*(1-EXP((-F1/12)/4))*1% -> 0.01842474 | G7: =0.8*EXP((-G1/12)/4)*2.5%-0.6*(1-EXP((-G1/12)/4))*1% -> 0.017921155 | H7: =0.8*EXP((-H1/12)/4)*2.5%-0.6*(1-EXP((-H1/12)/4))*1% -> 0.017427953 | I7: =0.8*EXP((-I1/12)/4)*2.5%-0.6*(1-EXP((-I1/12)/4))*1% -> 0.016944919 | J7: =0.8*EXP((-J1/12)/4)*2.5%-0.6*(1-EXP((-J1/12)/4))*1% -> 0.016471845 | K7: =0.8*EXP((-K1/12)/4)*2.5%-0.6*(1-EXP((-K1/12)/4))*1% -> 0.016008525 | ... II7: =0.8*EXP((-II1/12)/4)*2.5%-0.6*(1-EXP((-II1/12)/4))*1% -> -0.0058248134
